Workbook
Name Slicer_Category: #N/A
Name Slicer_Payment_Mode: #N/A
Name Slicer_Status: #N/A
Name Slicer_Transaction_Type: #N/A
Name Slicer_Warehouse_ID: #N/A

Sheet Products_Master
A1: Product_ID | B1: Product_Name | C1: Category | D1: Sub_Category | E1: Brand | F1: Unit_of_Measure | G1: Standard_Cost | H1: Standard_Selling_Price | I1: Reorder_Level
A2: P1001 | B2: Dell Business Laptop 1 | C2: Laptops | D2: Business Laptop | E2: Dell | F2: PCS | G2: 45000 | H2: 54900 | I2: 10
A3: P1002 | B3: HP Business Laptop 2 | C3: Laptops | D3: Business Laptop | E3: HP | F3: PCS | G3: 45500 | H3: 55510 | I3: 10
A4: P1003 | B4: Lenovo Business Laptop 3 | C4: Laptops | D4: Business Laptop | E4: Lenovo | F4: PCS | G4: 46000 | H4: 56120 | I4: 10
A5: P1004 | B5: ASUS Business Laptop 4 | C5: Laptops | D5: Business Laptop | E5: ASUS | F5: PCS | G5: 46500 | H5: 56730 | I5: 10
A6: P1005 | B6: Acer Business Laptop 5 | C6: Laptops | D6: Business Laptop | E6: Acer | F6: PCS | G6: 47000 | H6: 57340 | I6: 10
A7: P1006 | B7: Dell Business Laptop 6 | C7: Laptops | D7: Business Laptop | E7: Dell | F7: PCS | G7: 46200 | H7: 56364 | I7: 10
A8: P1007 | B8: HP Business Laptop 7 | C8: Laptops | D8: Business Laptop | E8: HP | F8: PCS | G8: 46700 | H8: 56974 | I8: 10
A9: P1008 | B9: Lenovo Business Laptop 8 | C9: Laptops | D9: Business Laptop | E9: Lenovo | F9: PCS | G9: 47200 | H9: 57584 | I9: 10
A10: P1009 | B10: ASUS Business Laptop 9 | C10: Laptops | D10: Business Laptop | E10: ASUS | F10: PCS | G10: 47700 | H10: 58194 | I10: 10
A11: P1010 | B11: Acer Business Laptop 10 | C11: Laptops | D11: Business Laptop | E11: Acer | F11: PCS | G11: 48200 | H11: 58804 | I11: 10
A12: P1011 | B12: Dell Business Laptop 11 | C12: Laptops | D12: Business Laptop | E12: Dell | F12: PCS | G12: 47400 | H12: 57828 | I12: 10
A13: P1012 | B13: HP Business Laptop 12 | C13: Laptops | D13: Business Laptop | E13: HP | F13: PCS | G13: 47900 | H13: 58438 | I13: 10
... A101: P1100 | B101: Logitech Headset 6 | C101: Audio Devices | D101: Headset | E101: Logitech | F101: PCS | G101: 2000 | H101: 2440 | I101: 25

Sheet Suppliers_Masters
A1: Supplier_ID | B1: Supplier_Name | C1: City | D1: State | E1: Supplier_Rating | F1: Lead_Time_Days | G1: Contact_Person
A2: SUP001 | B2: Dell Technologies India | C2: Bengaluru | D2: Karnataka | E2: 4.8 | F2: 5 | G2: Rahul Sharma
A3: SUP002 | B3: HP India Pvt. Ltd. | C3: Mumbai | D3: Maharashtra | E3: 4.7 | F3: 6 | G3: Amit Verma
A4: SUP003 | B4: Lenovo India Pvt. Ltd. | C4: Bengaluru | D4: Karnataka | E4: 4.6 | F4: 7 | G4: Neha Singh
A5: SUP004 | B5: ASUS India | C5: Mumbai | D5: Maharashtra | E5: 4.5 | F5: 6 | G5: Rohan Patil
A6: SUP005 | B6: Acer India | C6: Chennai | D6: Tamil Nadu | E6: 4.4 | F6: 7 | G6: Priya Nair
A7: SUP006 | B7: Samsung India Electronics | C7: Noida | D7: Uttar Pradesh | E7: 4.8 | F7: 5 | G7: Ankit Gupta
A8: SUP007 | B8: Logitech India | C8: Pune | D8: Maharashtra | E8: 4.7 | F8: 4 | G8: Sneha Joshi
A9: SUP008 | B9: TP-Link India | C9: New Delhi | D9: Delhi | E9: 4.5 | F9: 5 | G9: Vikas Mehta
A10: SUP009 | B10: Cisco India | C10: Bengaluru | D10: Karnataka | E10: 4.9 | F10: 8 | G10: Karan Rao
A11: SUP010 | B11: Seagate India | C11: Pune | D11: Maharashtra | E11: 4.6 | F11: 6 | G11: Pooja Kulkarni
A12: SUP011 | B12: Western Digital India | C12: Mumbai | D12: Maharashtra | E12: 4.7 | F12: 5 | G12: Saurabh Jain
A13: SUP012 | B13: Canon India | C13: Gurugram | D13: Haryana | E13: 4.5 | F13: 6 | G13: Manish Yadav
... A21: SUP020 | B21: Zebronics India | C21: Chennai | D21: Tamil Nadu | E21: 4.3 | F21: 5 | G21: Kavya Reddy

Sheet Warehouses_Master
A1: Warehouse_ID | B1: Warehouse_Name | C1: City | D1: State | E1: Capacity_Units | F1: Warehouse_Type
A2: WH001 | B2: Pune Central Warehouse | C2: Pune | D2: Maharashtra | E2: 25000 | F2: Central
A3: WH002 | B3: Mumbai Distribution Center | C3: Mumbai | D3: Maharashtra | E3: 20000 | F3: Regional
A4: WH003 | B4: Nagpur Logistics Hub | C4: Nagpur | D4: Maharashtra | E4: 18000 | F4: Regional
A5: WH004 | B5: Hyderabad Fulfillment Center | C5: Hyderabad | D5: Telangana | E5: 22000 | F5: Regional
A6: WH005 | B6: Bengaluru South Warehouse | C6: Bengaluru | D6: Karnataka | E6: 30000 | F6: Central

Sheet Employees_Master
A1: Employee_ID | B1: Employee_Name | C1: Department | D1: Designation | E1: Location
A2: EMP001 | B2: Aarav Sharma | C2: Inventory | D2: Inventory Executive | E2: Pune
A3: EMP002 | B3: Neha Patil | C3: Inventory | D3: Inventory Executive | E3: Mumbai
A4: EMP003 | B4: Rahul Verma | C4: Inventory | D4: Warehouse Executive | E4: Nagpur
A5: EMP004 | B5: Priya Kulkarni | C5: Inventory | D5: Warehouse Executive | E5: Hyderabad
A6: EMP005 | B6: Rohan Deshmukh | C6: Procurement | D6: Procurement Executive | E6: Pune
A7: EMP006 | B7: Sneha Joshi | C7: Procurement | D7: Procurement Executive | E7: Mumbai
A8: EMP007 | B8: Karan Mehta | C8: Procurement | D8: Senior Procurement Executive | E8: Bengaluru
A9: EMP008 | B9: Anjali Singh | C9: Procurement | D9: Procurement Analyst | E9: Chennai
A10: EMP009 | B10: Vikram Rao | C10: Operations | D10: Operations Executive | E10: Pune
A11: EMP010 | B11: Pooja Nair | C11: Operations | D11: Operations Executive | E11: Nagpur
A12: EMP011 | B12: Aditya Jain | C12: Operations | D12: Operations Analyst | E12: Hyderabad
... A26: EMP025 | B26: Ishita Kapoor | C26: Logistics | D26: Logistics Manager | E26: Hyderabad

Sheet Calendar
A1: Date | B1: Day | C1: Day_Name | D1: Week_No | E1: Month_No | F1: Month_Name | G1: Quarter | H1: Year | I1: Is_Weekend | J1: Financial_Year | K1: Financial_Quarter
A2: 01-01-2025 | B2: 1 | C2: Wednesday | D2: 1 | E2: 1 | F2: January | G2: Q1 | H2: 2025 | I2: No | J2: FY 2024-25 | K2: FQ4
A3: 02-01-2025 | B3: 2 | C3: Thursday | D3: 1 | E3: 1 | F3: January | G3: Q1 | H3: 2025 | I3: No | J3: FY 2024-25 | K3: FQ4
A4: 03-01-2025 | B4: 3 | C4: Friday | D4: 1 | E4: 1 | F4: January | G4: Q1 | H4: 2025 | I4: No | J4: FY 2024-25 | K4: FQ4
A5: 04-01-2025 | B5: 4 | C5: Saturday | D5: 1 | E5: 1 | F5: January | G5: Q1 | H5: 2025 | I5: Yes | J5: FY 2024-25 | K5: FQ4
A6: 05-01-2025 | B6: 5 | C6: Sunday | D6: 1 | E6: 1 | F6: January | G6: Q1 | H6: 2025 | I6: Yes | J6: FY 2024-25 | K6: FQ4
A7: 06-01-2025 | B7: 6 | C7: Monday | D7: 2 | E7: 1 | F7: January | G7: Q1 | H7: 2025 | I7: No | J7: FY 2024-25 | K7: FQ4
A8: 07-01-2025 | B8: 7 | C8: Tuesday | D8: 2 | E8: 1 | F8: January | G8: Q1 | H8: 2025 | I8: No | J8: FY 2024-25 | K8: FQ4
A9: 08-01-2025 | B9: 8 | C9: Wednesday | D9: 2 | E9: 1 | F9: January | G9: Q1 | H9: 2025 | I9: No | J9: FY 2024-25 | K9: FQ4
A10: 09-01-2025 | B10: 9 | C10: Thursday | D10: 2 | E10: 1 | F10: January | G10: Q1 | H10: 2025 | I10: No | J10: FY 2024-25 | K10: FQ4
A11: 10-01-2025 | B11: 10 | C11: Friday | D11: 2 | E11: 1 | F11: January | G11: Q1 | H11: 2025 | I11: No | J11: FY 2024-25 | K11: FQ4
A12: 11-01-2025 | B12: 11 | C12: Saturday | D12: 2 | E12: 1 | F12: January | G12: Q1 | H12: 2025 | I12: Yes | J12: FY 2024-25 | K12: FQ4
A13: 12-01-2025 | B13: 12 | C13: Sunday | D13: 2 | E13: 1 | F13: January | G13: Q1 | H13: 2025 | I13: Yes | J13: FY 2024-25 | K13: FQ4
... A731: 31-12-2026 | B731: 31 | C731: Thursday | D731: 53 | E731: 12 | F731: December | G731: Q4 | H731: 2026 | I731: No | J731: FY 2026-27 | K731: FQ3

Sheet Sales_Trend
A1: Transaction_Type | B1: (All)
A3: Row Labels | B3: Sum of Total_Value
A4: 2025 | B4: 1889750745
A5: Jan | B5: 154422626
A6: Feb | B6: 163187939
A7: Mar | B7: 177401501
A8: Apr | B8: 150856288
A9: May | B9: 163442278
A10: Jun | B10: 162467525
A11: Jul | B11: 159248916
A12: Aug | B12: 146717528
A13: Sep | B13: 169887116
A14: Oct | B14: 156348491
A15: Nov | B15: 141817415
... A30: Grand Total | B30: 3815308401

Sheet Category Wise Sales 
A1: Transaction_Type | B1: (All)
A3: Row Labels | B3: Sum of Total_Value
A4: Electronics | B4: 1967152262
A5: Furniture | B5: 757068446
A6: Stationery | B6: 1091087693
A7: Grand Total | B7: 3815308401

Sheet Sales by Warehouse
A1: Transaction_Type | B1: (All)
A3: Row Labels | B3: Sum of Total_Value
B4: 407530
A5: W01 | B5: 803827680
A6: W02 | B6: 749372598
A7: W03 | B7: 831714835
A8: W04 | B8: 691056091
A9: W05 | B9: 738929667
A10: Grand Total | B10: 3815308401

Sheet Transaction Analysis
A3: Row Labels | B3: Sum of Total_Value
A4: Adjustment | B4: 891142236
A5: Purchase | B5: 900263468
A6: Return | B6: 1005857263
A7: Sale | B7: 1018045434
A8: Grand Total | B8: 3815308401

Sheet Top 10 sales Product
A1: Transaction_Type | B1: (All)
A3: Row Labels | B3: Sum of Total_Value
A4: Office Chair | B4: 436176948
A5: Monitor | B5: 429459556
A6: Mouse | B6: 422105054
A7: Keyboard | B7: 402900066
A8: File Folder | B8: 368003447
A9: Notebook | B9: 367594825
A10: Laptop | B10: 362486633
A11: Pen | B11: 355489421
A12: Printer | B12: 350200953
A13: Office Desk | B13: 320891498
A14: Grand Total | B14: 3815308401

Sheet Stocks Analysis
A3: Row Labels | B3: Sum of Stock_Before | C3: Sum of Stock_After
B4: 280 | C4: 363
A5: W01 | B5: 164331 | C5: 170261
A6: W02 | B6: 157559 | C6: 166060
A7: W03 | B7: 177201 | C7: 185014
A8: W04 | B8: 149041 | C8: 155566
A9: W05 | B9: 163441 | C9: 171581
A10: Grand Total | B10: 811853 | C10: 848845

Sheet Payment Mode Analysis 
A1: Transaction_Type | B1: (All)
A3: Row Labels | B3: Sum of Total_Value
A4: Card | B4: 930970668
A5: Cash | B5: 946545687
A6: Credit | B6: 981068753
A7: UPI | B7: 956723293
A8: Grand Total | B8: 3815308401

Sheet Inventory_Transaction
A1: Transaction_ID | B1: Transaction_Date | C1: Product_ID | D1: Product_Name | E1: Category | F1: Sub_Category | G1: Supplier_ID | H1: Warehouse_ID | I1: Transaction_Type | J1: Quantity | K1: Unit_Price | L1: Total_Value | M1: Stock_Before | N1: Stock_After | O1: Employee_ID | P1: Customer_ID | Q1: Payment_Mode | R1: Status | S1: Remarks | T1: Duplicates | U1: Miossing Transaction | V1: Invalid Product | W1: Invalid Supplier | X1: Invalid Warehouse | Y1: Invalid Employee | Z1: Stocks check | AA1: Total value check | AB1: Stock_After Check | AC1: Quantity_Check | AD1: Stock_Status
A2: T00001 | B2: 45800 | C2: P002 | D2: Keyboard | E2: Electronics | F2: Accessories | G2: S004 | H2: W05 | I2: Purchase | J2: 95 | K2: 18074 | L2: 1717030 | M2: 175 | N2: 270 | O2: E003 | Q2: Credit | R2: Completed | S2: Regular Transaction | T2: =IF(COUNTIF(T4,Q14)>1,"Duplicate","OK") -> OK | U2: =IF(Table2[[#This Row],[Transaction_ID]]="","Missing","OK") -> OK | V2: =IF(COUNTIF(Table2[[#This Row],[Product_ID]],Table2[[#This Row],[Product_ID]])=0,"Invalid Product","OK") -> OK | W2: =IF(COUNTIF(Table2[[#This Row],[Supplier_ID]],Table2[[#This Row],[Supplier_ID]])=0,"Invalid Supplier","OK") -> OK | X2: =IF(COUNTIF(Table2[[#This Row],[Warehouse_ID]],Table2[[#This Row],[Warehouse_ID]])=0,"Invalid Warehouse","OK") -> OK | Y2: =IF(COUNTIF(Table2[[#This Row],[Employee_ID]],Table2[[#This Row],[Employee_ID]])=0,"Invalid Employee","OK") -> OK | Z2: =IF(Table2[[#This Row],[Stock_After]]=Table2[[#This Row],[Stock_After]]+Table2[[#This Row],[Stock_After]]-Table2[[#This Row],[Stock_After]]-Table2[[#This Row],[Stock_After]]+Table2[[#This Row],[Stock_After]],"OK","Error") -> OK | AA2: =IF(ROUND(Table2[[#This Row],[Total_Value]],2)=ROUND(Table2[[#This Row],[Quantity]]*Table2[[#This Row],[Unit_Price]],2),"OK","Error") -> OK | AB2: =IF(Table2[[#This Row],[Transaction_Type]]="Purchase", IF(Table2[[#This Row],[Stock_After]]=Table2[[#This Row],[Stock_Before]]+Table2[[#This Row],[Quantity]], "OK", "Error"), IF(Table2[[#This Row],[Transaction_Type]]="Return", IF(Table2[[#This Row],[Stock_After]]=Table2[[#This Row],[Stock_Before]]+Table2[[#This Row],[Quantity]], "OK", "Error"), IF(Table2[[#This Row],[Transaction_Type]]="Sale", IF(Table2[[#This Row],[Stock_After]]=MAX(0, Table2[[#This Row],[Stock_Before]]-Table2[[#This Row],[Quantity]]), "OK", "Error"), IF(Table2[[#This Row],[Transaction_Type]]="Adjustment", IF(Table2[[#This Row],[Stock_After]]>=0, "OK", "Error"), "Check")))) -> OK | AC2: =IF(AND(Table2[[#This Row],[Quantity]]>=0,Table2[[#This Row],[Unit_Price]]>=0),"OK","Error") -> OK | AD2: =IF(Table2[[#This Row],[Stock_After]]=0,"Stock-Out",IF(Table2[[#This Row],[Stock_After]]<=10,"Low Stock","Healthy")) -> Healthy
A3: T00002 | B3: 46274 | C3: P001 | D3: Laptop | E3: Electronics | F3: Computers | G3: S001 | H3: W05 | I3: Purchase | J3: 12 | K3: 14378 | L3: 172536 | M3: 169 | N3: 181 | O3: E007 | Q3: Credit | R3: Pending | S3: Regular Transaction | T3: =IF(COUNTIF(T5,Q15)>1,"Duplicate","OK") -> OK | U3: =IF(Table2[[#This Row],[Transaction_ID]]="","Missing","OK") -> OK | V3: =IF(COUNTIF(Table2[[#This Row],[Product_ID]],Table2[[#This Row],[Product_ID]])=0,"Invalid Product","OK") -> OK | W3: =IF(COUNTIF(Table2[[#This Row],[Supplier_ID]],Table2[[#This Row],[Supplier_ID]])=0,"Invalid Supplier","OK") -> OK | X3: =IF(COUNTIF(Table2[[#This Row],[Warehouse_ID]],Table2[[#This Row],[Warehouse_ID]])=0,"Invalid Warehouse","OK") -> OK | Y3: =IF(COUNTIF(Table2[[#This Row],[Employee_ID]],Table2[[#This Row],[Employee_ID]])=0,"Invalid Employee","OK") -> OK | Z3: =IF(Table2[[#This Row],[Stock_After]]=Table2[[#This Row],[Stock_After]]+Table2[[#This Row],[Stock_After]]-Table2[[#This Row],[Stock_After]]-Table2[[#This Row],[Stock_After]]+Table2[[#This Row],[Stock_After]],"OK","Error") -> OK | AA3: =IF(ROUND(Table2[[#This Row],[Total_Value]],2)=ROUND(Table2[[#This Row],[Quantity]]*Table2[[#This Row],[Unit_Price]],2),"OK","Error") -> OK | AB3: =IF(Table2[[#This Row],[Transaction_Type]]="Purchase", IF(Table2[[#This Row],[Stock_After]]=Table2[[#This Row],[Stock_Before]]+Table2[[#This Row],[Quantity]], "OK", "Error"), IF(Table2[[#This Row],[Transaction_Type]]="Return", IF(Table2[[#This Row],[Stock_After]]=Table2[[#This Row],[Stock_Before]]+Table2[[#This Row],[Quantity]], "OK", "Error"), IF(Table2[[#This Row],[Transaction_Type]]="Sale", IF(Table2[[#This Row],[Stock_After]]=MAX(0, Table2[[#This Row],[Stock_Before]]-Table2[[#This Row],[Quantity]]), "OK", "Error"), IF(Table2[[#This Row],[Transaction_Type]]="Adjustment", IF(Table2[[#This Row],[Stock_After]]>=0, "OK", "Error"), "Check")))) -> OK | AC3: =IF(AND(Table2[[#This Row],[Quantity]]>=0,Table2[[#This Row],[Unit_Price]]>=0),"OK","Error") -> OK | AD3: =IF(Table2[[#This Row],[Stock_After]]=0,"Stock-Out",IF(Table2[[#This Row],[Stock_After]]<=10,"Low Stock","Healthy")) -> Healthy
A4: T00003 | B4: 46372 | C4: P004 | D4: Monitor | E4: Electronics | F4: Displays | G4: S014 | H4: W03 | I4: Adjustment | J4: 76 | K4: 18281 | L4: 1389356 | M4: 464 | N4: 388 | O4: E009 | Q4: Card | R4: Completed | S4: Regular Transaction | T4: =IF(COUNTIF(T6,Q16)>1,"Duplicate","OK") -> OK | U4: =IF(Table2[[#This Row],[Transaction_ID]]="","Missing","OK") -> OK | V4: =IF(COUNTIF(Table2[[#This Row],[Product_ID]],Table2[[#This Row],[Product_ID]])=0,"Invalid Product","OK") -> OK | W4: =IF(COUNTIF(Table2[[#This Row],[Supplier_ID]],Table2[[#This Row],[Supplier_ID]])=0,"Invalid Supplier","OK") -> OK | X4: =IF(COUNTIF(Table2[[#This Row],[Warehouse_ID]],Table2[[#This Row],[Warehouse_ID]])=0,"Invalid Warehouse","OK") -> OK | Y4: =IF(COUNTIF(Table2[[#This Row],[Employee_ID]],Table2[[#This Row],[Employee_ID]])=0,"Invalid Employee","OK") -> OK | Z4: =IF(Table2[[#This Row],[Stock_After]]=Table2[[#This Row],[Stock_After]]+Table2[[#This Row],[Stock_After]]-Table2[[#This Row],[Stock_After]]-Table2[[#This Row],[Stock_After]]+Table2[[#This Row],[Stock_After]],"OK","Error") -> OK | AA4: =IF(ROUND(Table2[[#This Row],[Total_Value]],2)=ROUND(Table2[[#This Row],[Quantity]]*Table2[[#This Row],[Unit_Price]],2),"OK","Error") -> OK | AB4: =IF(Table2[[#This Row],[Transaction_Type]]="Purchase", IF(Table2[[#This Row],[Stock_After]]=Table2[[#This Row],[Stock_Before]]+Table2[[#This Row],[Quantity]], "OK", "Error"), IF(Table2[[#This Row],[Transaction_Type]]="Return", IF(Table2[[#This Row],[Stock_After]]=Table2[[#This Row],[Stock_Before]]+Table2[[#This Row],[Quantity]], "OK", "Error"), IF(Table2[[#This Row],[Transaction_Type]]="Sale", IF(Table2[[#This Row],[Stock_After]]=MAX(0, Table2[[#This Row],[Stock_Before]]-Table2[[#This Row],[Quantity]]), "OK", "Error"), IF(Table2[[#This Row],[Transaction_Type]]="Adjustment", IF(Table2[[#This Row],[Stock_After]]>=0, "OK", "Error"), "Check")))) -> OK | AC4: =IF(AND(Table2[[#This Row],[Quantity]]>=0,Table2[[#This Row],[Unit_Price]]>=0),"OK","Error") -> OK | AD4: =IF(Table2[[#This Row],[Stock_After]]=0,"Stock-Out",IF(Table2[[#This Row],[Stock_After]]<=10,"Low Stock","Healthy")) -> Healthy
A5: T00004 | B5: 46025 | C5: P004 | D5: Monitor | E5: Electronics | F5: Displays | G5: S012 | H5: W05 | I5: Return | J5: 14 | K5: 6128 | L5: 85792 | M5: 244 | N5: 258 | O5: E009 | Q5: Cash | R5: Completed | S5: Regular Transaction | T5: =IF(COUNTIF(T7,Q17)>1,"Duplicate","OK") -> OK | U5: =IF(Table2[[#This Row],[Transaction_ID]]="","Missing","OK") -> OK | V5: =IF(COUNTIF(Table2[[#This Row],[Product_ID]],Table2[[#This Row],[Product_ID]])=0,"Invalid Product","OK") -> OK | W5: =IF(COUNTIF(Table2[[#This Row],[Supplier_ID]],Table2[[#This Row],[Supplier_ID]])=0,"Invalid Supplier","OK") -> OK | X5: =IF(COUNTIF(Table2[[#This Row],[Warehouse_ID]],Table2[[#This Row],[Warehouse_ID]])=0,"Invalid Warehouse","OK") -> OK | Y5: =IF(COUNTIF(Table2[[#This Row],[Employee_ID]],Table2[[#This Row],[Employee_ID]])=0,"Invalid Employee","OK") -> OK | Z5: =IF(Table2[[#This Row],[Stock_After]]=Table2[[#This Row],[Stock_After]]+Table2[[#This Row],[Stock_After]]-Table2[[#This Row],[Stock_After]]-Table2[[#This Row],[Stock_After]]+Table2[[#This Row],[Stock_After]],"OK","Error") -> OK | AA5: =IF(ROUND(Table2[[#This Row],[Total_Value]],2)=ROUND(Table2[[#This Row],[Quantity]]*Table2[[#This Row],[Unit_Price]],2),"OK","Error") -> OK | AB5: =IF(Table2[[#This Row],[Transaction_Type]]="Purchase", IF(Table2[[#This Row],[Stock_After]]=Table2[[#This Row],[Stock_Before]]+Table2[[#This Row],[Quantity]], "OK", "Error"), IF(Table2[[#This Row],[Transaction_Type]]="Return", IF(Table2[[#This Row],[Stock_After]]=Table2[[#This Row],[Stock_Before]]+Table2[[#This Row],[Quantity]], "OK", "Error"), IF(Table2[[#This Row],[Transaction_Type]]="Sale", IF(Table2[[#This Row],[Stock_After]]=MAX(0, Table2[[#This Row],[Stock_Before]]-Table2[[#This Row],[Quantity]]), "OK", "Error"), IF(Table2[[#This Row],[Transaction_Type]]="Adjustment", IF(Table2[[#This Row],[Stock_After]]>=0, "OK", "Error"), "Check")))) -> OK | AC5: =IF(AND(Table2[[#This Row],[Quantity]]>=0,Table2[[#This Row],[Unit_Price]]>=0),"OK","Error") -> OK | AD5: =IF(Table2[[#This Row],[Stock_After]]=0,"Stock-Out",IF(Table2[[#This Row],[Stock_After]]<=10,"Low Stock","Healthy")) -> Healthy
A6: T00005 | B6: 46301 | C6: P008 | D6: Notebook | E6: Stationery | F6: Books | G6: S020 | H6: W03 | I6: Purchase | J6: 49 | K6: 5214 | L6: 255486 | M6: 332 | N6: 381 | O6: E019 | Q6: Card | R6: Approved | S6: Regular Transaction | T6: =IF(COUNTIF(T8,Q18)>1,"Duplicate","OK") -> OK | U6: =IF(Table2[[#This Row],[Transaction_ID]]="","Missing","OK") -> OK | V6: =IF(COUNTIF(Table2[[#This Row],[Product_ID]],Table2[[#This Row],[Product_ID]])=0,"Invalid Product","OK") -> OK | W6: =IF(COUNTIF(Table2[[#This Row],[Supplier_ID]],Table2[[#This Row],[Supplier_ID]])=0,"Invalid Supplier","OK") -> OK | X6: =IF(COUNTIF(Table2[[#This Row],[Warehouse_ID]],Table2[[#This Row],[Warehouse_ID]])=0,"Invalid Warehouse","OK") -> OK | Y6: =IF(COUNTIF(Table2[[#This Row],[Employee_ID]],Table2[[#This Row],[Employee_ID]])=0,"Invalid Employee","OK") -> OK | Z6: =IF(Table2[[#This Row],[Stock_After]]=Table2[[#This Row],[Stock_After]]+Table2[[#This Row],[Stock_After]]-Table2[[#This Row],[Stock_After]]-Table2[[#This Row],[Stock_After]]+Table2[[#This Row],[Stock_After]],"OK","Error") -> OK | AA6: =IF(ROUND(Table2[[#This Row],[Total_Value]],2)=ROUND(Table2[[#This Row],[Quantity]]*Table2[[#This Row],[Unit_Price]],2),"OK","Error") -> OK | AB6: =IF(Table2[[#This Row],[Transaction_Type]]="Purchase", IF(Table2[[#This Row],[Stock_After]]=Table2[[#This Row],[Stock_Before]]+Table2[[#This Row],[Quantity]], "OK", "Error"), IF(Table2[[#This Row],[Transaction_Type]]="Return", IF(Table2[[#This Row],[Stock_After]]=Table2[[#This Row],[Stock_Before]]+Table2[[#This Row],[Quantity]], "OK", "Error"), IF(Table2[[#This Row],[Transaction_Type]]="Sale", IF(Table2[[#This Row],[Stock_After]]=MAX(0, Table2[[#This Row],[Stock_Before]]-Table2[[#This Row],[Quantity]]), "OK", "Error"), IF(Table2[[#This Row],[Transaction_Type]]="Adjustment", IF(Table2[[#This Row],[Stock_After]]>=0, "OK", "Error"), "Check")))) -> OK | AC6: =IF(AND(Table2[[#This Row],[Quantity]]>=0,Table2[[#This Row],[Unit_Price]]>=0),"OK","Error") -> OK | AD6: =IF(Table2[[#This Row],[Stock_After]]=0,"Stock-Out",IF(Table2[[#This Row],[Stock_After]]<=10,"Low Stock","Healthy")) -> Healthy
A7: T00006 | B7: 45739 | C7: P002 | D7: Keyboard | E7: Electronics | F7: Accessories | G7: S008 | H7: W01 | I7: Purchase | J7: 85 | K7: 14985 | L7: 1273725 | M7: 445 | N7: 530 | O7: E013 | Q7: UPI | R7: Approved | S7: Regular Transaction | T7: =IF(COUNTIF(T9,Q19)>1,"Duplicate","OK") -> OK | U7: =IF(Table2[[#This Row],[Transaction_ID]]="","Missing","OK") -> OK | V7: =IF(COUNTIF(Table2[[#This Row],[Product_ID]],Table2[[#This Row],[Product_ID]])=0,"Invalid Product","OK") -> OK | W7: =IF(COUNTIF(Table2[[#This Row],[Supplier_ID]],Table2[[#This Row],[Supplier_ID]])=0,"Invalid Supplier","OK") -> OK | X7: =IF(COUNTIF(Table2[[#This Row],[Warehouse_ID]],Table2[[#This Row],[Warehouse_ID]])=0,"Invalid Warehouse","OK") -> OK | Y7: =IF(COUNTIF(Table2[[#This Row],[Employee_ID]],Table2[[#This Row],[Employee_ID]])=0,"Invalid Employee","OK") -> OK | Z7: =IF(Table2[[#This Row],[Stock_After]]=Table2[[#This Row],[Stock_After]]+Table2[[#This Row],[Stock_After]]-Table2[[#This Row],[Stock_After]]-Table2[[#This Row],[Stock_After]]+Table2[[#This Row],[Stock_After]],"OK","Error") -> OK | AA7: =IF(ROUND(Table2[[#This Row],[Total_Value]],2)=ROUND(Table2[[#This Row],[Quantity]]*Table2[[#This Row],[Unit_Price]],2),"OK","Error") -> OK | AB7: =IF(Table2[[#This Row],[Transaction_Type]]="Purchase", IF(Table2[[#This Row],[Stock_After]]=Table2[[#This Row],[Stock_Before]]+Table2[[#This Row],[Quantity]], "OK", "Error"), IF(Table2[[#This Row],[Transaction_Type]]="Return", IF(Table2[[#This Row],[Stock_After]]=Table2[[#This Row],[Stock_Before]]+Table2[[#This Row],[Quantity]], "OK", "Error"), IF(Table2[[#This Row],[Transaction_Type]]="Sale", IF(Table2[[#This Row],[Stock_After]]=MAX(0, Table2[[#This Row],[Stock_Before]]-Table2[[#This Row],[Quantity]]), "OK", "Error"), IF(Table2[[#This Row],[Transaction_Type]]="Adjustment", IF(Table2[[#This Row],[Stock_After]]>=0, "OK", "Error"), "Check")))) -> OK | AC7: =IF(AND(Table2[[#This Row],[Quantity]]>=0,Table2[[#This Row],[Unit_Price]]>=0),"OK","Error") -> OK | AD7: =IF(Table2[[#This Row],[Stock_After]]=0,"Stock-Out",IF(Table2[[#This Row],[Stock_After]]<=10,"Low Stock","Healthy")) -> Healthy
A8: T00007 | B8: 46344 | C8: P008 | D8: Notebook | E8: Stationery | F8: Books | G8: S009 | H8: W01 | I8: Return | J8: 21 | K8: 24310 | L8: 510510 | M8: 231 | N8: 252 | O8: E020 | Q8: Card | R8: Completed | S8: Regular Transaction | T8: =IF(COUNTIF(T10,Q20)>1,"Duplicate","OK") -> OK | U8: =IF(Table2[[#This Row],[Transaction_ID]]="","Missing","OK") -> OK | V8: =IF(COUNTIF(Table2[[#This Row],[Product_ID]],Table2[[#This Row],[Product_ID]])=0,"Invalid Product","OK") -> OK | W8: =IF(COUNTIF(Table2[[#This Row],[Supplier_ID]],Table2[[#This Row],[Supplier_ID]])=0,"Invalid Supplier","OK") -> OK | X8: =IF(COUNTIF(Table2[[#This Row],[Warehouse_ID]],Table2[[#This Row],[Warehouse_ID]])=0,"Invalid Warehouse","OK") -> OK | Y8: =IF(COUNTIF(Table2[[#This Row],[Employee_ID]],Table2[[#This Row],[Employee_ID]])=0,"Invalid Employee","OK") -> OK | Z8: =IF(Table2[[#This Row],[Stock_After]]=Table2[[#This Row],[Stock_After]]+Table2[[#This Row],[Stock_After]]-Table2[[#This Row],[Stock_After]]-Table2[[#This Row],[Stock_After]]+Table2[[#This Row],[Stock_After]],"OK","Error") -> OK | AA8: =IF(ROUND(Table2[[#This Row],[Total_Value]],2)=ROUND(Table2[[#This Row],[Quantity]]*Table2[[#This Row],[Unit_Price]],2),"OK","Error") -> OK | AB8: =IF(Table2[[#This Row],[Transaction_Type]]="Purchase", IF(Table2[[#This Row],[Stock_After]]=Table2[[#This Row],[Stock_Before]]+Table2[[#This Row],[Quantity]], "OK", "Error"), IF(Table2[[#This Row],[Transaction_Type]]="Return", IF(Table2[[#This Row],[Stock_After]]=Table2[[#This Row],[Stock_Before]]+Table2[[#This Row],[Quantity]], "OK", "Error"), IF(Table2[[#This Row],[Transaction_Type]]="Sale", IF(Table2[[#This Row],[Stock_After]]=MAX(0, Table2[[#This Row],[Stock_Before]]-Table2[[#This Row],[Quantity]]), "OK", "Error"), IF(Table2[[#This Row],[Transaction_Type]]="Adjustment", IF(Table2[[#This Row],[Stock_After]]>=0, "OK", "Error"), "Check")))) -> OK | AC8: =IF(AND(Table2[[#This Row],[Quantity]]>=0,Table2[[#This Row],[Unit_Price]]>=0),"OK","Error") -> OK | AD8: =IF(Table2[[#This Row],[Stock_After]]=0,"Stock-Out",IF(Table2[[#This Row],[Stock_After]]<=10,"Low Stock","Healthy")) -> Healthy
A9: T00008 | B9: 46362 | C9: P009 | D9: Pen | E9: Stationery | F9: Writing | G9: S018 | H9: W02 | I9: Sale | J9: 21 | K9: 30344 | L9: 637224 | M9: 244 | N9: 223 | O9: E011 | P9: C0139 | Q9: Cash | R9: Pending | S9: Regular Transaction | T9: =IF(COUNTIF(T11,Q21)>1,"Duplicate","OK") -> OK | U9: =IF(Table2[[#This Row],[Transaction_ID]]="","Missing","OK") -> OK | V9: =IF(COUNTIF(Table2[[#This Row],[Product_ID]],Table2[[#This Row],[Product_ID]])=0,"Invalid Product","OK") -> OK | W9: =IF(COUNTIF(Table2[[#This Row],[Supplier_ID]],Table2[[#This Row],[Supplier_ID]])=0,"Invalid Supplier","OK") -> OK | X9: =IF(COUNTIF(Table2[[#This Row],[Warehouse_ID]],Table2[[#This Row],[Warehouse_ID]])=0,"Invalid Warehouse","OK") -> OK | Y9: =IF(COUNTIF(Table2[[#This Row],[Employee_ID]],Table2[[#This Row],[Employee_ID]])=0,"Invalid Employee","OK") -> OK | Z9: =IF(Table2[[#This Row],[Stock_After]]=Table2[[#This Row],[Stock_After]]+Table2[[#This Row],[Stock_After]]-Table2[[#This Row],[Stock_After]]-Table2[[#This Row],[Stock_After]]+Table2[[#This Row],[Stock_After]],"OK","Error") -> OK | AA9: =IF(ROUND(Table2[[#This Row],[Total_Value]],2)=ROUND(Table2[[#This Row],[Quantity]]*Table2[[#This Row],[Unit_Price]],2),"OK","Error") -> OK | AB9: =IF(Table2[[#This Row],[Transaction_Type]]="Purchase", IF(Table2[[#This Row],[Stock_After]]=Table2[[#This Row],[Stock_Before]]+Table2[[#This Row],[Quantity]], "OK", "Error"), IF(Table2[[#This Row],[Transaction_Type]]="Return", IF(Table2[[#This Row],[Stock_After]]=Table2[[#This Row],[Stock_Before]]+Table2[[#This Row],[Quantity]], "OK", "Error"), IF(Table2[[#This Row],[Transaction_Type]]="Sale", IF(Table2[[#This Row],[Stock_After]]=MAX(0, Table2[[#This Row],[Stock_Before]]-Table2[[#This Row],[Quantity]]), "OK", "Error"), IF(Table2[[#This Row],[Transaction_Type]]="Adjustment", IF(Table2[[#This Row],[Stock_After]]>=0, "OK", "Error"), "Check")))) -> OK | AC9: =IF(AND(Table2[[#This Row],[Quantity]]>=0,Table2[[#This Row],[Unit_Price]]>=0),"OK","Error") -> OK | AD9: =IF(Table2[[#This Row],[Stock_After]]=0,"Stock-Out",IF(Table2[[#This Row],[Stock_After]]<=10,"Low Stock","Healthy")) -> Healthy
A10: T00009 | B10: 45874 | C10: P004 | D10: Monitor | E10: Electronics | F10: Displays | G10: S019 | H10: W03 | I10: Purchase | J10: 41 | K10: 26340 | L10: 1079940 | M10: 187 | N10: 228 | O10: E007 | Q10: Credit | R10: Completed | S10: Regular Transaction | T10: =IF(COUNTIF(T12,Q22)>1,"Duplicate","OK") -> OK | U10: =IF(Table2[[#This Row],[Transaction_ID]]="","Missing","OK") -> OK | V10: =IF(COUNTIF(Table2[[#This Row],[Product_ID]],Table2[[#This Row],[Product_ID]])=0,"Invalid Product","OK") -> OK | W10: =IF(COUNTIF(Table2[[#This Row],[Supplier_ID]],Table2[[#This Row],[Supplier_ID]])=0,"Invalid Supplier","OK") -> OK | X10: =IF(COUNTIF(Table2[[#This Row],[Warehouse_ID]],Table2[[#This Row],[Warehouse_ID]])=0,"Invalid Warehouse","OK") -> OK | Y10: =IF(COUNTIF(Table2[[#This Row],[Employee_ID]],Table2[[#This Row],[Employee_ID]])=0,"Invalid Employee","OK") -> OK | Z10: =IF(Table2[[#This Row],[Stock_After]]=Table2[[#This Row],[Stock_After]]+Table2[[#This Row],[Stock_After]]-Table2[[#This Row],[Stock_After]]-Table2[[#This Row],[Stock_After]]+Table2[[#This Row],[Stock_After]],"OK","Error") -> OK | AA10: =IF(ROUND(Table2[[#This Row],[Total_Value]],2)=ROUND(Table2[[#This Row],[Quantity]]*Table2[[#This Row],[Unit_Price]],2),"OK","Error") -> OK | AB10: =IF(Table2[[#This Row],[Transaction_Type]]="Purchase", IF(Table2[[#This Row],[Stock_After]]=Table2[[#This Row],[Stock_Before]]+Table2[[#This Row],[Quantity]], "OK", "Error"), IF(Table2[[#This Row],[Transaction_Type]]="Return", IF(Table2[[#This Row],[Stock_After]]=Table2[[#This Row],[Stock_Before]]+Table2[[#This Row],[Quantity]], "OK", "Error"), IF(Table2[[#This Row],[Transaction_Type]]="Sale", IF(Table2[[#This Row],[Stock_After]]=MAX(0, Table2[[#This Row],[Stock_Before]]-Table2[[#This Row],[Quantity]]), "OK", "Error"), IF(Table2[[#This Row],[Transaction_Type]]="Adjustment", IF(Table2[[#This Row],[Stock_After]]>=0, "OK", "Error"), "Check")))) -> OK | AC10: =IF(AND(Table2[[#This Row],[Quantity]]>=0,Table2[[#This Row],[Unit_Price]]>=0),"OK","Error") -> OK | AD10: =IF(Table2[[#This Row],[Stock_After]]=0,"Stock-Out",IF(Table2[[#This Row],[Stock_After]]<=10,"Low Stock","Healthy")) -> Healthy
A11: T00010 | B11: 46232 | C11: P007 | D11: Office Desk | E11: Furniture | F11: Desks | G11: S018 | H11: W03 | I11: Adjustment | J11: 19 | K11: 17409 | L11: 330771 | M11: 121 | N11: 102 | O11: E019 | Q11: Credit | R11: Pending | S11: Regular Transaction | T11: =IF(COUNTIF(T13,Q23)>1,"Duplicate","OK") -> OK | U11: =IF(Table2[[#This Row],[Transaction_ID]]="","Missing","OK") -> OK | V11: =IF(COUNTIF(Table2[[#This Row],[Product_ID]],Table2[[#This Row],[Product_ID]])=0,"Invalid Product","OK") -> OK | W11: =IF(COUNTIF(Table2[[#This Row],[Supplier_ID]],Table2[[#This Row],[Supplier_ID]])=0,"Invalid Supplier","OK") -> OK | X11: =IF(COUNTIF(Table2[[#This Row],[Warehouse_ID]],Table2[[#This Row],[Warehouse_ID]])=0,"Invalid Warehouse","OK") -> OK | Y11: =IF(COUNTIF(Table2[[#This Row],[Employee_ID]],Table2[[#This Row],[Employee_ID]])=0,"Invalid Employee","OK") -> OK | Z11: =IF(Table2[[#This Row],[Stock_After]]=Table2[[#This Row],[Stock_After]]+Table2[[#This Row],[Stock_After]]-Table2[[#This Row],[Stock_After]]-Table2[[#This Row],[Stock_After]]+Table2[[#This Row],[Stock_After]],"OK","Error") -> OK | AA11: =IF(ROUND(Table2[[#This Row],[Total_Value]],2)=ROUND(Table2[[#This Row],[Quantity]]*Table2[[#This Row],[Unit_Price]],2),"OK","Error") -> OK | AB11: =IF(Table2[[#This Row],[Transaction_Type]]="Purchase", IF(Table2[[#This Row],[Stock_After]]=Table2[[#This Row],[Stock_Before]]+Table2[[#This Row],[Quantity]], "OK", "Error"), IF(Table2[[#This Row],[Transaction_Type]]="Return", IF(Table2[[#This Row],[Stock_After]]=Table2[[#This Row],[Stock_Before]]+Table2[[#This Row],[Quantity]], "OK", "Error"), IF(Table2[[#This Row],[Transaction_Type]]="Sale", IF(Table2[[#This Row],[Stock_After]]=MAX(0, Table2[[#This Row],[Stock_Before]]-Table2[[#This Row],[Quantity]]), "OK", "Error"), IF(Table2[[#This Row],[Transaction_Type]]="Adjustment", IF(Table2[[#This Row],[Stock_After]]>=0, "OK", "Error"), "Check")))) -> OK | AC11: =IF(AND(Table2[[#This Row],[Quantity]]>=0,Table2[[#This Row],[Unit_Price]]>=0),"OK","Error") -> OK | AD11: =IF(Table2[[#This Row],[Stock_After]]=0,"Stock-Out",IF(Table2[[#This Row],[Stock_After]]<=10,"Low Stock","Healthy")) -> Healthy
A12: T00011 | B12: 45706 | C12: P010 | D12: File Folder | E12: Stationery | F12: Files | G12: S004 | H12: W02 | I12: Adjustment | J12: 47 | K12: 14423 | L12: 677881 | M12: 120 | N12: 167 | O12: E006 | Q12: Credit | R12: Completed | S12: Regular Transaction | T12: =IF(COUNTIF(T14,Q24)>1,"Duplicate","OK") -> OK | U12: =IF(Table2[[#This Row],[Transaction_ID]]="","Missing","OK") -> OK | V12: =IF(COUNTIF(Table2[[#This Row],[Product_ID]],Table2[[#This Row],[Product_ID]])=0,"Invalid Product","OK") -> OK | W12: =IF(COUNTIF(Table2[[#This Row],[Supplier_ID]],Table2[[#This Row],[Supplier_ID]])=0,"Invalid Supplier","OK") -> OK | X12: =IF(COUNTIF(Table2[[#This Row],[Warehouse_ID]],Table2[[#This Row],[Warehouse_ID]])=0,"Invalid Warehouse","OK") -> OK | Y12: =IF(COUNTIF(Table2[[#This Row],[Employee_ID]],Table2[[#This Row],[Employee_ID]])=0,"Invalid Employee","OK") -> OK | Z12: =IF(Table2[[#This Row],[Stock_After]]=Table2[[#This Row],[Stock_After]]+Table2[[#This Row],[Stock_After]]-Table2[[#This Row],[Stock_After]]-Table2[[#This Row],[Stock_After]]+Table2[[#This Row],[Stock_After]],"OK","Error") -> OK | AA12: =IF(ROUND(Table2[[#This Row],[Total_Value]],2)=ROUND(Table2[[#This Row],[Quantity]]*Table2[[#This Row],[Unit_Price]],2),"OK","Error") -> OK | AB12: =IF(Table2[[#This Row],[Transaction_Type]]="Purchase", IF(Table2[[#This Row],[Stock_After]]=Table2[[#This Row],[Stock_Before]]+Table2[[#This Row],[Quantity]], "OK", "Error"), IF(Table2[[#This Row],[Transaction_Type]]="Return", IF(Table2[[#This Row],[Stock_After]]=Table2[[#This Row],[Stock_Before]]+Table2[[#This Row],[Quantity]], "OK", "Error"), IF(Table2[[#This Row],[Transaction_Type]]="Sale", IF(Table2[[#This Row],[Stock_After]]=MAX(0, Table2[[#This Row],[Stock_Before]]-Table2[[#This Row],[Quantity]]), "OK", "Error"), IF(Table2[[#This Row],[Transaction_Type]]="Adjustment", IF(Table2[[#This Row],[Stock_After]]>=0, "OK", "Error"), "Check")))) -> OK | AC12: =IF(AND(Table2[[#This Row],[Quantity]]>=0,Table2[[#This Row],[Unit_Price]]>=0),"OK","Error") -> OK | AD12: =IF(Table2[[#This Row],[Stock_After]]=0,"Stock-Out",IF(Table2[[#This Row],[Stock_After]]<=10,"Low Stock","Healthy")) -> Healthy
A13: T00012 | B13: 46199 | C13: P010 | D13: File Folder | E13: Stationery | F13: Files | G13: S009 | H13: W05 | I13: Purchase | J13: 50 | K13: 25059 | L13: 1252950 | M13: 355 | N13: 405 | O13: E001 | Q13: Cash | R13: Approved | S13: Regular Transaction | T13: =IF(COUNTIF(T15,Q25)>1,"Duplicate","OK") -> OK | U13: =IF(Table2[[#This Row],[Transaction_ID]]="","Missing","OK") -> OK | V13: =IF(COUNTIF(Table2[[#This Row],[Product_ID]],Table2[[#This Row],[Product_ID]])=0,"Invalid Product","OK") -> OK | W13: =IF(COUNTIF(Table2[[#This Row],[Supplier_ID]],Table2[[#This Row],[Supplier_ID]])=0,"Invalid Supplier","OK") -> OK | X13: =IF(COUNTIF(Table2[[#This Row],[Warehouse_ID]],Table2[[#This Row],[Warehouse_ID]])=0,"Invalid Warehouse","OK") -> OK | Y13: =IF(COUNTIF(Table2[[#This Row],[Employee_ID]],Table2[[#This Row],[Employee_ID]])=0,"Invalid Employee","OK") -> OK | Z13: =IF(Table2[[#This Row],[Stock_After]]=Table2[[#This Row],[Stock_After]]+Table2[[#This Row],[Stock_After]]-Table2[[#This Row],[Stock_After]]-Table2[[#This Row],[Stock_After]]+Table2[[#This Row],[Stock_After]],"OK","Error") -> OK | AA13: =IF(ROUND(Table2[[#This Row],[Total_Value]],2)=ROUND(Table2[[#This Row],[Quantity]]*Table2[[#This Row],[Unit_Price]],2),"OK","Error") -> OK | AB13: =IF(Table2[[#This Row],[Transaction_Type]]="Purchase", IF(Table2[[#This Row],[Stock_After]]=Table2[[#This Row],[Stock_Before]]+Table2[[#This Row],[Quantity]], "OK", "Error"), IF(Table2[[#This Row],[Transaction_Type]]="Return", IF(Table2[[#This Row],[Stock_After]]=Table2[[#This Row],[Stock_Before]]+Table2[[#This Row],[Quantity]], "OK", "Error"), IF(Table2[[#This Row],[Transaction_Type]]="Sale", IF(Table2[[#This Row],[Stock_After]]=MAX(0, Table2[[#This Row],[Stock_Before]]-Table2[[#This Row],[Quantity]]), "OK", "Error"), IF(Table2[[#This Row],[Transaction_Type]]="Adjustment", IF(Table2[[#This Row],[Stock_After]]>=0, "OK", "Error"), "Check")))) -> OK | AC13: =IF(AND(Table2[[#This Row],[Quantity]]>=0,Table2[[#This Row],[Unit_Price]]>=0),"OK","Error") -> OK | AD13: =IF(Table2[[#This Row],[Stock_After]]=0,"Stock-Out",IF(Table2[[#This Row],[Stock_After]]<=10,"Low Stock","Healthy")) -> Healthy
A14: T00013 | B14: 45958 | C14: P009 | D14: Pen | E14: Stationery | F14: Writing | G14: S014 | H14: W02 | I14: Return | J14: 99 | K14: 42056 | L14: 4163544 | M14: 224 | N14: 323 | O14: E015 | Q14: Cash | R14: Completed | S14: Regular Transaction | T14: =IF(COUNTIF(T16,Q26)>1,"Duplicate","OK") -> OK | U14: =IF(Table2[[#This Row],[Transaction_ID]]="","Missing","OK") -> OK | V14: =IF(COUNTIF(Table2[[#This Row],[Product_ID]],Table2[[#This Row],[Product_ID]])=0,"Invalid Product","OK") -> OK | W14: =IF(COUNTIF(Table2[[#This Row],[Supplier_ID]],Table2[[#This Row],[Supplier_ID]])=0,"Invalid Supplier","OK") -> OK | X14: =IF(COUNTIF(Table2[[#This Row],[Warehouse_ID]],Table2[[#This Row],[Warehouse_ID]])=0,"Invalid Warehouse","OK") -> OK | Y14: =IF(COUNTIF(Table2[[#This Row],[Employee_ID]],Table2[[#This Row],[Employee_ID]])=0,"Invalid Employee","OK") -> OK | Z14: =IF(Table2[[#This Row],[Stock_After]]=Table2[[#This Row],[Stock_After]]+Table2[[#This Row],[Stock_After]]-Table2[[#This Row],[Stock_After]]-Table2[[#This Row],[Stock_After]]+Table2[[#This Row],[Stock_After]],"OK","Error") -> OK | AA14: =IF(ROUND(Table2[[#This Row],[Total_Value]],2)=ROUND(Table2[[#This Row],[Quantity]]*Table2[[#This Row],[Unit_Price]],2),"OK","Error") -> OK | AB14: =IF(Table2[[#This Row],[Transaction_Type]]="Purchase", IF(Table2[[#This Row],[Stock_After]]=Table2[[#This Row],[Stock_Before]]+Table2[[#This Row],[Quantity]], "OK", "Error"), IF(Table2[[#This Row],[Transaction_Type]]="Return", IF(Table2[[#This Row],[Stock_After]]=Table2[[#This Row],[Stock_Before]]+Table2[[#This Row],[Quantity]], "OK", "Error"), IF(Table2[[#This Row],[Transaction_Type]]="Sale", IF(Table2[[#This Row],[Stock_After]]=MAX(0, Table2[[#This Row],[Stock_Before]]-Table2[[#This Row],[Quantity]]), "OK", "Error"), IF(Table2[[#This Row],[Transaction_Type]]="Adjustment", IF(Table2[[#This Row],[Stock_After]]>=0, "OK", "Error"), "Check")))) -> OK | AC14: =IF(AND(Table2[[#This Row],[Quantity]]>=0,Table2[[#This Row],[Unit_Price]]>=0),"OK","Error") -> OK | AD14: =IF(Table2[[#This Row],[Stock_After]]=0,"Stock-Out",IF(Table2[[#This Row],[Stock_After]]<=10,"Low Stock","Healthy")) -> Healthy
A15: T00014 | B15: 46312 | C15: P005 | D15: Printer | E15: Electronics | F15: Printers | G15: S017 | H15: W05 | I15: Sale | J15: 65 | K15: 7023 | L15: 456495 | M15: 495 | N15: 430 | O15: E007 | P15: C0321 | Q15: Card | R15: Approved | S15: Regular Transaction | T15: =IF(COUNTIF(T17,Q27)>1,"Duplicate","OK") -> OK | U15: =IF(Table2[[#This Row],[Transaction_ID]]="","Missing","OK") -> OK | V15: =IF(COUNTIF(Table2[[#This Row],[Product_ID]],Table2[[#This Row],[Product_ID]])=0,"Invalid Product","OK") -> OK | W15: =IF(COUNTIF(Table2[[#This Row],[Supplier_ID]],Table2[[#This Row],[Supplier_ID]])=0,"Invalid Supplier","OK") -> OK | X15: =IF(COUNTIF(Table2[[#This Row],[Warehouse_ID]],Table2[[#This Row],[Warehouse_ID]])=0,"Invalid Warehouse","OK") -> OK | Y15: =IF(COUNTIF(Table2[[#This Row],[Employee_ID]],Table2[[#This Row],[Employee_ID]])=0,"Invalid Employee","OK") -> OK | Z15: =IF(Table2[[#This Row],[Stock_After]]=Table2[[#This Row],[Stock_After]]+Table2[[#This Row],[Stock_After]]-Table2[[#This Row],[Stock_After]]-Table2[[#This Row],[Stock_After]]+Table2[[#This Row],[Stock_After]],"OK","Error") -> OK | AA15: =IF(ROUND(Table2[[#This Row],[Total_Value]],2)=ROUND(Table2[[#This Row],[Quantity]]*Table2[[#This Row],[Unit_Price]],2),"OK","Error") -> OK | AB15: =IF(Table2[[#This Row],[Transaction_Type]]="Purchase", IF(Table2[[#This Row],[Stock_After]]=Table2[[#This Row],[Stock_Before]]+Table2[[#This Row],[Quantity]], "OK", "Error"), IF(Table2[[#This Row],[Transaction_Type]]="Return", IF(Table2[[#This Row],[Stock_After]]=Table2[[#This Row],[Stock_Before]]+Table2[[#This Row],[Quantity]], "OK", "Error"), IF(Table2[[#This Row],[Transaction_Type]]="Sale", IF(Table2[[#This Row],[Stock_After]]=MAX(0, Table2[[#This Row],[Stock_Before]]-Table2[[#This Row],[Quantity]]), "OK", "Error"), IF(Table2[[#This Row],[Transaction_Type]]="Adjustment", IF(Table2[[#This Row],[Stock_After]]>=0, "OK", "Error"), "Check")))) -> OK | AC15: =IF(AND(Table2[[#This Row],[Quantity]]>=0,Table2[[#This Row],[Unit_Price]]>=0),"OK","Error") -> OK | AD15: =IF(Table2[[#This Row],[Stock_After]]=0,"Stock-Out",IF(Table2[[#This Row],[Stock_After]]<=10,"Low Stock","Healthy")) -> Healthy
A16: T00015 | B16: 46158 | C16: P006 | D16: Office Chair | E16: Furniture | F16: Chairs | G16: S001 | H16: W01 | I16: Sale | J16: 70 | K16: 34807 | L16: 2436490 | M16: 50 | N16: 0 | O16: E012 | P16: C0307 | Q16: UPI | R16: Approved | S16: Regular Transaction | T16: =IF(COUNTIF(T18,Q28)>1,"Duplicate","OK") -> OK | U16: =IF(Table2[[#This Row],[Transaction_ID]]="","Missing","OK") -> OK | V16: =IF(COUNTIF(Table2[[#This Row],[Product_ID]],Table2[[#This Row],[Product_ID]])=0,"Invalid Product","OK") -> OK | W16: =IF(COUNTIF(Table2[[#This Row],[Supplier_ID]],Table2[[#This Row],[Supplier_ID]])=0,"Invalid Supplier","OK") -> OK | X16: =IF(COUNTIF(Table2[[#This Row],[Warehouse_ID]],Table2[[#This Row],[Warehouse_ID]])=0,"Invalid Warehouse","OK") -> OK | Y16: =IF(COUNTIF(Table2[[#This Row],[Employee_ID]],Table2[[#This Row],[Employee_ID]])=0,"Invalid Employee","OK") -> OK | Z16: =IF(Table2[[#This Row],[Stock_After]]=Table2[[#This Row],[Stock_After]]+Table2[[#This Row],[Stock_After]]-Table2[[#This Row],[Stock_After]]-Table2[[#This Row],[Stock_After]]+Table2[[#This Row],[Stock_After]],"OK","Error") -> OK | AA16: =IF(ROUND(Table2[[#This Row],[Total_Value]],2)=ROUND(Table2[[#This Row],[Quantity]]*Table2[[#This Row],[Unit_Price]],2),"OK","Error") -> OK | AB16: =IF(Table2[[#This Row],[Transaction_Type]]="Purchase", IF(Table2[[#This Row],[Stock_After]]=Table2[[#This Row],[Stock_Before]]+Table2[[#This Row],[Quantity]], "OK", "Error"), IF(Table2[[#This Row],[Transaction_Type]]="Return", IF(Table2[[#This Row],[Stock_After]]=Table2[[#This Row],[Stock_Before]]+Table2[[#This Row],[Quantity]], "OK", "Error"), IF(Table2[[#This Row],[Transaction_Type]]="Sale", IF(Table2[[#This Row],[Stock_After]]=MAX(0, Table2[[#This Row],[Stock_Before]]-Table2[[#This Row],[Quantity]]), "OK", "Error"), IF(Table2[[#This Row],[Transaction_Type]]="Adjustment", IF(Table2[[#This Row],[Stock_After]]>=0, "OK", "Error"), "Check")))) -> OK | AC16: =IF(AND(Table2[[#This Row],[Quantity]]>=0,Table2[[#This Row],[Unit_Price]]>=0),"OK","Error") -> OK | AD16: =IF(Table2[[#This Row],[Stock_After]]=0,"Stock-Out",IF(Table2[[#This Row],[Stock_After]]<=10,"Low Stock","Healthy")) -> Stock-Out
A17: T00016 | B17: 46155 | C17: P004 | D17: Monitor | E17: Electronics | F17: Displays | G17: S003 | H17: W05 | I17: Purchase | J17: 31 | K17: 37232 | L17: 1154192 | M17: 90 | N17: 121 | O17: E005 | Q17: Card | R17: Completed | S17: Regular Transaction | T17: =IF(COUNTIF(T19,Q29)>1,"Duplicate","OK") -> OK | U17: =IF(Table2[[#This Row],[Transaction_ID]]="","Missing","OK") -> OK | V17: =IF(COUNTIF(Table2[[#This Row],[Product_ID]],Table2[[#This Row],[Product_ID]])=0,"Invalid Product","OK") -> OK | W17: =IF(COUNTIF(Table2[[#This Row],[Supplier_ID]],Table2[[#This Row],[Supplier_ID]])=0,"Invalid Supplier","OK") -> OK | X17: =IF(COUNTIF(Table2[[#This Row],[Warehouse_ID]],Table2[[#This Row],[Warehouse_ID]])=0,"Invalid Warehouse","OK") -> OK | Y17: =IF(COUNTIF(Table2[[#This Row],[Employee_ID]],Table2[[#This Row],[Employee_ID]])=0,"Invalid Employee","OK") -> OK | Z17: =IF(Table2[[#This Row],[Stock_After]]=Table2[[#This Row],[Stock_After]]+Table2[[#This Row],[Stock_After]]-Table2[[#This Row],[Stock_After]]-Table2[[#This Row],[Stock_After]]+Table2[[#This Row],[Stock_After]],"OK","Error") -> OK | AA17: =IF(ROUND(Table2[[#This Row],[Total_Value]],2)=ROUND(Table2[[#This Row],[Quantity]]*Table2[[#This Row],[Unit_Price]],2),"OK","Error") -> OK | AB17: =IF(Table2[[#This Row],[Transaction_Type]]="Purchase", IF(Table2[[#This Row],[Stock_After]]=Table2[[#This Row],[Stock_Before]]+Table2[[#This Row],[Quantity]], "OK", "Error"), IF(Table2[[#This Row],[Transaction_Type]]="Return", IF(Table2[[#This Row],[Stock_After]]=Table2[[#This Row],[Stock_Before]]+Table2[[#This Row],[Quantity]], "OK", "Error"), IF(Table2[[#This Row],[Transaction_Type]]="Sale", IF(Table2[[#This Row],[Stock_After]]=MAX(0, Table2[[#This Row],[Stock_Before]]-Table2[[#This Row],[Quantity]]), "OK", "Error"), IF(Table2[[#This Row],[Transaction_Type]]="Adjustment", IF(Table2[[#This Row],[Stock_After]]>=0, "OK", "Error"), "Check")))) -> OK | AC17: =IF(AND(Table2[[#This Row],[Quantity]]>=0,Table2[[#This Row],[Unit_Price]]>=0),"OK","Error") -> OK | AD17: =IF(Table2[[#This Row],[Stock_After]]=0,"Stock-Out",IF(Table2[[#This Row],[Stock_After]]<=10,"Low Stock","Healthy")) -> Healthy
A18: T00017 | B18: 45874 | C18: P008 | D18: Notebook | E18: Stationery | F18: Books | G18: S018 | H18: W02 | I18: Sale | J18: 34 | K18: 34631 | L18: 1177454 | M18: 496 | N18: 462 | O18: E010 | P18: C0311 | Q18: Credit | R18: Approved | S18: Regular Transaction | T18: =IF(COUNTIF(T20,Q30)>1,"Duplicate","OK") -> OK | U18: =IF(Table2[[#This Row],[Transaction_ID]]="","Missing","OK") -> OK | V18: =IF(COUNTIF(Table2[[#This Row],[Product_ID]],Table2[[#This Row],[Product_ID]])=0,"Invalid Product","OK") -> OK | W18: =IF(COUNTIF(Table2[[#This Row],[Supplier_ID]],Table2[[#This Row],[Supplier_ID]])=0,"Invalid Supplier","OK") -> OK | X18: =IF(COUNTIF(Table2[[#This Row],[Warehouse_ID]],Table2[[#This Row],[Warehouse_ID]])=0,"Invalid Warehouse","OK") -> OK | Y18: =IF(COUNTIF(Table2[[#This Row],[Employee_ID]],Table2[[#This Row],[Employee_ID]])=0,"Invalid Employee","OK") -> OK | Z18: =IF(Table2[[#This Row],[Stock_After]]=Table2[[#This Row],[Stock_After]]+Table2[[#This Row],[Stock_After]]-Table2[[#This Row],[Stock_After]]-Table2[[#This Row],[Stock_After]]+Table2[[#This Row],[Stock_After]],"OK","Error") -> OK | AA18: =IF(ROUND(Table2[[#This Row],[Total_Value]],2)=ROUND(Table2[[#This Row],[Quantity]]*Table2[[#This Row],[Unit_Price]],2),"OK","Error") -> OK | AB18: =IF(Table2[[#This Row],[Transaction_Type]]="Purchase", IF(Table2[[#This Row],[Stock_After]]=Table2[[#This Row],[Stock_Before]]+Table2[[#This Row],[Quantity]], "OK", "Error"), IF(Table2[[#This Row],[Transaction_Type]]="Return", IF(Table2[[#This Row],[Stock_After]]=Table2[[#This Row],[Stock_Before]]+Table2[[#This Row],[Quantity]], "OK", "Error"), IF(Table2[[#This Row],[Transaction_Type]]="Sale", IF(Table2[[#This Row],[Stock_After]]=MAX(0, Table2[[#This Row],[Stock_Before]]-Table2[[#This Row],[Quantity]]), "OK", "Error"), IF(Table2[[#This Row],[Transaction_Type]]="Adjustment", IF(Table2[[#This Row],[Stock_After]]>=0, "OK", "Error"), "Check")))) -> OK | AC18: =IF(AND(Table2[[#This Row],[Quantity]]>=0,Table2[[#This Row],[Unit_Price]]>=0),"OK","Error") -> OK | AD18: =IF(Table2[[#This Row],[Stock_After]]=0,"Stock-Out",IF(Table2[[#This Row],[Stock_After]]<=10,"Low Stock","Healthy")) -> Healthy
A19: T00018 | B19: 45723 | C19: P006 | D19: Office Chair | E19: Furniture | F19: Chairs | G19: S011 | H19: W01 | I19: Adjustment | J19: 67 | K19: 29638 | L19: 1985746 | M19: 111 | N19: 44 | O19: E019 | Q19: Card | R19: Completed | S19: Regular Transaction | T19: =IF(COUNTIF(T21,Q31)>1,"Duplicate","OK") -> OK | U19: =IF(Table2[[#This Row],[Transaction_ID]]="","Missing","OK") -> OK | V19: =IF(COUNTIF(Table2[[#This Row],[Product_ID]],Table2[[#This Row],[Product_ID]])=0,"Invalid Product","OK") -> OK | W19: =IF(COUNTIF(Table2[[#This Row],[Supplier_ID]],Table2[[#This Row],[Supplier_ID]])=0,"Invalid Supplier","OK") -> OK | X19: =IF(COUNTIF(Table2[[#This Row],[Warehouse_ID]],Table2[[#This Row],[Warehouse_ID]])=0,"Invalid Warehouse","OK") -> OK | Y19: =IF(COUNTIF(Table2[[#This Row],[Employee_ID]],Table2[[#This Row],[Employee_ID]])=0,"Invalid Employee","OK") -> OK | Z19: =IF(Table2[[#This Row],[Stock_After]]=Table2[[#This Row],[Stock_After]]+Table2[[#This Row],[Stock_After]]-Table2[[#This Row],[Stock_After]]-Table2[[#This Row],[Stock_After]]+Table2[[#This Row],[Stock_After]],"OK","Error") -> OK | AA19: =IF(ROUND(Table2[[#This Row],[Total_Value]],2)=ROUND(Table2[[#This Row],[Quantity]]*Table2[[#This Row],[Unit_Price]],2),"OK","Error") -> OK | AB19: =IF(Table2[[#This Row],[Transaction_Type]]="Purchase", IF(Table2[[#This Row],[Stock_After]]=Table2[[#This Row],[Stock_Before]]+Table2[[#This Row],[Quantity]], "OK", "Error"), IF(Table2[[#This Row],[Transaction_Type]]="Return", IF(Table2[[#This Row],[Stock_After]]=Table2[[#This Row],[Stock_Before]]+Table2[[#This Row],[Quantity]], "OK", "Error"), IF(Table2[[#This Row],[Transaction_Type]]="Sale", IF(Table2[[#This Row],[Stock_After]]=MAX(0, Table2[[#This Row],[Stock_Before]]-Table2[[#This Row],[Quantity]]), "OK", "Error"), IF(Table2[[#This Row],[Transaction_Type]]="Adjustment", IF(Table2[[#This Row],[Stock_After]]>=0, "OK", "Error"), "Check")))) -> OK | AC19: =IF(AND(Table2[[#This Row],[Quantity]]>=0,Table2[[#This Row],[Unit_Price]]>=0),"OK","Error") -> OK | AD19: =IF(Table2[[#This Row],[Stock_After]]=0,"Stock-Out",IF(Table2[[#This Row],[Stock_After]]<=10,"Low Stock","Healthy")) -> Healthy
A20: T00019 | B20: 45892 | C20: P010 | D20: File Folder | E20: Stationery | F20: Files | G20: S003 | H20: W01 | I20: Sale | J20: 1 | K20: 4702 | L20: 4702 | M20: 412 | N20: 411 | O20: E011 | P20: C0324 | Q20: Cash | R20: Completed | S20: Regular Transaction | T20: =IF(COUNTIF(T22,Q32)>1,"Duplicate","OK") -> OK | U20: =IF(Table2[[#This Row],[Transaction_ID]]="","Missing","OK") -> OK | V20: =IF(COUNTIF(Table2[[#This Row],[Product_ID]],Table2[[#This Row],[Product_ID]])=0,"Invalid Product","OK") -> OK | W20: =IF(COUNTIF(Table2[[#This Row],[Supplier_ID]],Table2[[#This Row],[Supplier_ID]])=0,"Invalid Supplier","OK") -> OK | X20: =IF(COUNTIF(Table2[[#This Row],[Warehouse_ID]],Table2[[#This Row],[Warehouse_ID]])=0,"Invalid Warehouse","OK") -> OK | Y20: =IF(COUNTIF(Table2[[#This Row],[Employee_ID]],Table2[[#This Row],[Employee_ID]])=0,"Invalid Employee","OK") -> OK | Z20: =IF(Table2[[#This Row],[Stock_After]]=Table2[[#This Row],[Stock_After]]+Table2[[#This Row],[Stock_After]]-Table2[[#This Row],[Stock_After]]-Table2[[#This Row],[Stock_After]]+Table2[[#This Row],[Stock_After]],"OK","Error") -> OK | AA20: =IF(ROUND(Table2[[#This Row],[Total_Value]],2)=ROUND(Table2[[#This Row],[Quantity]]*Table2[[#This Row],[Unit_Price]],2),"OK","Error") -> OK | AB20: =IF(Table2[[#This Row],[Transaction_Type]]="Purchase", IF(Table2[[#This Row],[Stock_After]]=Table2[[#This Row],[Stock_Before]]+Table2[[#This Row],[Quantity]], "OK", "Error"), IF(Table2[[#This Row],[Transaction_Type]]="Return", IF(Table2[[#This Row],[Stock_After]]=Table2[[#This Row],[Stock_Before]]+Table2[[#This Row],[Quantity]], "OK", "Error"), IF(Table2[[#This Row],[Transaction_Type]]="Sale", IF(Table2[[#This Row],[Stock_After]]=MAX(0, Table2[[#This Row],[Stock_Before]]-Table2[[#This Row],[Quantity]]), "OK", "Error"), IF(Table2[[#This Row],[Transaction_Type]]="Adjustment", IF(Table2[[#This Row],[Stock_After]]>=0, "OK", "Error"), "Check")))) -> OK | AC20: =IF(AND(Table2[[#This Row],[Quantity]]>=0,Table2[[#This Row],[Unit_Price]]>=0),"OK","Error") -> OK | AD20: =IF(Table2[[#This Row],[Stock_After]]=0,"Stock-Out",IF(Table2[[#This Row],[Stock_After]]<=10,"Low Stock","Healthy")) -> Healthy
A21: T00020 | B21: 45793 | C21: P009 | D21: Pen | E21: Stationery | F21: Writing | G21: S019 | H21: W05 | I21: Sale | J21: 36 | K21: 43892 | L21: 1580112 | M21: 298 | N21: 262 | O21: E016 | P21: C0110 | Q21: Card | R21: Pending | S21: Regular Transaction | T21: =IF(COUNTIF(T23,Q33)>1,"Duplicate","OK") -> OK | U21: =IF(Table2[[#This Row],[Transaction_ID]]="","Missing","OK") -> OK | V21: =IF(COUNTIF(Table2[[#This Row],[Product_ID]],Table2[[#This Row],[Product_ID]])=0,"Invalid Product","OK") -> OK | W21: =IF(COUNTIF(Table2[[#This Row],[Supplier_ID]],Table2[[#This Row],[Supplier_ID]])=0,"Invalid Supplier","OK") -> OK | X21: =IF(COUNTIF(Table2[[#This Row],[Warehouse_ID]],Table2[[#This Row],[Warehouse_ID]])=0,"Invalid Warehouse","OK") -> OK | Y21: =IF(COUNTIF(Table2[[#This Row],[Employee_ID]],Table2[[#This Row],[Employee_ID]])=0,"Invalid Employee","OK") -> OK | Z21: =IF(Table2[[#This Row],[Stock_After]]=Table2[[#This Row],[Stock_After]]+Table2[[#This Row],[Stock_After]]-Table2[[#This Row],[Stock_After]]-Table2[[#This Row],[Stock_After]]+Table2[[#This Row],[Stock_After]],"OK","Error") -> OK | AA21: =IF(ROUND(Table2[[#This Row],[Total_Value]],2)=ROUND(Table2[[#This Row],[Quantity]]*Table2[[#This Row],[Unit_Price]],2),"OK","Error") -> OK | AB21: =IF(Table2[[#This Row],[Transaction_Type]]="Purchase", IF(Table2[[#This Row],[Stock_After]]=Table2[[#This Row],[Stock_Before]]+Table2[[#This Row],[Quantity]], "OK", "Error"), IF(Table2[[#This Row],[Transaction_Type]]="Return", IF(Table2[[#This Row],[Stock_After]]=Table2[[#This Row],[Stock_Before]]+Table2[[#This Row],[Quantity]], "OK", "Error"), IF(Table2[[#This Row],[Transaction_Type]]="Sale", IF(Table2[[#This Row],[Stock_After]]=MAX(0, Table2[[#This Row],[Stock_Before]]-Table2[[#This Row],[Quantity]]), "OK", "Error"), IF(Table2[[#This Row],[Transaction_Type]]="Adjustment", IF(Table2[[#This Row],[Stock_After]]>=0, "OK", "Error"), "Check")))) -> OK | AC21: =IF(AND(Table2[[#This Row],[Quantity]]>=0,Table2[[#This Row],[Unit_Price]]>=0),"OK","Error") -> OK | AD21: =IF(Table2[[#This Row],[Stock_After]]=0,"Stock-Out",IF(Table2[[#This Row],[Stock_After]]<=10,"Low Stock","Healthy")) -> Healthy
A22: T00021 | B22: 46091 | C22: P008 | D22: Notebook | E22: Stationery | F22: Books | G22: S014 | H22: W04 | I22: Adjustment | J22: 25 | K22: 6231 | L22: 155775 | M22: 99 | N22: 124 | O22: E002 | Q22: Cash | R22: Approved | S22: Regular Transaction | T22: =IF(COUNTIF(T24,Q34)>1,"Duplicate","OK") -> OK | U22: =IF(Table2[[#This Row],[Transaction_ID]]="","Missing","OK") -> OK | V22: =IF(COUNTIF(Table2[[#This Row],[Product_ID]],Table2[[#This Row],[Product_ID]])=0,"Invalid Product","OK") -> OK | W22: =IF(COUNTIF(Table2[[#This Row],[Supplier_ID]],Table2[[#This Row],[Supplier_ID]])=0,"Invalid Supplier","OK") -> OK | X22: =IF(COUNTIF(Table2[[#This Row],[Warehouse_ID]],Table2[[#This Row],[Warehouse_ID]])=0,"Invalid Warehouse","OK") -> OK | Y22: =IF(COUNTIF(Table2[[#This Row],[Employee_ID]],Table2[[#This Row],[Employee_ID]])=0,"Invalid Employee","OK") -> OK | Z22: =IF(Table2[[#This Row],[Stock_After]]=Table2[[#This Row],[Stock_After]]+Table2[[#This Row],[Stock_After]]-Table2[[#This Row],[Stock_After]]-Table2[[#This Row],[Stock_After]]+Table2[[#This Row],[Stock_After]],"OK","Error") -> OK | AA22: =IF(ROUND(Table2[[#This Row],[Total_Value]],2)=ROUND(Table2[[#This Row],[Quantity]]*Table2[[#This Row],[Unit_Price]],2),"OK","Error") -> OK | AB22: =IF(Table2[[#This Row],[Transaction_Type]]="Purchase", IF(Table2[[#This Row],[Stock_After]]=Table2[[#This Row],[Stock_Before]]+Table2[[#This Row],[Quantity]], "OK", "Error"), IF(Table2[[#This Row],[Transaction_Type]]="Return", IF(Table2[[#This Row],[Stock_After]]=Table2[[#This Row],[Stock_Before]]+Table2[[#This Row],[Quantity]], "OK", "Error"), IF(Table2[[#This Row],[Transaction_Type]]="Sale", IF(Table2[[#This Row],[Stock_After]]=MAX(0, Table2[[#This Row],[Stock_Before]]-Table2[[#This Row],[Quantity]]), "OK", "Error"), IF(Table2[[#This Row],[Transaction_Type]]="Adjustment", IF(Table2[[#This Row],[Stock_After]]>=0, "OK", "Error"), "Check")))) -> OK | AC22: =IF(AND(Table2[[#This Row],[Quantity]]>=0,Table2[[#This Row],[Unit_Price]]>=0),"OK","Error") -> OK | AD22: =IF(Table2[[#This Row],[Stock_After]]=0,"Stock-Out",IF(Table2[[#This Row],[Stock_After]]<=10,"Low Stock","Healthy")) -> Healthy
A23: T00022 | B23: 45854 | C23: P001 | D23: Laptop | E23: Electronics | F23: Computers | G23: S007 | H23: W05 | I23: Adjustment | J23: 94 | K23: 22286 | L23: 2094884 | M23: 459 | N23: 365 | O23: E015 | Q23: Card | R23: Completed | S23: Regular Transaction | T23: =IF(COUNTIF(T25,Q35)>1,"Duplicate","OK") -> OK | U23: =IF(Table2[[#This Row],[Transaction_ID]]="","Missing","OK") -> OK | V23: =IF(COUNTIF(Table2[[#This Row],[Product_ID]],Table2[[#This Row],[Product_ID]])=0,"Invalid Product","OK") -> OK | W23: =IF(COUNTIF(Table2[[#This Row],[Supplier_ID]],Table2[[#This Row],[Supplier_ID]])=0,"Invalid Supplier","OK") -> OK | X23: =IF(COUNTIF(Table2[[#This Row],[Warehouse_ID]],Table2[[#This Row],[Warehouse_ID]])=0,"Invalid Warehouse","OK") -> OK | Y23: =IF(COUNTIF(Table2[[#This Row],[Employee_ID]],Table2[[#This Row],[Employee_ID]])=0,"Invalid Employee","OK") -> OK | Z23: =IF(Table2[[#This Row],[Stock_After]]=Table2[[#This Row],[Stock_After]]+Table2[[#This Row],[Stock_After]]-Table2[[#This Row],[Stock_After]]-Table2[[#This Row],[Stock_After]]+Table2[[#This Row],[Stock_After]],"OK","Error") -> OK | AA23: =IF(ROUND(Table2[[#This Row],[Total_Value]],2)=ROUND(Table2[[#This Row],[Quantity]]*Table2[[#This Row],[Unit_Price]],2),"OK","Error") -> OK | AB23: =IF(Table2[[#This Row],[Transaction_Type]]="Purchase", IF(Table2[[#This Row],[Stock_After]]=Table2[[#This Row],[Stock_Before]]+Table2[[#This Row],[Quantity]], "OK", "Error"), IF(Table2[[#This Row],[Transaction_Type]]="Return", IF(Table2[[#This Row],[Stock_After]]=Table2[[#This Row],[Stock_Before]]+Table2[[#This Row],[Quantity]], "OK", "Error"), IF(Table2[[#This Row],[Transaction_Type]]="Sale", IF(Table2[[#This Row],[Stock_After]]=MAX(0, Table2[[#This Row],[Stock_Before]]-Table2[[#This Row],[Quantity]]), "OK", "Error"), IF(Table2[[#This Row],[Transaction_Type]]="Adjustment", IF(Table2[[#This Row],[Stock_After]]>=0, "OK", "Error"), "Check")))) -> OK | AC23: =IF(AND(Table2[[#This Row],[Quantity]]>=0,Table2[[#This Row],[Unit_Price]]>=0),"OK","Error") -> OK | AD23: =IF(Table2[[#This Row],[Stock_After]]=0,"Stock-Out",IF(Table2[[#This Row],[Stock_After]]<=10,"Low Stock","Healthy")) -> Healthy
A24: T00023 | B24: 46111 | C24: P007 | D24: Office Desk | E24: Furniture | F24: Desks | G24: S018 | H24: W01 | I24: Sale | J24: 36 | K24: 30368 | L24: 1093248 | M24: 177 | N24: 141 | O24: E002 | P24: C0448 | Q24: Cash | R24: Completed | S24: Regular Transaction | T24: =IF(COUNTIF(T26,Q36)>1,"Duplicate","OK") -> OK | U24: =IF(Table2[[#This Row],[Transaction_ID]]="","Missing","OK") -> OK | V24: =IF(COUNTIF(Table2[[#This Row],[Product_ID]],Table2[[#This Row],[Product_ID]])=0,"Invalid Product","OK") -> OK | W24: =IF(COUNTIF(Table2[[#This Row],[Supplier_ID]],Table2[[#This Row],[Supplier_ID]])=0,"Invalid Supplier","OK") -> OK | X24: =IF(COUNTIF(Table2[[#This Row],[Warehouse_ID]],Table2[[#This Row],[Warehouse_ID]])=0,"Invalid Warehouse","OK") -> OK | Y24: =IF(COUNTIF(Table2[[#This Row],[Employee_ID]],Table2[[#This Row],[Employee_ID]])=0,"Invalid Employee","OK") -> OK | Z24: =IF(Table2[[#This Row],[Stock_After]]=Table2[[#This Row],[Stock_After]]+Table2[[#This Row],[Stock_After]]-Table2[[#This Row],[Stock_After]]-Table2[[#This Row],[Stock_After]]+Table2[[#This Row],[Stock_After]],"OK","Error") -> OK | AA24: =IF(ROUND(Table2[[#This Row],[Total_Value]],2)=ROUND(Table2[[#This Row],[Quantity]]*Table2[[#This Row],[Unit_Price]],2),"OK","Error") -> OK | AB24: =IF(Table2[[#This Row],[Transaction_Type]]="Purchase", IF(Table2[[#This Row],[Stock_After]]=Table2[[#This Row],[Stock_Before]]+Table2[[#This Row],[Quantity]], "OK", "Error"), IF(Table2[[#This Row],[Transaction_Type]]="Return", IF(Table2[[#This Row],[Stock_After]]=Table2[[#This Row],[Stock_Before]]+Table2[[#This Row],[Quantity]], "OK", "Error"), IF(Table2[[#This Row],[Transaction_Type]]="Sale", IF(Table2[[#This Row],[Stock_After]]=MAX(0, Table2[[#This Row],[Stock_Before]]-Table2[[#This Row],[Quantity]]), "OK", "Error"), IF(Table2[[#This Row],[Transaction_Type]]="Adjustment", IF(Table2[[#This Row],[Stock_After]]>=0, "OK", "Error"), "Check")))) -> OK | AC24: =IF(AND(Table2[[#This Row],[Quantity]]>=0,Table2[[#This Row],[Unit_Price]]>=0),"OK","Error") -> OK | AD24: =IF(Table2[[#This Row],[Stock_After]]=0,"Stock-Out",IF(Table2[[#This Row],[Stock_After]]<=10,"Low Stock","Healthy")) -> Healthy
A25: T00024 | B25: 46068 | C25: P002 | D25: Keyboard | E25: Electronics | F25: Accessories | G25: S002 | H25: W02 | I25: Sale | J25: 22 | K25: 26684 | L25: 587048 | M25: 298 | N25: 276 | O25: E013 | P25: C0247 | Q25: Cash | R25: Completed | S25: Regular Transaction | T25: =IF(COUNTIF(T27,Q37)>1,"Duplicate","OK") -> OK | U25: =IF(Table2[[#This Row],[Transaction_ID]]="","Missing","OK") -> OK | V25: =IF(COUNTIF(Table2[[#This Row],[Product_ID]],Table2[[#This Row],[Product_ID]])=0,"Invalid Product","OK") -> OK | W25: =IF(COUNTIF(Table2[[#This Row],[Supplier_ID]],Table2[[#This Row],[Supplier_ID]])=0,"Invalid Supplier","OK") -> OK | X25: =IF(COUNTIF(Table2[[#This Row],[Warehouse_ID]],Table2[[#This Row],[Warehouse_ID]])=0,"Invalid Warehouse","OK") -> OK | Y25: =IF(COUNTIF(Table2[[#This Row],[Employee_ID]],Table2[[#This Row],[Employee_ID]])=0,"Invalid Employee","OK") -> OK | Z25: =IF(Table2[[#This Row],[Stock_After]]=Table2[[#This Row],[Stock_After]]+Table2[[#This Row],[Stock_After]]-Table2[[#This Row],[Stock_After]]-Table2[[#This Row],[Stock_After]]+Table2[[#This Row],[Stock_After]],"OK","Error") -> OK | AA25: =IF(ROUND(Table2[[#This Row],[Total_Value]],2)=ROUND(Table2[[#This Row],[Quantity]]*Table2[[#This Row],[Unit_Price]],2),"OK","Error") -> OK | AB25: =IF(Table2[[#This Row],[Transaction_Type]]="Purchase", IF(Table2[[#This Row],[Stock_After]]=Table2[[#This Row],[Stock_Before]]+Table2[[#This Row],[Quantity]], "OK", "Error"), IF(Table2[[#This Row],[Transaction_Type]]="Return", IF(Table2[[#This Row],[Stock_After]]=Table2[[#This Row],[Stock_Before]]+Table2[[#This Row],[Quantity]], "OK", "Error"), IF(Table2[[#This Row],[Transaction_Type]]="Sale", IF(Table2[[#This Row],[Stock_After]]=MAX(0, Table2[[#This Row],[Stock_Before]]-Table2[[#This Row],[Quantity]]), "OK", "Error"), IF(Table2[[#This Row],[Transaction_Type]]="Adjustment", IF(Table2[[#This Row],[Stock_After]]>=0, "OK", "Error"), "Check")))) -> OK | AC25: =IF(AND(Table2[[#This Row],[Quantity]]>=0,Table2[[#This Row],[Unit_Price]]>=0),"OK","Error") -> OK | AD25: =IF(Table2[[#This Row],[Stock_After]]=0,"Stock-Out",IF(Table2[[#This Row],[Stock_After]]<=10,"Low Stock","Healthy")) -> Healthy
A26: T00025 | B26: 46227 | C26: P007 | D26: Office Desk | E26: Furniture | F26: Desks | G26: S016 | H26: W02 | I26: Return | J26: 59 | K26: 18744 | L26: 1105896 | M26: 266 | N26: 325 | O26: E007 | Q26: UPI | R26: Pending | S26: Regular Transaction | T26: =IF(COUNTIF(T28,Q38)>1,"Duplicate","OK") -> OK | U26: =IF(Table2[[#This Row],[Transaction_ID]]="","Missing","OK") -> OK | V26: =IF(COUNTIF(Table2[[#This Row],[Product_ID]],Table2[[#This Row],[Product_ID]])=0,"Invalid Product","OK") -> OK | W26: =IF(COUNTIF(Table2[[#This Row],[Supplier_ID]],Table2[[#This Row],[Supplier_ID]])=0,"Invalid Supplier","OK") -> OK | X26: =IF(COUNTIF(Table2[[#This Row],[Warehouse_ID]],Table2[[#This Row],[Warehouse_ID]])=0,"Invalid Warehouse","OK") -> OK | Y26: =IF(COUNTIF(Table2[[#This Row],[Employee_ID]],Table2[[#This Row],[Employee_ID]])=0,"Invalid Employee","OK") -> OK | Z26: =IF(Table2[[#This Row],[Stock_After]]=Table2[[#This Row],[Stock_After]]+Table2[[#This Row],[Stock_After]]-Table2[[#This Row],[Stock_After]]-Table2[[#This Row],[Stock_After]]+Table2[[#This Row],[Stock_After]],"OK","Error") -> OK | AA26: =IF(ROUND(Table2[[#This Row],[Total_Value]],2)=ROUND(Table2[[#This Row],[Quantity]]*Table2[[#This Row],[Unit_Price]],2),"OK","Error") -> OK | AB26: =IF(Table2[[#This Row],[Transaction_Type]]="Purchase", IF(Table2[[#This Row],[Stock_After]]=Table2[[#This Row],[Stock_Before]]+Table2[[#This Row],[Quantity]], "OK", "Error"), IF(Table2[[#This Row],[Transaction_Type]]="Return", IF(Table2[[#This Row],[Stock_After]]=Table2[[#This Row],[Stock_Before]]+Table2[[#This Row],[Quantity]], "OK", "Error"), IF(Table2[[#This Row],[Transaction_Type]]="Sale", IF(Table2[[#This Row],[Stock_After]]=MAX(0, Table2[[#This Row],[Stock_Before]]-Table2[[#This Row],[Quantity]]), "OK", "Error"), IF(Table2[[#This Row],[Transaction_Type]]="Adjustment", IF(Table2[[#This Row],[Stock_After]]>=0, "OK", "Error"), "Check")))) -> OK | AC26: =IF(AND(Table2[[#This Row],[Quantity]]>=0,Table2[[#This Row],[Unit_Price]]>=0),"OK","Error") -> OK | AD26: =IF(Table2[[#This Row],[Stock_After]]=0,"Stock-Out",IF(Table2[[#This Row],[Stock_After]]<=10,"Low Stock","Healthy")) -> Healthy
A27: T00026 | B27: 45979 | C27: P004 | D27: Monitor | E27: Electronics | F27: Displays | G27: S002 | H27: W01 | I27: Purchase | J27: 75 | K27: 48267 | L27: 3620025 | M27: 327 | N27: 402 | O27: E019 | Q27: Credit | R27: Completed | S27: Regular Transaction | T27: =IF(COUNTIF(T29,Q39)>1,"Duplicate","OK") -> OK | U27: =IF(Table2[[#This Row],[Transaction_ID]]="","Missing","OK") -> OK | V27: =IF(COUNTIF(Table2[[#This Row],[Product_ID]],Table2[[#This Row],[Product_ID]])=0,"Invalid Product","OK") -> OK | W27: =IF(COUNTIF(Table2[[#This Row],[Supplier_ID]],Table2[[#This Row],[Supplier_ID]])=0,"Invalid Supplier","OK") -> OK | X27: =IF(COUNTIF(Table2[[#This Row],[Warehouse_ID]],Table2[[#This Row],[Warehouse_ID]])=0,"Invalid Warehouse","OK") -> OK | Y27: =IF(COUNTIF(Table2[[#This Row],[Employee_ID]],Table2[[#This Row],[Employee_ID]])=0,"Invalid Employee","OK") -> OK | Z27: =IF(Table2[[#This Row],[Stock_After]]=Table2[[#This Row],[Stock_After]]+Table2[[#This Row],[Stock_After]]-Table2[[#This Row],[Stock_After]]-Table2[[#This Row],[Stock_After]]+Table2[[#This Row],[Stock_After]],"OK","Error") -> OK | AA27: =IF(ROUND(Table2[[#This Row],[Total_Value]],2)=ROUND(Table2[[#This Row],[Quantity]]*Table2[[#This Row],[Unit_Price]],2),"OK","Error") -> OK | AB27: =IF(Table2[[#This Row],[Transaction_Type]]="Purchase", IF(Table2[[#This Row],[Stock_After]]=Table2[[#This Row],[Stock_Before]]+Table2[[#This Row],[Quantity]], "OK", "Error"), IF(Table2[[#This Row],[Transaction_Type]]="Return", IF(Table2[[#This Row],[Stock_After]]=Table2[[#This Row],[Stock_Before]]+Table2[[#This Row],[Quantity]], "OK", "Error"), IF(Table2[[#This Row],[Transaction_Type]]="Sale", IF(Table2[[#This Row],[Stock_After]]=MAX(0, Table2[[#This Row],[Stock_Before]]-Table2[[#This Row],[Quantity]]), "OK", "Error"), IF(Table2[[#This Row],[Transaction_Type]]="Adjustment", IF(Table2[[#This Row],[Stock_After]]>=0, "OK", "Error"), "Check")))) -> OK | AC27: =IF(AND(Table2[[#This Row],[Quantity]]>=0,Table2[[#This Row],[Unit_Price]]>=0),"OK","Error") -> OK | AD27: =IF(Table2[[#This Row],[Stock_After]]=0,"Stock-Out",IF(Table2[[#This Row],[Stock_After]]<=10,"Low Stock","Healthy")) -> Healthy
A28: T00027 | B28: 45728 | C28: P009 | D28: Pen | E28: Stationery | F28: Writing | G28: S020 | H28: W01 | I28: Sale | J28: 8 | K28: 33331 | L28: 266648 | M28: 91 | N28: 83 | O28: E008 | P28: C0436 | Q28: Credit | R28: Completed | S28: Regular Transaction | T28: =IF(COUNTIF(T30,Q40)>1,"Duplicate","OK") -> OK | U28: =IF(Table2[[#This Row],[Transaction_ID]]="","Missing","OK") -> OK | V28: =IF(COUNTIF(Table2[[#This Row],[Product_ID]],Table2[[#This Row],[Product_ID]])=0,"Invalid Product","OK") -> OK | W28: =IF(COUNTIF(Table2[[#This Row],[Supplier_ID]],Table2[[#This Row],[Supplier_ID]])=0,"Invalid Supplier","OK") -> OK | X28: =IF(COUNTIF(Table2[[#This Row],[Warehouse_ID]],Table2[[#This Row],[Warehouse_ID]])=0,"Invalid Warehouse","OK") -> OK | Y28: =IF(COUNTIF(Table2[[#This Row],[Employee_ID]],Table2[[#This Row],[Employee_ID]])=0,"Invalid Employee","OK") -> OK | Z28: =IF(Table2[[#This Row],[Stock_After]]=Table2[[#This Row],[Stock_After]]+Table2[[#This Row],[Stock_After]]-Table2[[#This Row],[Stock_After]]-Table2[[#This Row],[Stock_After]]+Table2[[#This Row],[Stock_After]],"OK","Error") -> OK | AA28: =IF(ROUND(Table2[[#This Row],[Total_Value]],2)=ROUND(Table2[[#This Row],[Quantity]]*Table2[[#This Row],[Unit_Price]],2),"OK","Error") -> OK | AB28: =IF(Table2[[#This Row],[Transaction_Type]]="Purchase", IF(Table2[[#This Row],[Stock_After]]=Table2[[#This Row],[Stock_Before]]+Table2[[#This Row],[Quantity]], "OK", "Error"), IF(Table2[[#This Row],[Transaction_Type]]="Return", IF(Table2[[#This Row],[Stock_After]]=Table2[[#This Row],[Stock_Before]]+Table2[[#This Row],[Quantity]], "OK", "Error"), IF(Table2[[#This Row],[Transaction_Type]]="Sale", IF(Table2[[#This Row],[Stock_After]]=MAX(0, Table2[[#This Row],[Stock_Before]]-Table2[[#This Row],[Quantity]]), "OK", "Error"), IF(Table2[[#This Row],[Transaction_Type]]="Adjustment", IF(Table2[[#This Row],[Stock_After]]>=0, "OK", "Error"), "Check")))) -> OK | AC28: =IF(AND(Table2[[#This Row],[Quantity]]>=0,Table2[[#This Row],[Unit_Price]]>=0),"OK","Error") -> OK | AD28: =IF(Table2[[#This Row],[Stock_After]]=0,"Stock-Out",IF(Table2[[#This Row],[Stock_After]]<=10,"Low Stock","Healthy")) -> Healthy
A29: T00028 | B29: 46087 | C29: P002 | D29: Keyboard | E29: Electronics | F29: Accessories | G29: S019 | H29: W05 | I29: Sale | J29: 75 | K29: 39012 | L29: 2925900 | M29: 70 | N29: 0 | O29: E017 | P29: C0318 | Q29: UPI | R29: Completed | S29: Regular Transaction | T29: =IF(COUNTIF(T31,Q41)>1,"Duplicate","OK") -> OK | U29: =IF(Table2[[#This Row],[Transaction_ID]]="","Missing","OK") -> OK | V29: =IF(COUNTIF(Table2[[#This Row],[Product_ID]],Table2[[#This Row],[Product_ID]])=0,"Invalid Product","OK") -> OK | W29: =IF(COUNTIF(Table2[[#This Row],[Supplier_ID]],Table2[[#This Row],[Supplier_ID]])=0,"Invalid Supplier","OK") -> OK | X29: =IF(COUNTIF(Table2[[#This Row],[Warehouse_ID]],Table2[[#This Row],[Warehouse_ID]])=0,"Invalid Warehouse","OK") -> OK | Y29: =IF(COUNTIF(Table2[[#This Row],[Employee_ID]],Table2[[#This Row],[Employee_ID]])=0,"Invalid Employee","OK") -> OK | Z29: =IF(Table2[[#This Row],[Stock_After]]=Table2[[#This Row],[Stock_After]]+Table2[[#This Row],[Stock_After]]-Table2[[#This Row],[Stock_After]]-Table2[[#This Row],[Stock_After]]+Table2[[#This Row],[Stock_After]],"OK","Error") -> OK | AA29: =IF(ROUND(Table2[[#This Row],[Total_Value]],2)=ROUND(Table2[[#This Row],[Quantity]]*Table2[[#This Row],[Unit_Price]],2),"OK","Error") -> OK | AB29: =IF(Table2[[#This Row],[Transaction_Type]]="Purchase", IF(Table2[[#This Row],[Stock_After]]=Table2[[#This Row],[Stock_Before]]+Table2[[#This Row],[Quantity]], "OK", "Error"), IF(Table2[[#This Row],[Transaction_Type]]="Return", IF(Table2[[#This Row],[Stock_After]]=Table2[[#This Row],[Stock_Before]]+Table2[[#This Row],[Quantity]], "OK", "Error"), IF(Table2[[#This Row],[Transaction_Type]]="Sale", IF(Table2[[#This Row],[Stock_After]]=MAX(0, Table2[[#This Row],[Stock_Before]]-Table2[[#This Row],[Quantity]]), "OK", "Error"), IF(Table2[[#This Row],[Transaction_Type]]="Adjustment", IF(Table2[[#This Row],[Stock_After]]>=0, "OK", "Error"), "Check")))) -> OK | AC29: =IF(AND(Table2[[#This Row],[Quantity]]>=0,Table2[[#This Row],[Unit_Price]]>=0),"OK","Error") -> OK | AD29: =IF(Table2[[#This Row],[Stock_After]]=0,"Stock-Out",IF(Table2[[#This Row],[Stock_After]]<=10,"Low Stock","Healthy")) -> Stock-Out
A30: T00029 | B30: 46063 | C30: P005 | D30: Printer | E30: Electronics | F30: Printers | G30: S005 | H30: W03 | I30: Sale | J30: 86 | K30: 46986 | L30: 4040796 | M30: 210 | N30: 124 | O30: E015 | P30: C0123 | Q30: UPI | R30: Approved | S30: Regular Transaction | T30: =IF(COUNTIF(T32,Q42)>1,"Duplicate","OK") -> OK | U30: =IF(Table2[[#This Row],[Transaction_ID]]="","Missing","OK") -> OK | V30: =IF(COUNTIF(Table2[[#This Row],[Product_ID]],Table2[[#This Row],[Product_ID]])=0,"Invalid Product","OK") -> OK | W30: =IF(COUNTIF(Table2[[#This Row],[Supplier_ID]],Table2[[#This Row],[Supplier_ID]])=0,"Invalid Supplier","OK") -> OK | X30: =IF(COUNTIF(Table2[[#This Row],[Warehouse_ID]],Table2[[#This Row],[Warehouse_ID]])=0,"Invalid Warehouse","OK") -> OK | Y30: =IF(COUNTIF(Table2[[#This Row],[Employee_ID]],Table2[[#This Row],[Employee_ID]])=0,"Invalid Employee","OK") -> OK | Z30: =IF(Table2[[#This Row],[Stock_After]]=Table2[[#This Row],[Stock_After]]+Table2[[#This Row],[Stock_After]]-Table2[[#This Row],[Stock_After]]-Table2[[#This Row],[Stock_After]]+Table2[[#This Row],[Stock_After]],"OK","Error") -> OK | AA30: =IF(ROUND(Table2[[#This Row],[Total_Value]],2)=ROUND(Table2[[#This Row],[Quantity]]*Table2[[#This Row],[Unit_Price]],2),"OK","Error") -> OK | AB30: =IF(Table2[[#This Row],[Transaction_Type]]="Purchase", IF(Table2[[#This Row],[Stock_After]]=Table2[[#This Row],[Stock_Before]]+Table2[[#This Row],[Quantity]], "OK", "Error"), IF(Table2[[#This Row],[Transaction_Type]]="Return", IF(Table2[[#This Row],[Stock_After]]=Table2[[#This Row],[Stock_Before]]+Table2[[#This Row],[Quantity]], "OK", "Error"), IF(Table2[[#This Row],[Transaction_Type]]="Sale", IF(Table2[[#This Row],[Stock_After]]=MAX(0, Table2[[#This Row],[Stock_Before]]-Table2[[#This Row],[Quantity]]), "OK", "Error"), IF(Table2[[#This Row],[Transaction_Type]]="Adjustment", IF(Table2[[#This Row],[Stock_After]]>=0, "OK", "Error"), "Check")))) -> OK | AC30: =IF(AND(Table2[[#This Row],[Quantity]]>=0,Table2[[#This Row],[Unit_Price]]>=0),"OK","Error") -> OK | AD30: =IF(Table2[[#This Row],[Stock_After]]=0,"Stock-Out",IF(Table2[[#This Row],[Stock_After]]<=10,"Low Stock","Healthy")) -> Healthy
A31: T00030 | B31: 45733 | C31: P002 | D31: Keyboard | E31: Electronics | F31: Accessories | G31: S018 | H31: W02 | I31: Purchase | J31: 59 | K31: 40758 | L31: 2404722 | M31: 338 | N31: 397 | O31: E017 | Q31: UPI | R31: Completed | S31: Regular Transaction | T31: =IF(COUNTIF(T33,Q43)>1,"Duplicate","OK") -> OK | U31: =IF(Table2[[#This Row],[Transaction_ID]]="","Missing","OK") -> OK | V31: =IF(COUNTIF(Table2[[#This Row],[Product_ID]],Table2[[#This Row],[Product_ID]])=0,"Invalid Product","OK") -> OK | W31: =IF(COUNTIF(Table2[[#This Row],[Supplier_ID]],Table2[[#This Row],[Supplier_ID]])=0,"Invalid Supplier","OK") -> OK | X31: =IF(COUNTIF(Table2[[#This Row],[Warehouse_ID]],Table2[[#This Row],[Warehouse_ID]])=0,"Invalid Warehouse","OK") -> OK | Y31: =IF(COUNTIF(Table2[[#This Row],[Employee_ID]],Table2[[#This Row],[Employee_ID]])=0,"Invalid Employee","OK") -> OK | Z31: =IF(Table2[[#This Row],[Stock_After]]=Table2[[#This Row],[Stock_After]]+Table2[[#This Row],[Stock_After]]-Table2[[#This Row],[Stock_After]]-Table2[[#This Row],[Stock_After]]+Table2[[#This Row],[Stock_After]],"OK","Error") -> OK | AA31: =IF(ROUND(Table2[[#This Row],[Total_Value]],2)=ROUND(Table2[[#This Row],[Quantity]]*Table2[[#This Row],[Unit_Price]],2),"OK","Error") -> OK | AB31: =IF(Table2[[#This Row],[Transaction_Type]]="Purchase", IF(Table2[[#This Row],[Stock_After]]=Table2[[#This Row],[Stock_Before]]+Table2[[#This Row],[Quantity]], "OK", "Error"), IF(Table2[[#This Row],[Transaction_Type]]="Return", IF(Table2[[#This Row],[Stock_After]]=Table2[[#This Row],[Stock_Before]]+Table2[[#This Row],[Quantity]], "OK", "Error"), IF(Table2[[#This Row],[Transaction_Type]]="Sale", IF(Table2[[#This Row],[Stock_After]]=MAX(0, Table2[[#This Row],[Stock_Before]]-Table2[[#This Row],[Quantity]]), "OK", "Error"), IF(Table2[[#This Row],[Transaction_Type]]="Adjustment", IF(Table2[[#This Row],[Stock_After]]>=0, "OK", "Error"), "Check")))) -> OK | AC31: =IF(AND(Table2[[#This Row],[Quantity]]>=0,Table2[[#This Row],[Unit_Price]]>=0),"OK","Error") -> OK | AD31: =IF(Table2[[#This Row],[Stock_After]]=0,"Stock-Out",IF(Table2[[#This Row],[Stock_After]]<=10,"Low Stock","Healthy")) -> Healthy
A32: T00031 | B32: 45819 | C32: P003 | D32: Mouse | E32: Electronics | F32: Accessories | G32: S015 | H32: W05 | I32: Return | J32: 9 | K32: 16059 | L32: 144531 | M32: 239 | N32: 248 | O32: E010 | Q32: Cash | R32: Approved | S32: Regular Transaction | T32: =IF(COUNTIF(T34,Q44)>1,"Duplicate","OK") -> OK | U32: =IF(Table2[[#This Row],[Transaction_ID]]="","Missing","OK") -> OK | V32: =IF(COUNTIF(Table2[[#This Row],[Product_ID]],Table2[[#This Row],[Product_ID]])=0,"Invalid Product","OK") -> OK | W32: =IF(COUNTIF(Table2[[#This Row],[Supplier_ID]],Table2[[#This Row],[Supplier_ID]])=0,"Invalid Supplier","OK") -> OK | X32: =IF(COUNTIF(Table2[[#This Row],[Warehouse_ID]],Table2[[#This Row],[Warehouse_ID]])=0,"Invalid Warehouse","OK") -> OK | Y32: =IF(COUNTIF(Table2[[#This Row],[Employee_ID]],Table2[[#This Row],[Employee_ID]])=0,"Invalid Employee","OK") -> OK | Z32: =IF(Table2[[#This Row],[Stock_After]]=Table2[[#This Row],[Stock_After]]+Table2[[#This Row],[Stock_After]]-Table2[[#This Row],[Stock_After]]-Table2[[#This Row],[Stock_After]]+Table2[[#This Row],[Stock_After]],"OK","Error") -> OK | AA32: =IF(ROUND(Table2[[#This Row],[Total_Value]],2)=ROUND(Table2[[#This Row],[Quantity]]*Table2[[#This Row],[Unit_Price]],2),"OK","Error") -> OK | AB32: =IF(Table2[[#This Row],[Transaction_Type]]="Purchase", IF(Table2[[#This Row],[Stock_After]]=Table2[[#This Row],[Stock_Before]]+Table2[[#This Row],[Quantity]], "OK", "Error"), IF(Table2[[#This Row],[Transaction_Type]]="Return", IF(Table2[[#This Row],[Stock_After]]=Table2[[#This Row],[Stock_Before]]+Table2[[#This Row],[Quantity]], "OK", "Error"), IF(Table2[[#This Row],[Transaction_Type]]="Sale", IF(Table2[[#This Row],[Stock_After]]=MAX(0, Table2[[#This Row],[Stock_Before]]-Table2[[#This Row],[Quantity]]), "OK", "Error"), IF(Table2[[#This Row],[Transaction_Type]]="Adjustment", IF(Table2[[#This Row],[Stock_After]]>=0, "OK", "Error"), "Check")))) -> OK | AC32: =IF(AND(Table2[[#This Row],[Quantity]]>=0,Table2[[#This Row],[Unit_Price]]>=0),"OK","Error") -> OK | AD32: =IF(Table2[[#This Row],[Stock_After]]=0,"Stock-Out",IF(Table2[[#This Row],[Stock_After]]<=10,"Low Stock","Healthy")) -> Healthy
A33: T00032 | B33: 45928 | C33: P009 | D33: Pen | E33: Stationery | F33: Writing | G33: S004 | H33: W01 | I33: Return | J33: 85 | K33: 6838 | L33: 581230 | M33: 499 | N33: 584 | O33: E018 | Q33: Card | R33: Completed | S33: Regular Transaction | T33: =IF(COUNTIF(T35,Q45)>1,"Duplicate","OK") -> OK | U33: =IF(Table2[[#This Row],[Transaction_ID]]="","Missing","OK") -> OK | V33: =IF(COUNTIF(Table2[[#This Row],[Product_ID]],Table2[[#This Row],[Product_ID]])=0,"Invalid Product","OK") -> OK | W33: =IF(COUNTIF(Table2[[#This Row],[Supplier_ID]],Table2[[#This Row],[Supplier_ID]])=0,"Invalid Supplier","OK") -> OK | X33: =IF(COUNTIF(Table2[[#This Row],[Warehouse_ID]],Table2[[#This Row],[Warehouse_ID]])=0,"Invalid Warehouse","OK") -> OK | Y33: =IF(COUNTIF(Table2[[#This Row],[Employee_ID]],Table2[[#This Row],[Employee_ID]])=0,"Invalid Employee","OK") -> OK | Z33: =IF(Table2[[#This Row],[Stock_After]]=Table2[[#This Row],[Stock_After]]+Table2[[#This Row],[Stock_After]]-Table2[[#This Row],[Stock_After]]-Table2[[#This Row],[Stock_After]]+Table2[[#This Row],[Stock_After]],"OK","Error") -> OK | AA33: =IF(ROUND(Table2[[#This Row],[Total_Value]],2)=ROUND(Table2[[#This Row],[Quantity]]*Table2[[#This Row],[Unit_Price]],2),"OK","Error") -> OK | AB33: =IF(Table2[[#This Row],[Transaction_Type]]="Purchase", IF(Table2[[#This Row],[Stock_After]]=Table2[[#This Row],[Stock_Before]]+Table2[[#This Row],[Quantity]], "OK", "Error"), IF(Table2[[#This Row],[Transaction_Type]]="Return", IF(Table2[[#This Row],[Stock_After]]=Table2[[#This Row],[Stock_Before]]+Table2[[#This Row],[Quantity]], "OK", "Error"), IF(Table2[[#This Row],[Transaction_Type]]="Sale", IF(Table2[[#This Row],[Stock_After]]=MAX(0, Table2[[#This Row],[Stock_Before]]-Table2[[#This Row],[Quantity]]), "OK", "Error"), IF(Table2[[#This Row],[Transaction_Type]]="Adjustment", IF(Table2[[#This Row],[Stock_After]]>=0, "OK", "Error"), "Check")))) -> OK | AC33: =IF(AND(Table2[[#This Row],[Quantity]]>=0,Table2[[#This Row],[Unit_Price]]>=0),"OK","Error") -> OK | AD33: =IF(Table2[[#This Row],[Stock_After]]=0,"Stock-Out",IF(Table2[[#This Row],[Stock_After]]<=10,"Low Stock","Healthy")) -> Healthy
A34: T00033 | B34: 45866 | C34: P005 | D34: Printer | E34: Electronics | F34: Printers | G34: S009 | H34: W05 | I34: Return | J34: 78 | K34: 13853 | L34: 1080534 | M34: 417 | N34: 495 | O34: E016 | Q34: UPI | R34: Approved | S34: Regular Transaction | T34: =IF(COUNTIF(T36,Q46)>1,"Duplicate","OK") -> OK | U34: =IF(Table2[[#This Row],[Transaction_ID]]="","Missing","OK") -> OK | V34: =IF(COUNTIF(Table2[[#This Row],[Product_ID]],Table2[[#This Row],[Product_ID]])=0,"Invalid Product","OK") -> OK | W34: =IF(COUNTIF(Table2[[#This Row],[Supplier_ID]],Table2[[#This Row],[Supplier_ID]])=0,"Invalid Supplier","OK") -> OK | X34: =IF(COUNTIF(Table2[[#This Row],[Warehouse_ID]],Table2[[#This Row],[Warehouse_ID]])=0,"Invalid Warehouse","OK") -> OK | Y34: =IF(COUNTIF(Table2[[#This Row],[Employee_ID]],Table2[[#This Row],[Employee_ID]])=0,"Invalid Employee","OK") -> OK | Z34: =IF(Table2[[#This Row],[Stock_After]]=Table2[[#This Row],[Stock_After]]+Table2[[#This Row],[Stock_After]]-Table2[[#This Row],[Stock_After]]-Table2[[#This Row],[Stock_After]]+Table2[[#This Row],[Stock_After]],"OK","Error") -> OK | AA34: =IF(ROUND(Table2[[#This Row],[Total_Value]],2)=ROUND(Table2[[#This Row],[Quantity]]*Table2[[#This Row],[Unit_Price]],2),"OK","Error") -> OK | AB34: =IF(Table2[[#This Row],[Transaction_Type]]="Purchase", IF(Table2[[#This Row],[Stock_After]]=Table2[[#This Row],[Stock_Before]]+Table2[[#This Row],[Quantity]], "OK", "Error"), IF(Table2[[#This Row],[Transaction_Type]]="Return", IF(Table2[[#This Row],[Stock_After]]=Table2[[#This Row],[Stock_Before]]+Table2[[#This Row],[Quantity]], "OK", "Error"), IF(Table2[[#This Row],[Transaction_Type]]="Sale", IF(Table2[[#This Row],[Stock_After]]=MAX(0, Table2[[#This Row],[Stock_Before]]-Table2[[#This Row],[Quantity]]), "OK", "Error"), IF(Table2[[#This Row],[Transaction_Type]]="Adjustment", IF(Table2[[#This Row],[Stock_After]]>=0, "OK", "Error"), "Check")))) -> OK | AC34: =IF(AND(Table2[[#This Row],[Quantity]]>=0,Table2[[#This Row],[Unit_Price]]>=0),"OK","Error") -> OK | AD34: =IF(Table2[[#This Row],[Stock_After]]=0,"Stock-Out",IF(Table2[[#This Row],[Stock_After]]<=10,"Low Stock","Healthy")) -> Healthy
A35: T00034 | B35: 45703 | C35: P001 | D35: Laptop | E35: Electronics | F35: Computers | G35: S001 | H35: W03 | I35: Purchase | J35: 82 | K35: 27809 | L35: 2280338 | M35: 474 | N35: 556 | O35: E005 | Q35: UPI | R35: Approved | S35: Regular Transaction | T35: =IF(COUNTIF(T37,Q47)>1,"Duplicate","OK") -> OK | U35: =IF(Table2[[#This Row],[Transaction_ID]]="","Missing","OK") -> OK | V35: =IF(COUNTIF(Table2[[#This Row],[Product_ID]],Table2[[#This Row],[Product_ID]])=0,"Invalid Product","OK") -> OK | W35: =IF(COUNTIF(Table2[[#This Row],[Supplier_ID]],Table2[[#This Row],[Supplier_ID]])=0,"Invalid Supplier","OK") -> OK | X35: =IF(COUNTIF(Table2[[#This Row],[Warehouse_ID]],Table2[[#This Row],[Warehouse_ID]])=0,"Invalid Warehouse","OK") -> OK | Y35: =IF(COUNTIF(Table2[[#This Row],[Employee_ID]],Table2[[#This Row],[Employee_ID]])=0,"Invalid Employee","OK") -> OK | Z35: =IF(Table2[[#This Row],[Stock_After]]=Table2[[#This Row],[Stock_After]]+Table2[[#This Row],[Stock_After]]-Table2[[#This Row],[Stock_After]]-Table2[[#This Row],[Stock_After]]+Table2[[#This Row],[Stock_After]],"OK","Error") -> OK | AA35: =IF(ROUND(Table2[[#This Row],[Total_Value]],2)=ROUND(Table2[[#This Row],[Quantity]]*Table2[[#This Row],[Unit_Price]],2),"OK","Error") -> OK | AB35: =IF(Table2[[#This Row],[Transaction_Type]]="Purchase", IF(Table2[[#This Row],[Stock_After]]=Table2[[#This Row],[Stock_Before]]+Table2[[#This Row],[Quantity]], "OK", "Error"), IF(Table2[[#This Row],[Transaction_Type]]="Return", IF(Table2[[#This Row],[Stock_After]]=Table2[[#This Row],[Stock_Before]]+Table2[[#This Row],[Quantity]], "OK", "Error"), IF(Table2[[#This Row],[Transaction_Type]]="Sale", IF(Table2[[#This Row],[Stock_After]]=MAX(0, Table2[[#This Row],[Stock_Before]]-Table2[[#This Row],[Quantity]]), "OK", "Error"), IF(Table2[[#This Row],[Transaction_Type]]="Adjustment", IF(Table2[[#This Row],[Stock_After]]>=0, "OK", "Error"), "Check")))) -> OK | AC35: =IF(AND(Table2[[#This Row],[Quantity]]>=0,Table2[[#This Row],[Unit_Price]]>=0),"OK","Error") -> OK | AD35: =IF(Table2[[#This Row],[Stock_After]]=0,"Stock-Out",IF(Table2[[#This Row],[Stock_After]]<=10,"Low Stock","Healthy")) -> Healthy
A36: T00035 | B36: 45735 | C36: P003 | D36: Mouse | E36: Electronics | F36: Accessories | G36: S005 | H36: W05 | I36: Adjustment | J36: 71 | K36: 46296 | L36: 3287016 | M36: 268 | N36: 197 | O36: E002 | Q36: UPI | R36: Completed | S36: Regular Transaction | T36: =IF(COUNTIF(T38,Q48)>1,"Duplicate","OK") -> OK | U36: =IF(Table2[[#This Row],[Transaction_ID]]="","Missing","OK") -> OK | V36: =IF(COUNTIF(Table2[[#This Row],[Product_ID]],Table2[[#This Row],[Product_ID]])=0,"Invalid Product","OK") -> OK | W36: =IF(COUNTIF(Table2[[#This Row],[Supplier_ID]],Table2[[#This Row],[Supplier_ID]])=0,"Invalid Supplier","OK") -> OK | X36: =IF(COUNTIF(Table2[[#This Row],[Warehouse_ID]],Table2[[#This Row],[Warehouse_ID]])=0,"Invalid Warehouse","OK") -> OK | Y36: =IF(COUNTIF(Table2[[#This Row],[Employee_ID]],Table2[[#This Row],[Employee_ID]])=0,"Invalid Employee","OK") -> OK | Z36: =IF(Table2[[#This Row],[Stock_After]]=Table2[[#This Row],[Stock_After]]+Table2[[#This Row],[Stock_After]]-Table2[[#This Row],[Stock_After]]-Table2[[#This Row],[Stock_After]]+Table2[[#This Row],[Stock_After]],"OK","Error") -> OK | AA36: =IF(ROUND(Table2[[#This Row],[Total_Value]],2)=ROUND(Table2[[#This Row],[Quantity]]*Table2[[#This Row],[Unit_Price]],2),"OK","Error") -> OK | AB36: =IF(Table2[[#This Row],[Transaction_Type]]="Purchase", IF(Table2[[#This Row],[Stock_After]]=Table2[[#This Row],[Stock_Before]]+Table2[[#This Row],[Quantity]], "OK", "Error"), IF(Table2[[#This Row],[Transaction_Type]]="Return", IF(Table2[[#This Row],[Stock_After]]=Table2[[#This Row],[Stock_Before]]+Table2[[#This Row],[Quantity]], "OK", "Error"), IF(Table2[[#This Row],[Transaction_Type]]="Sale", IF(Table2[[#This Row],[Stock_After]]=MAX(0, Table2[[#This Row],[Stock_Before]]-Table2[[#This Row],[Quantity]]), "OK", "Error"), IF(Table2[[#This Row],[Transaction_Type]]="Adjustment", IF(Table2[[#This Row],[Stock_After]]>=0, "OK", "Error"), "Check")))) -> OK | AC36: =IF(AND(Table2[[#This Row],[Quantity]]>=0,Table2[[#This Row],[Unit_Price]]>=0),"OK","Error") -> OK | AD36: =IF(Table2[[#This Row],[Stock_After]]=0,"Stock-Out",IF(Table2[[#This Row],[Stock_After]]<=10,"Low Stock","Healthy")) -> Healthy
A37: T00036 | B37: 45698 | C37: P010 | D37: File Folder | E37: Stationery | F37: Files | G37: S012 | H37: W02 | I37: Sale | J37: 56 | K37: 8402 | L37: 470512 | M37: 71 | N37: 15 | O37: E008 | P37: C0158 | Q37: Cash | R37: Approved | S37: Regular Transaction | T37: =IF(COUNTIF(T39,Q49)>1,"Duplicate","OK") -> OK | U37: =IF(Table2[[#This Row],[Transaction_ID]]="","Missing","OK") -> OK | V37: =IF(COUNTIF(Table2[[#This Row],[Product_ID]],Table2[[#This Row],[Product_ID]])=0,"Invalid Product","OK") -> OK | W37: =IF(COUNTIF(Table2[[#This Row],[Supplier_ID]],Table2[[#This Row],[Supplier_ID]])=0,"Invalid Supplier","OK") -> OK | X37: =IF(COUNTIF(Table2[[#This Row],[Warehouse_ID]],Table2[[#This Row],[Warehouse_ID]])=0,"Invalid Warehouse","OK") -> OK | Y37: =IF(COUNTIF(Table2[[#This Row],[Employee_ID]],Table2[[#This Row],[Employee_ID]])=0,"Invalid Employee","OK") -> OK | Z37: =IF(Table2[[#This Row],[Stock_After]]=Table2[[#This Row],[Stock_After]]+Table2[[#This Row],[Stock_After]]-Table2[[#This Row],[Stock_After]]-Table2[[#This Row],[Stock_After]]+Table2[[#This Row],[Stock_After]],"OK","Error") -> OK | AA37: =IF(ROUND(Table2[[#This Row],[Total_Value]],2)=ROUND(Table2[[#This Row],[Quantity]]*Table2[[#This Row],[Unit_Price]],2),"OK","Error") -> OK | AB37: =IF(Table2[[#This Row],[Transaction_Type]]="Purchase", IF(Table2[[#This Row],[Stock_After]]=Table2[[#This Row],[Stock_Before]]+Table2[[#This Row],[Quantity]], "OK", "Error"), IF(Table2[[#This Row],[Transaction_Type]]="Return", IF(Table2[[#This Row],[Stock_After]]=Table2[[#This Row],[Stock_Before]]+Table2[[#This Row],[Quantity]], "OK", "Error"), IF(Table2[[#This Row],[Transaction_Type]]="Sale", IF(Table2[[#This Row],[Stock_After]]=MAX(0, Table2[[#This Row],[Stock_Before]]-Table2[[#This Row],[Quantity]]), "OK", "Error"), IF(Table2[[#This Row],[Transaction_Type]]="Adjustment", IF(Table2[[#This Row],[Stock_After]]>=0, "OK", "Error"), "Check")))) -> OK | AC37: =IF(AND(Table2[[#This Row],[Quantity]]>=0,Table2[[#This Row],[Unit_Price]]>=0),"OK","Error") -> OK | AD37: =IF(Table2[[#This Row],[Stock_After]]=0,"Stock-Out",IF(Table2[[#This Row],[Stock_After]]<=10,"Low Stock","Healthy")) -> Healthy
A38: T00037 | B38: 45839 | C38: P006 | D38: Office Chair | E38: Furniture | F38: Chairs | G38: S014 | H38: W01 | I38: Adjustment | J38: 80 | K38: 49167 | L38: 3933360 | M38: 129 | N38: 49 | O38: E006 | Q38: UPI | R38: Completed | S38: Regular Transaction | T38: =IF(COUNTIF(T40,Q50)>1,"Duplicate","OK") -> OK | U38: =IF(Table2[[#This Row],[Transaction_ID]]="","Missing","OK") -> OK | V38: =IF(COUNTIF(Table2[[#This Row],[Product_ID]],Table2[[#This Row],[Product_ID]])=0,"Invalid Product","OK") -> OK | W38: =IF(COUNTIF(Table2[[#This Row],[Supplier_ID]],Table2[[#This Row],[Supplier_ID]])=0,"Invalid Supplier","OK") -> OK | X38: =IF(COUNTIF(Table2[[#This Row],[Warehouse_ID]],Table2[[#This Row],[Warehouse_ID]])=0,"Invalid Warehouse","OK") -> OK | Y38: =IF(COUNTIF(Table2[[#This Row],[Employee_ID]],Table2[[#This Row],[Employee_ID]])=0,"Invalid Employee","OK") -> OK | Z38: =IF(Table2[[#This Row],[Stock_After]]=Table2[[#This Row],[Stock_After]]+Table2[[#This Row],[Stock_After]]-Table2[[#This Row],[Stock_After]]-Table2[[#This Row],[Stock_After]]+Table2[[#This Row],[Stock_After]],"OK","Error") -> OK | AA38: =IF(ROUND(Table2[[#This Row],[Total_Value]],2)=ROUND(Table2[[#This Row],[Quantity]]*Table2[[#This Row],[Unit_Price]],2),"OK","Error") -> OK | AB38: =IF(Table2[[#This Row],[Transaction_Type]]="Purchase", IF(Table2[[#This Row],[Stock_After]]=Table2[[#This Row],[Stock_Before]]+Table2[[#This Row],[Quantity]], "OK", "Error"), IF(Table2[[#This Row],[Transaction_Type]]="Return", IF(Table2[[#This Row],[Stock_After]]=Table2[[#This Row],[Stock_Before]]+Table2[[#This Row],[Quantity]], "OK", "Error"), IF(Table2[[#This Row],[Transaction_Type]]="Sale", IF(Table2[[#This Row],[Stock_After]]=MAX(0, Table2[[#This Row],[Stock_Before]]-Table2[[#This Row],[Quantity]]), "OK", "Error"), IF(Table2[[#This Row],[Transaction_Type]]="Adjustment", IF(Table2[[#This Row],[Stock_After]]>=0, "OK", "Error"), "Check")))) -> OK | AC38: =IF(AND(Table2[[#This Row],[Quantity]]>=0,Table2[[#This Row],[Unit_Price]]>=0),"OK","Error") -> OK | AD38: =IF(Table2[[#This Row],[Stock_After]]=0,"Stock-Out",IF(Table2[[#This Row],[Stock_After]]<=10,"Low Stock","Healthy")) -> Healthy
A39: T00038 | B39: 46049 | C39: P007 | D39: Office Desk | E39: Furniture | F39: Desks | G39: S002 | H39: W04 | I39: Sale | J39: 35 | K39: 10483 | L39: 366905 | M39: 453 | N39: 418 | O39: E008 | P39: C0360 | Q39: Card | R39: Completed | S39: Regular Transaction | T39: =IF(COUNTIF(T41,Q51)>1,"Duplicate","OK") -> OK | U39: =IF(Table2[[#This Row],[Transaction_ID]]="","Missing","OK") -> OK | V39: =IF(COUNTIF(Table2[[#This Row],[Product_ID]],Table2[[#This Row],[Product_ID]])=0,"Invalid Product","OK") -> OK | W39: =IF(COUNTIF(Table2[[#This Row],[Supplier_ID]],Table2[[#This Row],[Supplier_ID]])=0,"Invalid Supplier","OK") -> OK | X39: =IF(COUNTIF(Table2[[#This Row],[Warehouse_ID]],Table2[[#This Row],[Warehouse_ID]])=0,"Invalid Warehouse","OK") -> OK | Y39: =IF(COUNTIF(Table2[[#This Row],[Employee_ID]],Table2[[#This Row],[Employee_ID]])=0,"Invalid Employee","OK") -> OK | Z39: =IF(Table2[[#This Row],[Stock_After]]=Table2[[#This Row],[Stock_After]]+Table2[[#This Row],[Stock_After]]-Table2[[#This Row],[Stock_After]]-Table2[[#This Row],[Stock_After]]+Table2[[#This Row],[Stock_After]],"OK","Error") -> OK | AA39: =IF(ROUND(Table2[[#This Row],[Total_Value]],2)=ROUND(Table2[[#This Row],[Quantity]]*Table2[[#This Row],[Unit_Price]],2),"OK","Error") -> OK | AB39: =IF(Table2[[#This Row],[Transaction_Type]]="Purchase", IF(Table2[[#This Row],[Stock_After]]=Table2[[#This Row],[Stock_Before]]+Table2[[#This Row],[Quantity]], "OK", "Error"), IF(Table2[[#This Row],[Transaction_Type]]="Return", IF(Table2[[#This Row],[Stock_After]]=Table2[[#This Row],[Stock_Before]]+Table2[[#This Row],[Quantity]], "OK", "Error"), IF(Table2[[#This Row],[Transaction_Type]]="Sale", IF(Table2[[#This Row],[Stock_After]]=MAX(0, Table2[[#This Row],[Stock_Before]]-Table2[[#This Row],[Quantity]]), "OK", "Error"), IF(Table2[[#This Row],[Transaction_Type]]="Adjustment", IF(Table2[[#This Row],[Stock_After]]>=0, "OK", "Error"), "Check")))) -> OK | AC39: =IF(AND(Table2[[#This Row],[Quantity]]>=0,Table2[[#This Row],[Unit_Price]]>=0),"OK","Error") -> OK | AD39: =IF(Table2[[#This Row],[Stock_After]]=0,"Stock-Out",IF(Table2[[#This Row],[Stock_After]]<=10,"Low Stock","Healthy")) -> Healthy
A40: T00039 | B40: 46333 | C40: P008 | D40: Notebook | E40: Stationery | F40: Books | G40: S007 | H40: W04 | I40: Return | J40: 40 | K40: 14965 | L40: 598600 | M40: 164 | N40: 204 | O40: E011 | Q40: UPI | R40: Completed | S40: Regular Transaction | T40: =IF(COUNTIF(T42,Q52)>1,"Duplicate","OK") -> OK | U40: =IF(Table2[[#This Row],[Transaction_ID]]="","Missing","OK") -> OK | V40: =IF(COUNTIF(Table2[[#This Row],[Product_ID]],Table2[[#This Row],[Product_ID]])=0,"Invalid Product","OK") -> OK | W40: =IF(COUNTIF(Table2[[#This Row],[Supplier_ID]],Table2[[#This Row],[Supplier_ID]])=0,"Invalid Supplier","OK") -> OK | X40: =IF(COUNTIF(Table2[[#This Row],[Warehouse_ID]],Table2[[#This Row],[Warehouse_ID]])=0,"Invalid Warehouse","OK") -> OK | Y40: =IF(COUNTIF(Table2[[#This Row],[Employee_ID]],Table2[[#This Row],[Employee_ID]])=0,"Invalid Employee","OK") -> OK | Z40: =IF(Table2[[#This Row],[Stock_After]]=Table2[[#This Row],[Stock_After]]+Table2[[#This Row],[Stock_After]]-Table2[[#This Row],[Stock_After]]-Table2[[#This Row],[Stock_After]]+Table2[[#This Row],[Stock_After]],"OK","Error") -> OK | AA40: =IF(ROUND(Table2[[#This Row],[Total_Value]],2)=ROUND(Table2[[#This Row],[Quantity]]*Table2[[#This Row],[Unit_Price]],2),"OK","Error") -> OK | AB40: =IF(Table2[[#This Row],[Transaction_Type]]="Purchase", IF(Table2[[#This Row],[Stock_After]]=Table2[[#This Row],[Stock_Before]]+Table2[[#This Row],[Quantity]], "OK", "Error"), IF(Table2[[#This Row],[Transaction_Type]]="Return", IF(Table2[[#This Row],[Stock_After]]=Table2[[#This Row],[Stock_Before]]+Table2[[#This Row],[Quantity]], "OK", "Error"), IF(Table2[[#This Row],[Transaction_Type]]="Sale", IF(Table2[[#This Row],[Stock_After]]=MAX(0, Table2[[#This Row],[Stock_Before]]-Table2[[#This Row],[Quantity]]), "OK", "Error"), IF(Table2[[#This Row],[Transaction_Type]]="Adjustment", IF(Table2[[#This Row],[Stock_After]]>=0, "OK", "Error"), "Check")))) -> OK | AC40: =IF(AND(Table2[[#This Row],[Quantity]]>=0,Table2[[#This Row],[Unit_Price]]>=0),"OK","Error") -> OK | AD40: =IF(Table2[[#This Row],[Stock_After]]=0,"Stock-Out",IF(Table2[[#This Row],[Stock_After]]<=10,"Low Stock","Healthy")) -> Healthy
A41: T00040 | B41: 46353 | C41: P002 | D41: Keyboard | E41: Electronics | F41: Accessories | G41: S018 | H41: W03 | I41: Return | J41: 45 | K41: 42090 | L41: 1894050 | M41: 310 | N41: 355 | O41: E001 | Q41: Cash | R41: Approved | S41: Regular Transaction | T41: =IF(COUNTIF(T43,Q53)>1,"Duplicate","OK") -> OK | U41: =IF(Table2[[#This Row],[Transaction_ID]]="","Missing","OK") -> OK | V41: =IF(COUNTIF(Table2[[#This Row],[Product_ID]],Table2[[#This Row],[Product_ID]])=0,"Invalid Product","OK") -> OK | W41: =IF(COUNTIF(Table2[[#This Row],[Supplier_ID]],Table2[[#This Row],[Supplier_ID]])=0,"Invalid Supplier","OK") -> OK | X41: =IF(COUNTIF(Table2[[#This Row],[Warehouse_ID]],Table2[[#This Row],[Warehouse_ID]])=0,"Invalid Warehouse","OK") -> OK | Y41: =IF(COUNTIF(Table2[[#This Row],[Employee_ID]],Table2[[#This Row],[Employee_ID]])=0,"Invalid Employee","OK") -> OK | Z41: =IF(Table2[[#This Row],[Stock_After]]=Table2[[#This Row],[Stock_After]]+Table2[[#This Row],[Stock_After]]-Table2[[#This Row],[Stock_After]]-Table2[[#This Row],[Stock_After]]+Table2[[#This Row],[Stock_After]],"OK","Error") -> OK | AA41: =IF(ROUND(Table2[[#This Row],[Total_Value]],2)=ROUND(Table2[[#This Row],[Quantity]]*Table2[[#This Row],[Unit_Price]],2),"OK","Error") -> OK | AB41: =IF(Table2[[#This Row],[Transaction_Type]]="Purchase", IF(Table2[[#This Row],[Stock_After]]=Table2[[#This Row],[Stock_Before]]+Table2[[#This Row],[Quantity]], "OK", "Error"), IF(Table2[[#This Row],[Transaction_Type]]="Return", IF(Table2[[#This Row],[Stock_After]]=Table2[[#This Row],[Stock_Before]]+Table2[[#This Row],[Quantity]], "OK", "Error"), IF(Table2[[#This Row],[Transaction_Type]]="Sale", IF(Table2[[#This Row],[Stock_After]]=MAX(0, Table2[[#This Row],[Stock_Before]]-Table2[[#This Row],[Quantity]]), "OK", "Error"), IF(Table2[[#This Row],[Transaction_Type]]="Adjustment", IF(Table2[[#This Row],[Stock_After]]>=0, "OK", "Error"), "Check")))) -> OK | AC41: =IF(AND(Table2[[#This Row],[Quantity]]>=0,Table2[[#This Row],[Unit_Price]]>=0),"OK","Error") -> OK | AD41: =IF(Table2[[#This Row],[Stock_After]]=0,"Stock-Out",IF(Table2[[#This Row],[Stock_After]]<=10,"Low Stock","Healthy")) -> Healthy
A42: T00041 | B42: 46102 | C42: P005 | D42: Printer | E42: Electronics | F42: Printers | G42: S012 | H42: W03 | I42: Sale | J42: 75 | K42: 17447 | L42: 1308525 | M42: 69 | N42: 0 | O42: E014 | P42: C0056 | Q42: Cash | R42: Pending | S42: Regular Transaction | T42: =IF(COUNTIF(T44,Q54)>1,"Duplicate","OK") -> OK | U42: =IF(Table2[[#This Row],[Transaction_ID]]="","Missing","OK") -> OK | V42: =IF(COUNTIF(Table2[[#This Row],[Product_ID]],Table2[[#This Row],[Product_ID]])=0,"Invalid Product","OK") -> OK | W42: =IF(COUNTIF(Table2[[#This Row],[Supplier_ID]],Table2[[#This Row],[Supplier_ID]])=0,"Invalid Supplier","OK") -> OK | X42: =IF(COUNTIF(Table2[[#This Row],[Warehouse_ID]],Table2[[#This Row],[Warehouse_ID]])=0,"Invalid Warehouse","OK") -> OK | Y42: =IF(COUNTIF(Table2[[#This Row],[Employee_ID]],Table2[[#This Row],[Employee_ID]])=0,"Invalid Employee","OK") -> OK | Z42: =IF(Table2[[#This Row],[Stock_After]]=Table2[[#This Row],[Stock_After]]+Table2[[#This Row],[Stock_After]]-Table2[[#This Row],[Stock_After]]-Table2[[#This Row],[Stock_After]]+Table2[[#This Row],[Stock_After]],"OK","Error") -> OK | AA42: =IF(ROUND(Table2[[#This Row],[Total_Value]],2)=ROUND(Table2[[#This Row],[Quantity]]*Table2[[#This Row],[Unit_Price]],2),"OK","Error") -> OK | AB42: =IF(Table2[[#This Row],[Transaction_Type]]="Purchase", IF(Table2[[#This Row],[Stock_After]]=Table2[[#This Row],[Stock_Before]]+Table2[[#This Row],[Quantity]], "OK", "Error"), IF(Table2[[#This Row],[Transaction_Type]]="Return", IF(Table2[[#This Row],[Stock_After]]=Table2[[#This Row],[Stock_Before]]+Table2[[#This Row],[Quantity]], "OK", "Error"), IF(Table2[[#This Row],[Transaction_Type]]="Sale", IF(Table2[[#This Row],[Stock_After]]=MAX(0, Table2[[#This Row],[Stock_Before]]-Table2[[#This Row],[Quantity]]), "OK", "Error"), IF(Table2[[#This Row],[Transaction_Type]]="Adjustment", IF(Table2[[#This Row],[Stock_After]]>=0, "OK", "Error"), "Check")))) -> OK | AC42: =IF(AND(Table2[[#This Row],[Quantity]]>=0,Table2[[#This Row],[Unit_Price]]>=0),"OK","Error") -> OK | AD42: =IF(Table2[[#This Row],[Stock_After]]=0,"Stock-Out",IF(Table2[[#This Row],[Stock_After]]<=10,"Low Stock","Healthy")) -> Stock-Out
A43: T00042 | B43: 46190 | C43: P007 | D43: Office Desk | E43: Furniture | F43: Desks | G43: S018 | H43: W02 | I43: Sale | J43: 33 | K43: 2958 | L43: 97614 | M43: 412 | N43: 379 | O43: E012 | P43: C0224 | Q43: Credit | R43: Completed | S43: Regular Transaction | T43: =IF(COUNTIF(T45,Q55)>1,"Duplicate","OK") -> OK | U43: =IF(Table2[[#This Row],[Transaction_ID]]="","Missing","OK") -> OK | V43: =IF(COUNTIF(Table2[[#This Row],[Product_ID]],Table2[[#This Row],[Product_ID]])=0,"Invalid Product","OK") -> OK | W43: =IF(COUNTIF(Table2[[#This Row],[Supplier_ID]],Table2[[#This Row],[Supplier_ID]])=0,"Invalid Supplier","OK") -> OK | X43: =IF(COUNTIF(Table2[[#This Row],[Warehouse_ID]],Table2[[#This Row],[Warehouse_ID]])=0,"Invalid Warehouse","OK") -> OK | Y43: =IF(COUNTIF(Table2[[#This Row],[Employee_ID]],Table2[[#This Row],[Employee_ID]])=0,"Invalid Employee","OK") -> OK | Z43: =IF(Table2[[#This Row],[Stock_After]]=Table2[[#This Row],[Stock_After]]+Table2[[#This Row],[Stock_After]]-Table2[[#This Row],[Stock_After]]-Table2[[#This Row],[Stock_After]]+Table2[[#This Row],[Stock_After]],"OK","Error") -> OK | AA43: =IF(ROUND(Table2[[#This Row],[Total_Value]],2)=ROUND(Table2[[#This Row],[Quantity]]*Table2[[#This Row],[Unit_Price]],2),"OK","Error") -> OK | AB43: =IF(Table2[[#This Row],[Transaction_Type]]="Purchase", IF(Table2[[#This Row],[Stock_After]]=Table2[[#This Row],[Stock_Before]]+Table2[[#This Row],[Quantity]], "OK", "Error"), IF(Table2[[#This Row],[Transaction_Type]]="Return", IF(Table2[[#This Row],[Stock_After]]=Table2[[#This Row],[Stock_Before]]+Table2[[#This Row],[Quantity]], "OK", "Error"), IF(Table2[[#This Row],[Transaction_Type]]="Sale", IF(Table2[[#This Row],[Stock_After]]=MAX(0, Table2[[#This Row],[Stock_Before]]-Table2[[#This Row],[Quantity]]), "OK", "Error"), IF(Table2[[#This Row],[Transaction_Type]]="Adjustment", IF(Table2[[#This Row],[Stock_After]]>=0, "OK", "Error"), "Check")))) -> OK | AC43: =IF(AND(Table2[[#This Row],[Quantity]]>=0,Table2[[#This Row],[Unit_Price]]>=0),"OK","Error") -> OK | AD43: =IF(Table2[[#This Row],[Stock_After]]=0,"Stock-Out",IF(Table2[[#This Row],[Stock_After]]<=10,"Low Stock","Healthy")) -> Healthy
A44: T00043 | B44: 45965 | C44: P002 | D44: Keyboard | E44: Electronics | F44: Accessories | G44: S017 | H44: W03 | I44: Return | J44: 80 | K44: 20622 | L44: 1649760 | M44: 389 | N44: 469 | O44: E014 | Q44: UPI | R44: Completed | S44: Regular Transaction | T44: =IF(COUNTIF(T46,Q56)>1,"Duplicate","OK") -> OK | U44: =IF(Table2[[#This Row],[Transaction_ID]]="","Missing","OK") -> OK | V44: =IF(COUNTIF(Table2[[#This Row],[Product_ID]],Table2[[#This Row],[Product_ID]])=0,"Invalid Product","OK") -> OK | W44: =IF(COUNTIF(Table2[[#This Row],[Supplier_ID]],Table2[[#This Row],[Supplier_ID]])=0,"Invalid Supplier","OK") -> OK | X44: =IF(COUNTIF(Table2[[#This Row],[Warehouse_ID]],Table2[[#This Row],[Warehouse_ID]])=0,"Invalid Warehouse","OK") -> OK | Y44: =IF(COUNTIF(Table2[[#This Row],[Employee_ID]],Table2[[#This Row],[Employee_ID]])=0,"Invalid Employee","OK") -> OK | Z44: =IF(Table2[[#This Row],[Stock_After]]=Table2[[#This Row],[Stock_After]]+Table2[[#This Row],[Stock_After]]-Table2[[#This Row],[Stock_After]]-Table2[[#This Row],[Stock_After]]+Table2[[#This Row],[Stock_After]],"OK","Error") -> OK | AA44: =IF(ROUND(Table2[[#This Row],[Total_Value]],2)=ROUND(Table2[[#This Row],[Quantity]]*Table2[[#This Row],[Unit_Price]],2),"OK","Error") -> OK | AB44: =IF(Table2[[#This Row],[Transaction_Type]]="Purchase", IF(Table2[[#This Row],[Stock_After]]=Table2[[#This Row],[Stock_Before]]+Table2[[#This Row],[Quantity]], "OK", "Error"), IF(Table2[[#This Row],[Transaction_Type]]="Return", IF(Table2[[#This Row],[Stock_After]]=Table2[[#This Row],[Stock_Before]]+Table2[[#This Row],[Quantity]], "OK", "Error"), IF(Table2[[#This Row],[Transaction_Type]]="Sale", IF(Table2[[#This Row],[Stock_After]]=MAX(0, Table2[[#This Row],[Stock_Before]]-Table2[[#This Row],[Quantity]]), "OK", "Error"), IF(Table2[[#This Row],[Transaction_Type]]="Adjustment", IF(Table2[[#This Row],[Stock_After]]>=0, "OK", "Error"), "Check")))) -> OK | AC44: =IF(AND(Table2[[#This Row],[Quantity]]>=0,Table2[[#This Row],[Unit_Price]]>=0),"OK","Error") -> OK | AD44: =IF(Table2[[#This Row],[Stock_After]]=0,"Stock-Out",IF(Table2[[#This Row],[Stock_After]]<=10,"Low Stock","Healthy")) -> Healthy
A45: T00044 | B45: 46338 | C45: P007 | D45: Office Desk | E45: Furniture | F45: Desks | G45: S013 | H45: W02 | I45: Return | J45: 71 | K45: 8391 | L45: 595761 | M45: 148 | N45: 219 | O45: E020 | Q45: UPI | R45: Approved | S45: Regular Transaction | T45: =IF(COUNTIF(T47,Q57)>1,"Duplicate","OK") -> OK | U45: =IF(Table2[[#This Row],[Transaction_ID]]="","Missing","OK") -> OK | V45: =IF(COUNTIF(Table2[[#This Row],[Product_ID]],Table2[[#This Row],[Product_ID]])=0,"Invalid Product","OK") -> OK | W45: =IF(COUNTIF(Table2[[#This Row],[Supplier_ID]],Table2[[#This Row],[Supplier_ID]])=0,"Invalid Supplier","OK") -> OK | X45: =IF(COUNTIF(Table2[[#This Row],[Warehouse_ID]],Table2[[#This Row],[Warehouse_ID]])=0,"Invalid Warehouse","OK") -> OK | Y45: =IF(COUNTIF(Table2[[#This Row],[Employee_ID]],Table2[[#This Row],[Employee_ID]])=0,"Invalid Employee","OK") -> OK | Z45: =IF(Table2[[#This Row],[Stock_After]]=Table2[[#This Row],[Stock_After]]+Table2[[#This Row],[Stock_After]]-Table2[[#This Row],[Stock_After]]-Table2[[#This Row],[Stock_After]]+Table2[[#This Row],[Stock_After]],"OK","Error") -> OK | AA45: =IF(ROUND(Table2[[#This Row],[Total_Value]],2)=ROUND(Table2[[#This Row],[Quantity]]*Table2[[#This Row],[Unit_Price]],2),"OK","Error") -> OK | AB45: =IF(Table2[[#This Row],[Transaction_Type]]="Purchase", IF(Table2[[#This Row],[Stock_After]]=Table2[[#This Row],[Stock_Before]]+Table2[[#This Row],[Quantity]], "OK", "Error"), IF(Table2[[#This Row],[Transaction_Type]]="Return", IF(Table2[[#This Row],[Stock_After]]=Table2[[#This Row],[Stock_Before]]+Table2[[#This Row],[Quantity]], "OK", "Error"), IF(Table2[[#This Row],[Transaction_Type]]="Sale", IF(Table2[[#This Row],[Stock_After]]=MAX(0, Table2[[#This Row],[Stock_Before]]-Table2[[#This Row],[Quantity]]), "OK", "Error"), IF(Table2[[#This Row],[Transaction_Type]]="Adjustment", IF(Table2[[#This Row],[Stock_After]]>=0, "OK", "Error"), "Check")))) -> OK | AC45: =IF(AND(Table2[[#This Row],[Quantity]]>=0,Table2[[#This Row],[Unit_Price]]>=0),"OK","Error") -> OK | AD45: =IF(Table2[[#This Row],[Stock_After]]=0,"Stock-Out",IF(Table2[[#This Row],[Stock_After]]<=10,"Low Stock","Healthy")) -> Healthy
A46: T00045 | B46: 46251 | C46: P007 | D46: Office Desk | E46: Furniture | F46: Desks | G46: S020 | H46: W03 | I46: Purchase | J46: 39 | K46: 18853 | L46: 735267 | M46: 157 | N46: 196 | O46: E015 | Q46: Credit | R46: Approved | S46: Regular Transaction | T46: =IF(COUNTIF(T48,Q58)>1,"Duplicate","OK") -> OK | U46: =IF(Table2[[#This Row],[Transaction_ID]]="","Missing","OK") -> OK | V46: =IF(COUNTIF(Table2[[#This Row],[Product_ID]],Table2[[#This Row],[Product_ID]])=0,"Invalid Product","OK") -> OK | W46: =IF(COUNTIF(Table2[[#This Row],[Supplier_ID]],Table2[[#This Row],[Supplier_ID]])=0,"Invalid Supplier","OK") -> OK | X46: =IF(COUNTIF(Table2[[#This Row],[Warehouse_ID]],Table2[[#This Row],[Warehouse_ID]])=0,"Invalid Warehouse","OK") -> OK | Y46: =IF(COUNTIF(Table2[[#This Row],[Employee_ID]],Table2[[#This Row],[Employee_ID]])=0,"Invalid Employee","OK") -> OK | Z46: =IF(Table2[[#This Row],[Stock_After]]=Table2[[#This Row],[Stock_After]]+Table2[[#This Row],[Stock_After]]-Table2[[#This Row],[Stock_After]]-Table2[[#This Row],[Stock_After]]+Table2[[#This Row],[Stock_After]],"OK","Error") -> OK | AA46: =IF(ROUND(Table2[[#This Row],[Total_Value]],2)=ROUND(Table2[[#This Row],[Quantity]]*Table2[[#This Row],[Unit_Price]],2),"OK","Error") -> OK | AB46: =IF(Table2[[#This Row],[Transaction_Type]]="Purchase", IF(Table2[[#This Row],[Stock_After]]=Table2[[#This Row],[Stock_Before]]+Table2[[#This Row],[Quantity]], "OK", "Error"), IF(Table2[[#This Row],[Transaction_Type]]="Return", IF(Table2[[#This Row],[Stock_After]]=Table2[[#This Row],[Stock_Before]]+Table2[[#This Row],[Quantity]], "OK", "Error"), IF(Table2[[#This Row],[Transaction_Type]]="Sale", IF(Table2[[#This Row],[Stock_After]]=MAX(0, Table2[[#This Row],[Stock_Before]]-Table2[[#This Row],[Quantity]]), "OK", "Error"), IF(Table2[[#This Row],[Transaction_Type]]="Adjustment", IF(Table2[[#This Row],[Stock_After]]>=0, "OK", "Error"), "Check")))) -> OK | AC46: =IF(AND(Table2[[#This Row],[Quantity]]>=0,Table2[[#This Row],[Unit_Price]]>=0),"OK","Error") -> OK | AD46: =IF(Table2[[#This Row],[Stock_After]]=0,"Stock-Out",IF(Table2[[#This Row],[Stock_After]]<=10,"Low Stock","Healthy")) -> Healthy
A47: T00046 | B47: 45831 | C47: P008 | D47: Notebook | E47: Stationery | F47: Books | G47: S003 | H47: W03 | I47: Sale | J47: 66 | K47: 31060 | L47: 2049960 | M47: 456 | N47: 390 | O47: E017 | P47: C0462 | Q47: UPI | R47: Pending | S47: Regular Transaction | T47: =IF(COUNTIF(T49,Q59)>1,"Duplicate","OK") -> OK | U47: =IF(Table2[[#This Row],[Transaction_ID]]="","Missing","OK") -> OK | V47: =IF(COUNTIF(Table2[[#This Row],[Product_ID]],Table2[[#This Row],[Product_ID]])=0,"Invalid Product","OK") -> OK | W47: =IF(COUNTIF(Table2[[#This Row],[Supplier_ID]],Table2[[#This Row],[Supplier_ID]])=0,"Invalid Supplier","OK") -> OK | X47: =IF(COUNTIF(Table2[[#This Row],[Warehouse_ID]],Table2[[#This Row],[Warehouse_ID]])=0,"Invalid Warehouse","OK") -> OK | Y47: =IF(COUNTIF(Table2[[#This Row],[Employee_ID]],Table2[[#This Row],[Employee_ID]])=0,"Invalid Employee","OK") -> OK | Z47: =IF(Table2[[#This Row],[Stock_After]]=Table2[[#This Row],[Stock_After]]+Table2[[#This Row],[Stock_After]]-Table2[[#This Row],[Stock_After]]-Table2[[#This Row],[Stock_After]]+Table2[[#This Row],[Stock_After]],"OK","Error") -> OK | AA47: =IF(ROUND(Table2[[#This Row],[Total_Value]],2)=ROUND(Table2[[#This Row],[Quantity]]*Table2[[#This Row],[Unit_Price]],2),"OK","Error") -> OK | AB47: =IF(Table2[[#This Row],[Transaction_Type]]="Purchase", IF(Table2[[#This Row],[Stock_After]]=Table2[[#This Row],[Stock_Before]]+Table2[[#This Row],[Quantity]], "OK", "Error"), IF(Table2[[#This Row],[Transaction_Type]]="Return", IF(Table2[[#This Row],[Stock_After]]=Table2[[#This Row],[Stock_Before]]+Table2[[#This Row],[Quantity]], "OK", "Error"), IF(Table2[[#This Row],[Transaction_Type]]="Sale", IF(Table2[[#This Row],[Stock_After]]=MAX(0, Table2[[#This Row],[Stock_Before]]-Table2[[#This Row],[Quantity]]), "OK", "Error"), IF(Table2[[#This Row],[Transaction_Type]]="Adjustment", IF(Table2[[#This Row],[Stock_After]]>=0, "OK", "Error"), "Check")))) -> OK | AC47: =IF(AND(Table2[[#This Row],[Quantity]]>=0,Table2[[#This Row],[Unit_Price]]>=0),"OK","Error") -> OK | AD47: =IF(Table2[[#This Row],[Stock_After]]=0,"Stock-Out",IF(Table2[[#This Row],[Stock_After]]<=10,"Low Stock","Healthy")) -> Healthy
A48: T00047 | B48: 45808 | C48: P002 | D48: Keyboard | E48: Electronics | F48: Accessories | G48: S001 | H48: W01 | I48: Sale | J48: 87 | K48: 20393 | L48: 1774191 | M48: 165 | N48: 78 | O48: E008 | P48: C0413 | Q48: Credit | R48: Completed | S48: Regular Transaction | T48: =IF(COUNTIF(T50,Q60)>1,"Duplicate","OK") -> OK | U48: =IF(Table2[[#This Row],[Transaction_ID]]="","Missing","OK") -> OK | V48: =IF(COUNTIF(Table2[[#This Row],[Product_ID]],Table2[[#This Row],[Product_ID]])=0,"Invalid Product","OK") -> OK | W48: =IF(COUNTIF(Table2[[#This Row],[Supplier_ID]],Table2[[#This Row],[Supplier_ID]])=0,"Invalid Supplier","OK") -> OK | X48: =IF(COUNTIF(Table2[[#This Row],[Warehouse_ID]],Table2[[#This Row],[Warehouse_ID]])=0,"Invalid Warehouse","OK") -> OK | Y48: =IF(COUNTIF(Table2[[#This Row],[Employee_ID]],Table2[[#This Row],[Employee_ID]])=0,"Invalid Employee","OK") -> OK | Z48: =IF(Table2[[#This Row],[Stock_After]]=Table2[[#This Row],[Stock_After]]+Table2[[#This Row],[Stock_After]]-Table2[[#This Row],[Stock_After]]-Table2[[#This Row],[Stock_After]]+Table2[[#This Row],[Stock_After]],"OK","Error") -> OK | AA48: =IF(ROUND(Table2[[#This Row],[Total_Value]],2)=ROUND(Table2[[#This Row],[Quantity]]*Table2[[#This Row],[Unit_Price]],2),"OK","Error") -> OK | AB48: =IF(Table2[[#This Row],[Transaction_Type]]="Purchase", IF(Table2[[#This Row],[Stock_After]]=Table2[[#This Row],[Stock_Before]]+Table2[[#This Row],[Quantity]], "OK", "Error"), IF(Table2[[#This Row],[Transaction_Type]]="Return", IF(Table2[[#This Row],[Stock_After]]=Table2[[#This Row],[Stock_Before]]+Table2[[#This Row],[Quantity]], "OK", "Error"), IF(Table2[[#This Row],[Transaction_Type]]="Sale", IF(Table2[[#This Row],[Stock_After]]=MAX(0, Table2[[#This Row],[Stock_Before]]-Table2[[#This Row],[Quantity]]), "OK", "Error"), IF(Table2[[#This Row],[Transaction_Type]]="Adjustment", IF(Table2[[#This Row],[Stock_After]]>=0, "OK", "Error"), "Check")))) -> OK | AC48: =IF(AND(Table2[[#This Row],[Quantity]]>=0,Table2[[#This Row],[Unit_Price]]>=0),"OK","Error") -> OK | AD48: =IF(Table2[[#This Row],[Stock_After]]=0,"Stock-Out",IF(Table2[[#This Row],[Stock_After]]<=10,"Low Stock","Healthy")) -> Healthy
A49: T00048 | B49: 45857 | C49: P010 | D49: File Folder | E49: Stationery | F49: Files | G49: S013 | H49: W04 | I49: Purchase | J49: 59 | K49: 27210 | L49: 1605390 | M49: 372 | N49: 431 | O49: E013 | Q49: Card | R49: Pending | S49: Regular Transaction | T49: =IF(COUNTIF(T51,Q61)>1,"Duplicate","OK") -> OK | U49: =IF(Table2[[#This Row],[Transaction_ID]]="","Missing","OK") -> OK | V49: =IF(COUNTIF(Table2[[#This Row],[Product_ID]],Table2[[#This Row],[Product_ID]])=0,"Invalid Product","OK") -> OK | W49: =IF(COUNTIF(Table2[[#This Row],[Supplier_ID]],Table2[[#This Row],[Supplier_ID]])=0,"Invalid Supplier","OK") -> OK | X49: =IF(COUNTIF(Table2[[#This Row],[Warehouse_ID]],Table2[[#This Row],[Warehouse_ID]])=0,"Invalid Warehouse","OK") -> OK | Y49: =IF(COUNTIF(Table2[[#This Row],[Employee_ID]],Table2[[#This Row],[Employee_ID]])=0,"Invalid Employee","OK") -> OK | Z49: =IF(Table2[[#This Row],[Stock_After]]=Table2[[#This Row],[Stock_After]]+Table2[[#This Row],[Stock_After]]-Table2[[#This Row],[Stock_After]]-Table2[[#This Row],[Stock_After]]+Table2[[#This Row],[Stock_After]],"OK","Error") -> OK | AA49: =IF(ROUND(Table2[[#This Row],[Total_Value]],2)=ROUND(Table2[[#This Row],[Quantity]]*Table2[[#This Row],[Unit_Price]],2),"OK","Error") -> OK | AB49: =IF(Table2[[#This Row],[Transaction_Type]]="Purchase", IF(Table2[[#This Row],[Stock_After]]=Table2[[#This Row],[Stock_Before]]+Table2[[#This Row],[Quantity]], "OK", "Error"), IF(Table2[[#This Row],[Transaction_Type]]="Return", IF(Table2[[#This Row],[Stock_After]]=Table2[[#This Row],[Stock_Before]]+Table2[[#This Row],[Quantity]], "OK", "Error"), IF(Table2[[#This Row],[Transaction_Type]]="Sale", IF(Table2[[#This Row],[Stock_After]]=MAX(0, Table2[[#This Row],[Stock_Before]]-Table2[[#This Row],[Quantity]]), "OK", "Error"), IF(Table2[[#This Row],[Transaction_Type]]="Adjustment", IF(Table2[[#This Row],[Stock_After]]>=0, "OK", "Error"), "Check")))) -> OK | AC49: =IF(AND(Table2[[#This Row],[Quantity]]>=0,Table2[[#This Row],[Unit_Price]]>=0),"OK","Error") -> OK | AD49: =IF(Table2[[#This Row],[Stock_After]]=0,"Stock-Out",IF(Table2[[#This Row],[Stock_After]]<=10,"Low Stock","Healthy")) -> Healthy
A50: T00049 | B50: 45882 | C50: P003 | D50: Mouse | E50: Electronics | F50: Accessories | G50: S006 | H50: W05 | I50: Purchase | J50: 97 | K50: 7035 | L50: 682395 | M50: 448 | N50: 545 | O50: E015 | Q50: Cash | R50: Approved | S50: Regular Transaction | T50: =IF(COUNTIF(T52,Q62)>1,"Duplicate","OK") -> OK | U50: =IF(Table2[[#This Row],[Transaction_ID]]="","Missing","OK") -> OK | V50: =IF(COUNTIF(Table2[[#This Row],[Product_ID]],Table2[[#This Row],[Product_ID]])=0,"Invalid Product","OK") -> OK | W50: =IF(COUNTIF(Table2[[#This Row],[Supplier_ID]],Table2[[#This Row],[Supplier_ID]])=0,"Invalid Supplier","OK") -> OK | X50: =IF(COUNTIF(Table2[[#This Row],[Warehouse_ID]],Table2[[#This Row],[Warehouse_ID]])=0,"Invalid Warehouse","OK") -> OK | Y50: =IF(COUNTIF(Table2[[#This Row],[Employee_ID]],Table2[[#This Row],[Employee_ID]])=0,"Invalid Employee","OK") -> OK | Z50: =IF(Table2[[#This Row],[Stock_After]]=Table2[[#This Row],[Stock_After]]+Table2[[#This Row],[Stock_After]]-Table2[[#This Row],[Stock_After]]-Table2[[#This Row],[Stock_After]]+Table2[[#This Row],[Stock_After]],"OK","Error") -> OK | AA50: =IF(ROUND(Table2[[#This Row],[Total_Value]],2)=ROUND(Table2[[#This Row],[Quantity]]*Table2[[#This Row],[Unit_Price]],2),"OK","Error") -> OK | AB50: =IF(Table2[[#This Row],[Transaction_Type]]="Purchase", IF(Table2[[#This Row],[Stock_After]]=Table2[[#This Row],[Stock_Before]]+Table2[[#This Row],[Quantity]], "OK", "Error"), IF(Table2[[#This Row],[Transaction_Type]]="Return", IF(Table2[[#This Row],[Stock_After]]=Table2[[#This Row],[Stock_Before]]+Table2[[#This Row],[Quantity]], "OK", "Error"), IF(Table2[[#This Row],[Transaction_Type]]="Sale", IF(Table2[[#This Row],[Stock_After]]=MAX(0, Table2[[#This Row],[Stock_Before]]-Table2[[#This Row],[Quantity]]), "OK", "Error"), IF(Table2[[#This Row],[Transaction_Type]]="Adjustment", IF(Table2[[#This Row],[Stock_After]]>=0, "OK", "Error"), "Check")))) -> OK | AC50: =IF(AND(Table2[[#This Row],[Quantity]]>=0,Table2[[#This Row],[Unit_Price]]>=0),"OK","Error") -> OK | AD50: =IF(Table2[[#This Row],[Stock_After]]=0,"Stock-Out",IF(Table2[[#This Row],[Stock_After]]<=10,"Low Stock","Healthy")) -> Healthy
A51: T00050 | B51: 46341 | C51: P009 | D51: Pen | E51: Stationery | F51: Writing | G51: S017 | H51: W05 | I51: Sale | J51: 16 | K51: 29964 | L51: 479424 | M51: 118 | N51: 102 | O51: E020 | P51: C0411 | Q51: UPI | R51: Approved | S51: Regular Transaction | T51: =IF(COUNTIF(T53,Q63)>1,"Duplicate","OK") -> OK | U51: =IF(Table2[[#This Row],[Transaction_ID]]="","Missing","OK") -> OK | V51: =IF(COUNTIF(Table2[[#This Row],[Product_ID]],Table2[[#This Row],[Product_ID]])=0,"Invalid Product","OK") -> OK | W51: =IF(COUNTIF(Table2[[#This Row],[Supplier_ID]],Table2[[#This Row],[Supplier_ID]])=0,"Invalid Supplier","OK") -> OK | X51: =IF(COUNTIF(Table2[[#This Row],[Warehouse_ID]],Table2[[#This Row],[Warehouse_ID]])=0,"Invalid Warehouse","OK") -> OK | Y51: =IF(COUNTIF(Table2[[#This Row],[Employee_ID]],Table2[[#This Row],[Employee_ID]])=0,"Invalid Employee","OK") -> OK | Z51: =IF(Table2[[#This Row],[Stock_After]]=Table2[[#This Row],[Stock_After]]+Table2[[#This Row],[Stock_After]]-Table2[[#This Row],[Stock_After]]-Table2[[#This Row],[Stock_After]]+Table2[[#This Row],[Stock_After]],"OK","Error") -> OK | AA51: =IF(ROUND(Table2[[#This Row],[Total_Value]],2)=ROUND(Table2[[#This Row],[Quantity]]*Table2[[#This Row],[Unit_Price]],2),"OK","Error") -> OK | AB51: =IF(Table2[[#This Row],[Transaction_Type]]="Purchase", IF(Table2[[#This Row],[Stock_After]]=Table2[[#This Row],[Stock_Before]]+Table2[[#This Row],[Quantity]], "OK", "Error"), IF(Table2[[#This Row],[Transaction_Type]]="Return", IF(Table2[[#This Row],[Stock_After]]=Table2[[#This Row],[Stock_Before]]+Table2[[#This Row],[Quantity]], "OK", "Error"), IF(Table2[[#This Row],[Transaction_Type]]="Sale", IF(Table2[[#This Row],[Stock_After]]=MAX(0, Table2[[#This Row],[Stock_Before]]-Table2[[#This Row],[Quantity]]), "OK", "Error"), IF(Table2[[#This Row],[Transaction_Type]]="Adjustment", IF(Table2[[#This Row],[Stock_After]]>=0, "OK", "Error"), "Check")))) -> OK | AC51: =IF(AND(Table2[[#This Row],[Quantity]]>=0,Table2[[#This Row],[Unit_Price]]>=0),"OK","Error") -> OK | AD51: =IF(Table2[[#This Row],[Stock_After]]=0,"Stock-Out",IF(Table2[[#This Row],[Stock_After]]<=10,"Low Stock","Healthy")) -> Healthy
A52: T00051 | B52: 45923 | C52: P008 | D52: Notebook | E52: Stationery | F52: Books | G52: S008 | H52: W03 | I52: Adjustment | J52: 71 | K52: 29273 | L52: 2078383 | M52: 131 | N52: 202 | O52: E017 | Q52: Credit | R52: Approved | S52: Regular Transaction | T52: =IF(COUNTIF(T54,Q64)>1,"Duplicate","OK") -> OK | U52: =IF(Table2[[#This Row],[Transaction_ID]]="","Missing","OK") -> OK | V52: =IF(COUNTIF(Table2[[#This Row],[Product_ID]],Table2[[#This Row],[Product_ID]])=0,"Invalid Product","OK") -> OK | W52: =IF(COUNTIF(Table2[[#This Row],[Supplier_ID]],Table2[[#This Row],[Supplier_ID]])=0,"Invalid Supplier","OK") -> OK | X52: =IF(COUNTIF(Table2[[#This Row],[Warehouse_ID]],Table2[[#This Row],[Warehouse_ID]])=0,"Invalid Warehouse","OK") -> OK | Y52: =IF(COUNTIF(Table2[[#This Row],[Employee_ID]],Table2[[#This Row],[Employee_ID]])=0,"Invalid Employee","OK") -> OK | Z52: =IF(Table2[[#This Row],[Stock_After]]=Table2[[#This Row],[Stock_After]]+Table2[[#This Row],[Stock_After]]-Table2[[#This Row],[Stock_After]]-Table2[[#This Row],[Stock_After]]+Table2[[#This Row],[Stock_After]],"OK","Error") -> OK | AA52: =IF(ROUND(Table2[[#This Row],[Total_Value]],2)=ROUND(Table2[[#This Row],[Quantity]]*Table2[[#This Row],[Unit_Price]],2),"OK","Error") -> OK | AB52: =IF(Table2[[#This Row],[Transaction_Type]]="Purchase", IF(Table2[[#This Row],[Stock_After]]=Table2[[#This Row],[Stock_Before]]+Table2[[#This Row],[Quantity]], "OK", "Error"), IF(Table2[[#This Row],[Transaction_Type]]="Return", IF(Table2[[#This Row],[Stock_After]]=Table2[[#This Row],[Stock_Before]]+Table2[[#This Row],[Quantity]], "OK", "Error"), IF(Table2[[#This Row],[Transaction_Type]]="Sale", IF(Table2[[#This Row],[Stock_After]]=MAX(0, Table2[[#This Row],[Stock_Before]]-Table2[[#This Row],[Quantity]]), "OK", "Error"), IF(Table2[[#This Row],[Transaction_Type]]="Adjustment", IF(Table2[[#This Row],[Stock_After]]>=0, "OK", "Error"), "Check")))) -> OK | AC52: =IF(AND(Table2[[#This Row],[Quantity]]>=0,Table2[[#This Row],[Unit_Price]]>=0),"OK","Error") -> OK | AD52: =IF(Table2[[#This Row],[Stock_After]]=0,"Stock-Out",IF(Table2[[#This Row],[Stock_After]]<=10,"Low Stock","Healthy")) -> Healthy
A53: T00052 | B53: 45898 | C53: P004 | D53: Monitor | E53: Electronics | F53: Displays | G53: S009 | H53: W03 | I53: Return | J53: 57 | K53: 5127 | L53: 292239 | M53: 415 | N53: 472 | O53: E011 | Q53: Cash | R53: Approved | S53: Regular Transaction | T53: =IF(COUNTIF(T55,Q65)>1,"Duplicate","OK") -> OK | U53: =IF(Table2[[#This Row],[Transaction_ID]]="","Missing","OK") -> OK | V53: =IF(COUNTIF(Table2[[#This Row],[Product_ID]],Table2[[#This Row],[Product_ID]])=0,"Invalid Product","OK") -> OK | W53: =IF(COUNTIF(Table2[[#This Row],[Supplier_ID]],Table2[[#This Row],[Supplier_ID]])=0,"Invalid Supplier","OK") -> OK | X53: =IF(COUNTIF(Table2[[#This Row],[Warehouse_ID]],Table2[[#This Row],[Warehouse_ID]])=0,"Invalid Warehouse","OK") -> OK | Y53: =IF(COUNTIF(Table2[[#This Row],[Employee_ID]],Table2[[#This Row],[Employee_ID]])=0,"Invalid Employee","OK") -> OK | Z53: =IF(Table2[[#This Row],[Stock_After]]=Table2[[#This Row],[Stock_After]]+Table2[[#This Row],[Stock_After]]-Table2[[#This Row],[Stock_After]]-Table2[[#This Row],[Stock_After]]+Table2[[#This Row],[Stock_After]],"OK","Error") -> OK | AA53: =IF(ROUND(Table2[[#This Row],[Total_Value]],2)=ROUND(Table2[[#This Row],[Quantity]]*Table2[[#This Row],[Unit_Price]],2),"OK","Error") -> OK | AB53: =IF(Table2[[#This Row],[Transaction_Type]]="Purchase", IF(Table2[[#This Row],[Stock_After]]=Table2[[#This Row],[Stock_Before]]+Table2[[#This Row],[Quantity]], "OK", "Error"), IF(Table2[[#This Row],[Transaction_Type]]="Return", IF(Table2[[#This Row],[Stock_After]]=Table2[[#This Row],[Stock_Before]]+Table2[[#This Row],[Quantity]], "OK", "Error"), IF(Table2[[#This Row],[Transaction_Type]]="Sale", IF(Table2[[#This Row],[Stock_After]]=MAX(0, Table2[[#This Row],[Stock_Before]]-Table2[[#This Row],[Quantity]]), "OK", "Error"), IF(Table2[[#This Row],[Transaction_Type]]="Adjustment", IF(Table2[[#This Row],[Stock_After]]>=0, "OK", "Error"), "Check")))) -> OK | AC53: =IF(AND(Table2[[#This Row],[Quantity]]>=0,Table2[[#This Row],[Unit_Price]]>=0),"OK","Error") -> OK | AD53: =IF(Table2[[#This Row],[Stock_After]]=0,"Stock-Out",IF(Table2[[#This Row],[Stock_After]]<=10,"Low Stock","Healthy")) -> Healthy
A54: T00053 | B54: 45877 | C54: P003 | D54: Mouse | E54: Electronics | F54: Accessories | G54: S003 | H54: W04 | I54: Sale | J54: 30 | K54: 25152 | L54: 754560 | M54: 405 | N54: 375 | O54: E014 | P54: C0079 | Q54: UPI | R54: Pending | S54: Regular Transaction | T54: =IF(COUNTIF(T56,Q66)>1,"Duplicate","OK") -> OK | U54: =IF(Table2[[#This Row],[Transaction_ID]]="","Missing","OK") -> OK | V54: =IF(COUNTIF(Table2[[#This Row],[Product_ID]],Table2[[#This Row],[Product_ID]])=0,"Invalid Product","OK") -> OK | W54: =IF(COUNTIF(Table2[[#This Row],[Supplier_ID]],Table2[[#This Row],[Supplier_ID]])=0,"Invalid Supplier","OK") -> OK | X54: =IF(COUNTIF(Table2[[#This Row],[Warehouse_ID]],Table2[[#This Row],[Warehouse_ID]])=0,"Invalid Warehouse","OK") -> OK | Y54: =IF(COUNTIF(Table2[[#This Row],[Employee_ID]],Table2[[#This Row],[Employee_ID]])=0,"Invalid Employee","OK") -> OK | Z54: =IF(Table2[[#This Row],[Stock_After]]=Table2[[#This Row],[Stock_After]]+Table2[[#This Row],[Stock_After]]-Table2[[#This Row],[Stock_After]]-Table2[[#This Row],[Stock_After]]+Table2[[#This Row],[Stock_After]],"OK","Error") -> OK | AA54: =IF(ROUND(Table2[[#This Row],[Total_Value]],2)=ROUND(Table2[[#This Row],[Quantity]]*Table2[[#This Row],[Unit_Price]],2),"OK","Error") -> OK | AB54: =IF(Table2[[#This Row],[Transaction_Type]]="Purchase", IF(Table2[[#This Row],[Stock_After]]=Table2[[#This Row],[Stock_Before]]+Table2[[#This Row],[Quantity]], "OK", "Error"), IF(Table2[[#This Row],[Transaction_Type]]="Return", IF(Table2[[#This Row],[Stock_After]]=Table2[[#This Row],[Stock_Before]]+Table2[[#This Row],[Quantity]], "OK", "Error"), IF(Table2[[#This Row],[Transaction_Type]]="Sale", IF(Table2[[#This Row],[Stock_After]]=MAX(0, Table2[[#This Row],[Stock_Before]]-Table2[[#This Row],[Quantity]]), "OK", "Error"), IF(Table2[[#This Row],[Transaction_Type]]="Adjustment", IF(Table2[[#This Row],[Stock_After]]>=0, "OK", "Error"), "Check")))) -> OK | AC54: =IF(AND(Table2[[#This Row],[Quantity]]>=0,Table2[[#This Row],[Unit_Price]]>=0),"OK","Error") -> OK | AD54: =IF(Table2[[#This Row],[Stock_After]]=0,"Stock-Out",IF(Table2[[#This Row],[Stock_After]]<=10,"Low Stock","Healthy")) -> Healthy
A55: T00054 | B55: 46256 | C55: P009 | D55: Pen | E55: Stationery | F55: Writing | G55: S001 | H55: W05 | I55: Adjustment | J55: 54 | K55: 4130 | L55: 223020 | M55: 155 | N55: 209 | O55: E013 | Q55: Credit | R55: Approved | S55: Regular Transaction | T55: =IF(COUNTIF(T57,Q67)>1,"Duplicate","OK") -> OK | U55: =IF(Table2[[#This Row],[Transaction_ID]]="","Missing","OK") -> OK | V55: =IF(COUNTIF(Table2[[#This Row],[Product_ID]],Table2[[#This Row],[Product_ID]])=0,"Invalid Product","OK") -> OK | W55: =IF(COUNTIF(Table2[[#This Row],[Supplier_ID]],Table2[[#This Row],[Supplier_ID]])=0,"Invalid Supplier","OK") -> OK | X55: =IF(COUNTIF(Table2[[#This Row],[Warehouse_ID]],Table2[[#This Row],[Warehouse_ID]])=0,"Invalid Warehouse","OK") -> OK | Y55: =IF(COUNTIF(Table2[[#This Row],[Employee_ID]],Table2[[#This Row],[Employee_ID]])=0,"Invalid Employee","OK") -> OK | Z55: =IF(Table2[[#This Row],[Stock_After]]=Table2[[#This Row],[Stock_After]]+Table2[[#This Row],[Stock_After]]-Table2[[#This Row],[Stock_After]]-Table2[[#This Row],[Stock_After]]+Table2[[#This Row],[Stock_After]],"OK","Error") -> OK | AA55: =IF(ROUND(Table2[[#This Row],[Total_Value]],2)=ROUND(Table2[[#This Row],[Quantity]]*Table2[[#This Row],[Unit_Price]],2),"OK","Error") -> OK | AB55: =IF(Table2[[#This Row],[Transaction_Type]]="Purchase", IF(Table2[[#This Row],[Stock_After]]=Table2[[#This Row],[Stock_Before]]+Table2[[#This Row],[Quantity]], "OK", "Error"), IF(Table2[[#This Row],[Transaction_Type]]="Return", IF(Table2[[#This Row],[Stock_After]]=Table2[[#This Row],[Stock_Before]]+Table2[[#This Row],[Quantity]], "OK", "Error"), IF(Table2[[#This Row],[Transaction_Type]]="Sale", IF(Table2[[#This Row],[Stock_After]]=MAX(0, Table2[[#This Row],[Stock_Before]]-Table2[[#This Row],[Quantity]]), "OK", "Error"), IF(Table2[[#This Row],[Transaction_Type]]="Adjustment", IF(Table2[[#This Row],[Stock_After]]>=0, "OK", "Error"), "Check")))) -> OK | AC55: =IF(AND(Table2[[#This Row],[Quantity]]>=0,Table2[[#This Row],[Unit_Price]]>=0),"OK","Error") -> OK | AD55: =IF(Table2[[#This Row],[Stock_After]]=0,"Stock-Out",IF(Table2[[#This Row],[Stock_After]]<=10,"Low Stock","Healthy")) -> Healthy
A56: T00055 | B56: 46209 | C56: P001 | D56: Laptop | E56: Electronics | F56: Computers | G56: S018 | H56: W05 | I56: Return | J56: 39 | K56: 49429 | L56: 1927731 | M56: 249 | N56: 288 | O56: E008 | Q56: Credit | R56: Approved | S56: Regular Transaction | T56: =IF(COUNTIF(T58,Q68)>1,"Duplicate","OK") -> OK | U56: =IF(Table2[[#This Row],[Transaction_ID]]="","Missing","OK") -> OK | V56: =IF(COUNTIF(Table2[[#This Row],[Product_ID]],Table2[[#This Row],[Product_ID]])=0,"Invalid Product","OK") -> OK | W56: =IF(COUNTIF(Table2[[#This Row],[Supplier_ID]],Table2[[#This Row],[Supplier_ID]])=0,"Invalid Supplier","OK") -> OK | X56: =IF(COUNTIF(Table2[[#This Row],[Warehouse_ID]],Table2[[#This Row],[Warehouse_ID]])=0,"Invalid Warehouse","OK") -> OK | Y56: =IF(COUNTIF(Table2[[#This Row],[Employee_ID]],Table2[[#This Row],[Employee_ID]])=0,"Invalid Employee","OK") -> OK | Z56: =IF(Table2[[#This Row],[Stock_After]]=Table2[[#This Row],[Stock_After]]+Table2[[#This Row],[Stock_After]]-Table2[[#This Row],[Stock_After]]-Table2[[#This Row],[Stock_After]]+Table2[[#This Row],[Stock_After]],"OK","Error") -> OK | AA56: =IF(ROUND(Table2[[#This Row],[Total_Value]],2)=ROUND(Table2[[#This Row],[Quantity]]*Table2[[#This Row],[Unit_Price]],2),"OK","Error") -> OK | AB56: =IF(Table2[[#This Row],[Transaction_Type]]="Purchase", IF(Table2[[#This Row],[Stock_After]]=Table2[[#This Row],[Stock_Before]]+Table2[[#This Row],[Quantity]], "OK", "Error"), IF(Table2[[#This Row],[Transaction_Type]]="Return", IF(Table2[[#This Row],[Stock_After]]=Table2[[#This Row],[Stock_Before]]+Table2[[#This Row],[Quantity]], "OK", "Error"), IF(Table2[[#This Row],[Transaction_Type]]="Sale", IF(Table2[[#This Row],[Stock_After]]=MAX(0, Table2[[#This Row],[Stock_Before]]-Table2[[#This Row],[Quantity]]), "OK", "Error"), IF(Table2[[#This Row],[Transaction_Type]]="Adjustment", IF(Table2[[#This Row],[Stock_After]]>=0, "OK", "Error"), "Check")))) -> OK | AC56: =IF(AND(Table2[[#This Row],[Quantity]]>=0,Table2[[#This Row],[Unit_Price]]>=0),"OK","Error") -> OK | AD56: =IF(Table2[[#This Row],[Stock_After]]=0,"Stock-Out",IF(Table2[[#This Row],[Stock_After]]<=10,"Low Stock","Healthy")) -> Healthy
A57: T00056 | B57: 46002 | C57: P004 | D57: Monitor | E57: Electronics | F57: Displays | G57: S013 | H57: W02 | I57: Return | J57: 56 | K57: 31877 | L57: 1785112 | M57: 64 | N57: 120 | O57: E015 | Q57: Card | R57: Approved | S57: Regular Transaction | T57: =IF(COUNTIF(T59,Q69)>1,"Duplicate","OK") -> OK | U57: =IF(Table2[[#This Row],[Transaction_ID]]="","Missing","OK") -> OK | V57: =IF(COUNTIF(Table2[[#This Row],[Product_ID]],Table2[[#This Row],[Product_ID]])=0,"Invalid Product","OK") -> OK | W57: =IF(COUNTIF(Table2[[#This Row],[Supplier_ID]],Table2[[#This Row],[Supplier_ID]])=0,"Invalid Supplier","OK") -> OK | X57: =IF(COUNTIF(Table2[[#This Row],[Warehouse_ID]],Table2[[#This Row],[Warehouse_ID]])=0,"Invalid Warehouse","OK") -> OK | Y57: =IF(COUNTIF(Table2[[#This Row],[Employee_ID]],Table2[[#This Row],[Employee_ID]])=0,"Invalid Employee","OK") -> OK | Z57: =IF(Table2[[#This Row],[Stock_After]]=Table2[[#This Row],[Stock_After]]+Table2[[#This Row],[Stock_After]]-Table2[[#This Row],[Stock_After]]-Table2[[#This Row],[Stock_After]]+Table2[[#This Row],[Stock_After]],"OK","Error") -> OK | AA57: =IF(ROUND(Table2[[#This Row],[Total_Value]],2)=ROUND(Table2[[#This Row],[Quantity]]*Table2[[#This Row],[Unit_Price]],2),"OK","Error") -> OK | AB57: =IF(Table2[[#This Row],[Transaction_Type]]="Purchase", IF(Table2[[#This Row],[Stock_After]]=Table2[[#This Row],[Stock_Before]]+Table2[[#This Row],[Quantity]], "OK", "Error"), IF(Table2[[#This Row],[Transaction_Type]]="Return", IF(Table2[[#This Row],[Stock_After]]=Table2[[#This Row],[Stock_Before]]+Table2[[#This Row],[Quantity]], "OK", "Error"), IF(Table2[[#This Row],[Transaction_Type]]="Sale", IF(Table2[[#This Row],[Stock_After]]=MAX(0, Table2[[#This Row],[Stock_Before]]-Table2[[#This Row],[Quantity]]), "OK", "Error"), IF(Table2[[#This Row],[Transaction_Type]]="Adjustment", IF(Table2[[#This Row],[Stock_After]]>=0, "OK", "Error"), "Check")))) -> OK | AC57: =IF(AND(Table2[[#This Row],[Quantity]]>=0,Table2[[#This Row],[Unit_Price]]>=0),"OK","Error") -> OK | AD57: =IF(Table2[[#This Row],[Stock_After]]=0,"Stock-Out",IF(Table2[[#This Row],[Stock_After]]<=10,"Low Stock","Healthy")) -> Healthy
A58: T00057 | B58: 45685 | C58: P010 | D58: File Folder | E58: Stationery | F58: Files | G58: S003 | H58: W04 | I58: Purchase | J58: 51 | K58: 38840 | L58: 1980840 | M58: 338 | N58: 389 | O58: E005 | Q58: Credit | R58: Pending | S58: Regular Transaction | T58: =IF(COUNTIF(T60,Q70)>1,"Duplicate","OK") -> OK | U58: =IF(Table2[[#This Row],[Transaction_ID]]="","Missing","OK") -> OK | V58: =IF(COUNTIF(Table2[[#This Row],[Product_ID]],Table2[[#This Row],[Product_ID]])=0,"Invalid Product","OK") -> OK | W58: =IF(COUNTIF(Table2[[#This Row],[Supplier_ID]],Table2[[#This Row],[Supplier_ID]])=0,"Invalid Supplier","OK") -> OK | X58: =IF(COUNTIF(Table2[[#This Row],[Warehouse_ID]],Table2[[#This Row],[Warehouse_ID]])=0,"Invalid Warehouse","OK") -> OK | Y58: =IF(COUNTIF(Table2[[#This Row],[Employee_ID]],Table2[[#This Row],[Employee_ID]])=0,"Invalid Employee","OK") -> OK | Z58: =IF(Table2[[#This Row],[Stock_After]]=Table2[[#This Row],[Stock_After]]+Table2[[#This Row],[Stock_After]]-Table2[[#This Row],[Stock_After]]-Table2[[#This Row],[Stock_After]]+Table2[[#This Row],[Stock_After]],"OK","Error") -> OK | AA58: =IF(ROUND(Table2[[#This Row],[Total_Value]],2)=ROUND(Table2[[#This Row],[Quantity]]*Table2[[#This Row],[Unit_Price]],2),"OK","Error") -> OK | AB58: =IF(Table2[[#This Row],[Transaction_Type]]="Purchase", IF(Table2[[#This Row],[Stock_After]]=Table2[[#This Row],[Stock_Before]]+Table2[[#This Row],[Quantity]], "OK", "Error"), IF(Table2[[#This Row],[Transaction_Type]]="Return", IF(Table2[[#This Row],[Stock_After]]=Table2[[#This Row],[Stock_Before]]+Table2[[#This Row],[Quantity]], "OK", "Error"), IF(Table2[[#This Row],[Transaction_Type]]="Sale", IF(Table2[[#This Row],[Stock_After]]=MAX(0, Table2[[#This Row],[Stock_Before]]-Table2[[#This Row],[Quantity]]), "OK", "Error"), IF(Table2[[#This Row],[Transaction_Type]]="Adjustment", IF(Table2[[#This Row],[Stock_After]]>=0, "OK", "Error"), "Check")))) -> OK | AC58: =IF(AND(Table2[[#This Row],[Quantity]]>=0,Table2[[#This Row],[Unit_Price]]>=0),"OK","Error") -> OK | AD58: =IF(Table2[[#This Row],[Stock_After]]=0,"Stock-Out",IF(Table2[[#This Row],[Stock_After]]<=10,"Low Stock","Healthy")) -> Healthy
A59: T00058 | B59: 46123 | C59: P003 | D59: Mouse | E59: Electronics | F59: Accessories | G59: S011 | H59: W03 | I59: Purchase | J59: 34 | K59: 24894 | L59: 846396 | M59: 217 | N59: 251 | O59: E013 | Q59: UPI | R59: Completed | S59: Regular Transaction | T59: =IF(COUNTIF(T61,Q71)>1,"Duplicate","OK") -> OK | U59: =IF(Table2[[#This Row],[Transaction_ID]]="","Missing","OK") -> OK | V59: =IF(COUNTIF(Table2[[#This Row],[Product_ID]],Table2[[#This Row],[Product_ID]])=0,"Invalid Product","OK") -> OK | W59: =IF(COUNTIF(Table2[[#This Row],[Supplier_ID]],Table2[[#This Row],[Supplier_ID]])=0,"Invalid Supplier","OK") -> OK | X59: =IF(COUNTIF(Table2[[#This Row],[Warehouse_ID]],Table2[[#This Row],[Warehouse_ID]])=0,"Invalid Warehouse","OK") -> OK | Y59: =IF(COUNTIF(Table2[[#This Row],[Employee_ID]],Table2[[#This Row],[Employee_ID]])=0,"Invalid Employee","OK") -> OK | Z59: =IF(Table2[[#This Row],[Stock_After]]=Table2[[#This Row],[Stock_After]]+Table2[[#This Row],[Stock_After]]-Table2[[#This Row],[Stock_After]]-Table2[[#This Row],[Stock_After]]+Table2[[#This Row],[Stock_After]],"OK","Error") -> OK | AA59: =IF(ROUND(Table2[[#This Row],[Total_Value]],2)=ROUND(Table2[[#This Row],[Quantity]]*Table2[[#This Row],[Unit_Price]],2),"OK","Error") -> OK | AB59: =IF(Table2[[#This Row],[Transaction_Type]]="Purchase", IF(Table2[[#This Row],[Stock_After]]=Table2[[#This Row],[Stock_Before]]+Table2[[#This Row],[Quantity]], "OK", "Error"), IF(Table2[[#This Row],[Transaction_Type]]="Return", IF(Table2[[#This Row],[Stock_After]]=Table2[[#This Row],[Stock_Before]]+Table2[[#This Row],[Quantity]], "OK", "Error"), IF(Table2[[#This Row],[Transaction_Type]]="Sale", IF(Table2[[#This Row],[Stock_After]]=MAX(0, Table2[[#This Row],[Stock_Before]]-Table2[[#This Row],[Quantity]]), "OK", "Error"), IF(Table2[[#This Row],[Transaction_Type]]="Adjustment", IF(Table2[[#This Row],[Stock_After]]>=0, "OK", "Error"), "Check")))) -> OK | AC59: =IF(AND(Table2[[#This Row],[Quantity]]>=0,Table2[[#This Row],[Unit_Price]]>=0),"OK","Error") -> OK | AD59: =IF(Table2[[#This Row],[Stock_After]]=0,"Stock-Out",IF(Table2[[#This Row],[Stock_After]]<=10,"Low Stock","Healthy")) -> Healthy
A60: T00059 | B60: 46210 | C60: P007 | D60: Office Desk | E60: Furniture | F60: Desks | G60: S002 | H60: W03 | I60: Return | J60: 11 | K60: 30872 | L60: 339592 | M60: 59 | N60: 70 | O60: E008 | Q60: Cash | R60: Pending | S60: Regular Transaction | T60: =IF(COUNTIF(T62,Q72)>1,"Duplicate","OK") -> OK | U60: =IF(Table2[[#This Row],[Transaction_ID]]="","Missing","OK") -> OK | V60: =IF(COUNTIF(Table2[[#This Row],[Product_ID]],Table2[[#This Row],[Product_ID]])=0,"Invalid Product","OK") -> OK | W60: =IF(COUNTIF(Table2[[#This Row],[Supplier_ID]],Table2[[#This Row],[Supplier_ID]])=0,"Invalid Supplier","OK") -> OK | X60: =IF(COUNTIF(Table2[[#This Row],[Warehouse_ID]],Table2[[#This Row],[Warehouse_ID]])=0,"Invalid Warehouse","OK") -> OK | Y60: =IF(COUNTIF(Table2[[#This Row],[Employee_ID]],Table2[[#This Row],[Employee_ID]])=0,"Invalid Employee","OK") -> OK | Z60: =IF(Table2[[#This Row],[Stock_After]]=Table2[[#This Row],[Stock_After]]+Table2[[#This Row],[Stock_After]]-Table2[[#This Row],[Stock_After]]-Table2[[#This Row],[Stock_After]]+Table2[[#This Row],[Stock_After]],"OK","Error") -> OK | AA60: =IF(ROUND(Table2[[#This Row],[Total_Value]],2)=ROUND(Table2[[#This Row],[Quantity]]*Table2[[#This Row],[Unit_Price]],2),"OK","Error") -> OK | AB60: =IF(Table2[[#This Row],[Transaction_Type]]="Purchase", IF(Table2[[#This Row],[Stock_After]]=Table2[[#This Row],[Stock_Before]]+Table2[[#This Row],[Quantity]], "OK", "Error"), IF(Table2[[#This Row],[Transaction_Type]]="Return", IF(Table2[[#This Row],[Stock_After]]=Table2[[#This Row],[Stock_Before]]+Table2[[#This Row],[Quantity]], "OK", "Error"), IF(Table2[[#This Row],[Transaction_Type]]="Sale", IF(Table2[[#This Row],[Stock_After]]=MAX(0, Table2[[#This Row],[Stock_Before]]-Table2[[#This Row],[Quantity]]), "OK", "Error"), IF(Table2[[#This Row],[Transaction_Type]]="Adjustment", IF(Table2[[#This Row],[Stock_After]]>=0, "OK", "Error"), "Check")))) -> OK | AC60: =IF(AND(Table2[[#This Row],[Quantity]]>=0,Table2[[#This Row],[Unit_Price]]>=0),"OK","Error") -> OK | AD60: =IF(Table2[[#This Row],[Stock_After]]=0,"Stock-Out",IF(Table2[[#This Row],[Stock_After]]<=10,"Low Stock","Healthy")) -> Healthy
A61: T00060 | B61: 46294 | C61: P001 | D61: Laptop | E61: Electronics | F61: Computers | G61: S005 | H61: W02 | I61: Purchase | J61: 32 | K61: 13115 | L61: 419680 | M61: 479 | N61: 511 | O61: E005 | Q61: Credit | R61: Completed | S61: Regular Transaction | T61: =IF(COUNTIF(T63,Q73)>1,"Duplicate","OK") -> OK | U61: =IF(Table2[[#This Row],[Transaction_ID]]="","Missing","OK") -> OK | V61: =IF(COUNTIF(Table2[[#This Row],[Product_ID]],Table2[[#This Row],[Product_ID]])=0,"Invalid Product","OK") -> OK | W61: =IF(COUNTIF(Table2[[#This Row],[Supplier_ID]],Table2[[#This Row],[Supplier_ID]])=0,"Invalid Supplier","OK") -> OK | X61: =IF(COUNTIF(Table2[[#This Row],[Warehouse_ID]],Table2[[#This Row],[Warehouse_ID]])=0,"Invalid Warehouse","OK") -> OK | Y61: =IF(COUNTIF(Table2[[#This Row],[Employee_ID]],Table2[[#This Row],[Employee_ID]])=0,"Invalid Employee","OK") -> OK | Z61: =IF(Table2[[#This Row],[Stock_After]]=Table2[[#This Row],[Stock_After]]+Table2[[#This Row],[Stock_After]]-Table2[[#This Row],[Stock_After]]-Table2[[#This Row],[Stock_After]]+Table2[[#This Row],[Stock_After]],"OK","Error") -> OK | AA61: =IF(ROUND(Table2[[#This Row],[Total_Value]],2)=ROUND(Table2[[#This Row],[Quantity]]*Table2[[#This Row],[Unit_Price]],2),"OK","Error") -> OK | AB61: =IF(Table2[[#This Row],[Transaction_Type]]="Purchase", IF(Table2[[#This Row],[Stock_After]]=Table2[[#This Row],[Stock_Before]]+Table2[[#This Row],[Quantity]], "OK", "Error"), IF(Table2[[#This Row],[Transaction_Type]]="Return", IF(Table2[[#This Row],[Stock_After]]=Table2[[#This Row],[Stock_Before]]+Table2[[#This Row],[Quantity]], "OK", "Error"), IF(Table2[[#This Row],[Transaction_Type]]="Sale", IF(Table2[[#This Row],[Stock_After]]=MAX(0, Table2[[#This Row],[Stock_Before]]-Table2[[#This Row],[Quantity]]), "OK", "Error"), IF(Table2[[#This Row],[Transaction_Type]]="Adjustment", IF(Table2[[#This Row],[Stock_After]]>=0, "OK", "Error"), "Check")))) -> OK | AC61: =IF(AND(Table2[[#This Row],[Quantity]]>=0,Table2[[#This Row],[Unit_Price]]>=0),"OK","Error") -> OK | AD61: =IF(Table2[[#This Row],[Stock_After]]=0,"Stock-Out",IF(Table2[[#This Row],[Stock_After]]<=10,"Low Stock","Healthy")) -> Healthy
A62: T00061 | B62: 45829 | C62: P002 | D62: Keyboard | E62: Electronics | F62: Accessories | G62: S020 | H62: W05 | I62: Sale | J62: 60 | K62: 45890 | L62: 2753400 | M62: 181 | N62: 121 | O62: E004 | P62: C0393 | Q62: Card | R62: Approved | S62: Regular Transaction | T62: =IF(COUNTIF(T64,Q74)>1,"Duplicate","OK") -> OK | U62: =IF(Table2[[#This Row],[Transaction_ID]]="","Missing","OK") -> OK | V62: =IF(COUNTIF(Table2[[#This Row],[Product_ID]],Table2[[#This Row],[Product_ID]])=0,"Invalid Product","OK") -> OK | W62: =IF(COUNTIF(Table2[[#This Row],[Supplier_ID]],Table2[[#This Row],[Supplier_ID]])=0,"Invalid Supplier","OK") -> OK | X62: =IF(COUNTIF(Table2[[#This Row],[Warehouse_ID]],Table2[[#This Row],[Warehouse_ID]])=0,"Invalid Warehouse","OK") -> OK | Y62: =IF(COUNTIF(Table2[[#This Row],[Employee_ID]],Table2[[#This Row],[Employee_ID]])=0,"Invalid Employee","OK") -> OK | Z62: =IF(Table2[[#This Row],[Stock_After]]=Table2[[#This Row],[Stock_After]]+Table2[[#This Row],[Stock_After]]-Table2[[#This Row],[Stock_After]]-Table2[[#This Row],[Stock_After]]+Table2[[#This Row],[Stock_After]],"OK","Error") -> OK | AA62: =IF(ROUND(Table2[[#This Row],[Total_Value]],2)=ROUND(Table2[[#This Row],[Quantity]]*Table2[[#This Row],[Unit_Price]],2),"OK","Error") -> OK | AB62: =IF(Table2[[#This Row],[Transaction_Type]]="Purchase", IF(Table2[[#This Row],[Stock_After]]=Table2[[#This Row],[Stock_Before]]+Table2[[#This Row],[Quantity]], "OK", "Error"), IF(Table2[[#This Row],[Transaction_Type]]="Return", IF(Table2[[#This Row],[Stock_After]]=Table2[[#This Row],[Stock_Before]]+Table2[[#This Row],[Quantity]], "OK", "Error"), IF(Table2[[#This Row],[Transaction_Type]]="Sale", IF(Table2[[#This Row],[Stock_After]]=MAX(0, Table2[[#This Row],[Stock_Before]]-Table2[[#This Row],[Quantity]]), "OK", "Error"), IF(Table2[[#This Row],[Transaction_Type]]="Adjustment", IF(Table2[[#This Row],[Stock_After]]>=0, "OK", "Error"), "Check")))) -> OK | AC62: =IF(AND(Table2[[#This Row],[Quantity]]>=0,Table2[[#This Row],[Unit_Price]]>=0),"OK","Error") -> OK | AD62: =IF(Table2[[#This Row],[Stock_After]]=0,"Stock-Out",IF(Table2[[#This Row],[Stock_After]]<=10,"Low Stock","Healthy")) -> Healthy
A63: T00062 | B63: 46351 | C63: P005 | D63: Printer | E63: Electronics | F63: Printers | G63: S013 | H63: W04 | I63: Purchase | J63: 75 | K63: 1732 | L63: 129900 | M63: 209 | N63: 284 | O63: E007 | Q63: Cash | R63: Pending | S63: Regular Transaction | T63: =IF(COUNTIF(T65,Q75)>1,"Duplicate","OK") -> OK | U63: =IF(Table2[[#This Row],[Transaction_ID]]="","Missing","OK") -> OK | V63: =IF(COUNTIF(Table2[[#This Row],[Product_ID]],Table2[[#This Row],[Product_ID]])=0,"Invalid Product","OK") -> OK | W63: =IF(COUNTIF(Table2[[#This Row],[Supplier_ID]],Table2[[#This Row],[Supplier_ID]])=0,"Invalid Supplier","OK") -> OK | X63: =IF(COUNTIF(Table2[[#This Row],[Warehouse_ID]],Table2[[#This Row],[Warehouse_ID]])=0,"Invalid Warehouse","OK") -> OK | Y63: =IF(COUNTIF(Table2[[#This Row],[Employee_ID]],Table2[[#This Row],[Employee_ID]])=0,"Invalid Employee","OK") -> OK | Z63: =IF(Table2[[#This Row],[Stock_After]]=Table2[[#This Row],[Stock_After]]+Table2[[#This Row],[Stock_After]]-Table2[[#This Row],[Stock_After]]-Table2[[#This Row],[Stock_After]]+Table2[[#This Row],[Stock_After]],"OK","Error") -> OK | AA63: =IF(ROUND(Table2[[#This Row],[Total_Value]],2)=ROUND(Table2[[#This Row],[Quantity]]*Table2[[#This Row],[Unit_Price]],2),"OK","Error") -> OK | AB63: =IF(Table2[[#This Row],[Transaction_Type]]="Purchase", IF(Table2[[#This Row],[Stock_After]]=Table2[[#This Row],[Stock_Before]]+Table2[[#This Row],[Quantity]], "OK", "Error"), IF(Table2[[#This Row],[Transaction_Type]]="Return", IF(Table2[[#This Row],[Stock_After]]=Table2[[#This Row],[Stock_Before]]+Table2[[#This Row],[Quantity]], "OK", "Error"), IF(Table2[[#This Row],[Transaction_Type]]="Sale", IF(Table2[[#This Row],[Stock_After]]=MAX(0, Table2[[#This Row],[Stock_Before]]-Table2[[#This Row],[Quantity]]), "OK", "Error"), IF(Table2[[#This Row],[Transaction_Type]]="Adjustment", IF(Table2[[#This Row],[Stock_After]]>=0, "OK", "Error"), "Check")))) -> OK | AC63: =IF(AND(Table2[[#This Row],[Quantity]]>=0,Table2[[#This Row],[Unit_Price]]>=0),"OK","Error") -> OK | AD63: =IF(Table2[[#This Row],[Stock_After]]=0,"Stock-Out",IF(Table2[[#This Row],[Stock_After]]<=10,"Low Stock","Healthy")) -> Healthy
A64: T00063 | B64: 46272 | C64: P010 | D64: File Folder | E64: Stationery | F64: Files | G64: S004 | H64: W05 | I64: Sale | J64: 14 | K64: 45741 | L64: 640374 | M64: 445 | N64: 431 | O64: E002 | P64: C0155 | Q64: UPI | R64: Pending | S64: Regular Transaction | T64: =IF(COUNTIF(T66,Q76)>1,"Duplicate","OK") -> OK | U64: =IF(Table2[[#This Row],[Transaction_ID]]="","Missing","OK") -> OK | V64: =IF(COUNTIF(Table2[[#This Row],[Product_ID]],Table2[[#This Row],[Product_ID]])=0,"Invalid Product","OK") -> OK | W64: =IF(COUNTIF(Table2[[#This Row],[Supplier_ID]],Table2[[#This Row],[Supplier_ID]])=0,"Invalid Supplier","OK") -> OK | X64: =IF(COUNTIF(Table2[[#This Row],[Warehouse_ID]],Table2[[#This Row],[Warehouse_ID]])=0,"Invalid Warehouse","OK") -> OK | Y64: =IF(COUNTIF(Table2[[#This Row],[Employee_ID]],Table2[[#This Row],[Employee_ID]])=0,"Invalid Employee","OK") -> OK | Z64: =IF(Table2[[#This Row],[Stock_After]]=Table2[[#This Row],[Stock_After]]+Table2[[#This Row],[Stock_After]]-Table2[[#This Row],[Stock_After]]-Table2[[#This Row],[Stock_After]]+Table2[[#This Row],[Stock_After]],"OK","Error") -> OK | AA64: =IF(ROUND(Table2[[#This Row],[Total_Value]],2)=ROUND(Table2[[#This Row],[Quantity]]*Table2[[#This Row],[Unit_Price]],2),"OK","Error") -> OK | AB64: =IF(Table2[[#This Row],[Transaction_Type]]="Purchase", IF(Table2[[#This Row],[Stock_After]]=Table2[[#This Row],[Stock_Before]]+Table2[[#This Row],[Quantity]], "OK", "Error"), IF(Table2[[#This Row],[Transaction_Type]]="Return", IF(Table2[[#This Row],[Stock_After]]=Table2[[#This Row],[Stock_Before]]+Table2[[#This Row],[Quantity]], "OK", "Error"), IF(Table2[[#This Row],[Transaction_Type]]="Sale", IF(Table2[[#This Row],[Stock_After]]=MAX(0, Table2[[#This Row],[Stock_Before]]-Table2[[#This Row],[Quantity]]), "OK", "Error"), IF(Table2[[#This Row],[Transaction_Type]]="Adjustment", IF(Table2[[#This Row],[Stock_After]]>=0, "OK", "Error"), "Check")))) -> OK | AC64: =IF(AND(Table2[[#This Row],[Quantity]]>=0,Table2[[#This Row],[Unit_Price]]>=0),"OK","Error") -> OK | AD64: =IF(Table2[[#This Row],[Stock_After]]=0,"Stock-Out",IF(Table2[[#This Row],[Stock_After]]<=10,"Low Stock","Healthy")) -> Healthy
A65: T00064 | B65: 46088 | C65: P009 | D65: Pen | E65: Stationery | F65: Writing | G65: S016 | H65: W01 | I65: Adjustment | J65: 85 | K65: 24335 | L65: 2068475 | M65: 85 | N65: 170 | O65: E014 | Q65: UPI | R65: Completed | S65: Regular Transaction | T65: =IF(COUNTIF(T67,Q77)>1,"Duplicate","OK") -> OK | U65: =IF(Table2[[#This Row],[Transaction_ID]]="","Missing","OK") -> OK | V65: =IF(COUNTIF(Table2[[#This Row],[Product_ID]],Table2[[#This Row],[Product_ID]])=0,"Invalid Product","OK") -> OK | W65: =IF(COUNTIF(Table2[[#This Row],[Supplier_ID]],Table2[[#This Row],[Supplier_ID]])=0,"Invalid Supplier","OK") -> OK | X65: =IF(COUNTIF(Table2[[#This Row],[Warehouse_ID]],Table2[[#This Row],[Warehouse_ID]])=0,"Invalid Warehouse","OK") -> OK | Y65: =IF(COUNTIF(Table2[[#This Row],[Employee_ID]],Table2[[#This Row],[Employee_ID]])=0,"Invalid Employee","OK") -> OK | Z65: =IF(Table2[[#This Row],[Stock_After]]=Table2[[#This Row],[Stock_After]]+Table2[[#This Row],[Stock_After]]-Table2[[#This Row],[Stock_After]]-Table2[[#This Row],[Stock_After]]+Table2[[#This Row],[Stock_After]],"OK","Error") -> OK | AA65: =IF(ROUND(Table2[[#This Row],[Total_Value]],2)=ROUND(Table2[[#This Row],[Quantity]]*Table2[[#This Row],[Unit_Price]],2),"OK","Error") -> OK | AB65: =IF(Table2[[#This Row],[Transaction_Type]]="Purchase", IF(Table2[[#This Row],[Stock_After]]=Table2[[#This Row],[Stock_Before]]+Table2[[#This Row],[Quantity]], "OK", "Error"), IF(Table2[[#This Row],[Transaction_Type]]="Return", IF(Table2[[#This Row],[Stock_After]]=Table2[[#This Row],[Stock_Before]]+Table2[[#This Row],[Quantity]], "OK", "Error"), IF(Table2[[#This Row],[Transaction_Type]]="Sale", IF(Table2[[#This Row],[Stock_After]]=MAX(0, Table2[[#This Row],[Stock_Before]]-Table2[[#This Row],[Quantity]]), "OK", "Error"), IF(Table2[[#This Row],[Transaction_Type]]="Adjustment", IF(Table2[[#This Row],[Stock_After]]>=0, "OK", "Error"), "Check")))) -> OK | AC65: =IF(AND(Table2[[#This Row],[Quantity]]>=0,Table2[[#This Row],[Unit_Price]]>=0),"OK","Error") -> OK | AD65: =IF(Table2[[#This Row],[Stock_After]]=0,"Stock-Out",IF(Table2[[#This Row],[Stock_After]]<=10,"Low Stock","Healthy")) -> Healthy
A66: T00065 | B66: 45934 | C66: P008 | D66: Notebook | E66: Stationery | F66: Books | G66: S020 | H66: W05 | I66: Sale | J66: 56 | K66: 11593 | L66: 649208 | M66: 425 | N66: 369 | O66: E016 | P66: C0268 | Q66: Credit | R66: Pending | S66: Regular Transaction | T66: =IF(COUNTIF(T68,Q78)>1,"Duplicate","OK") -> OK | U66: =IF(Table2[[#This Row],[Transaction_ID]]="","Missing","OK") -> OK | V66: =IF(COUNTIF(Table2[[#This Row],[Product_ID]],Table2[[#This Row],[Product_ID]])=0,"Invalid Product","OK") -> OK | W66: =IF(COUNTIF(Table2[[#This Row],[Supplier_ID]],Table2[[#This Row],[Supplier_ID]])=0,"Invalid Supplier","OK") -> OK | X66: =IF(COUNTIF(Table2[[#This Row],[Warehouse_ID]],Table2[[#This Row],[Warehouse_ID]])=0,"Invalid Warehouse","OK") -> OK | Y66: =IF(COUNTIF(Table2[[#This Row],[Employee_ID]],Table2[[#This Row],[Employee_ID]])=0,"Invalid Employee","OK") -> OK | Z66: =IF(Table2[[#This Row],[Stock_After]]=Table2[[#This Row],[Stock_After]]+Table2[[#This Row],[Stock_After]]-Table2[[#This Row],[Stock_After]]-Table2[[#This Row],[Stock_After]]+Table2[[#This Row],[Stock_After]],"OK","Error") -> OK | AA66: =IF(ROUND(Table2[[#This Row],[Total_Value]],2)=ROUND(Table2[[#This Row],[Quantity]]*Table2[[#This Row],[Unit_Price]],2),"OK","Error") -> OK | AB66: =IF(Table2[[#This Row],[Transaction_Type]]="Purchase", IF(Table2[[#This Row],[Stock_After]]=Table2[[#This Row],[Stock_Before]]+Table2[[#This Row],[Quantity]], "OK", "Error"), IF(Table2[[#This Row],[Transaction_Type]]="Return", IF(Table2[[#This Row],[Stock_After]]=Table2[[#This Row],[Stock_Before]]+Table2[[#This Row],[Quantity]], "OK", "Error"), IF(Table2[[#This Row],[Transaction_Type]]="Sale", IF(Table2[[#This Row],[Stock_After]]=MAX(0, Table2[[#This Row],[Stock_Before]]-Table2[[#This Row],[Quantity]]), "OK", "Error"), IF(Table2[[#This Row],[Transaction_Type]]="Adjustment", IF(Table2[[#This Row],[Stock_After]]>=0, "OK", "Error"), "Check")))) -> OK | AC66: =IF(AND(Table2[[#This Row],[Quantity]]>=0,Table2[[#This Row],[Unit_Price]]>=0),"OK","Error") -> OK | AD66: =IF(Table2[[#This Row],[Stock_After]]=0,"Stock-Out",IF(Table2[[#This Row],[Stock_After]]<=10,"Low Stock","Healthy")) -> Healthy
A67: T00066 | B67: 45943 | C67: P007 | D67: Office Desk | E67: Furniture | F67: Desks | G67: S015 | H67: W02 | I67: Return | J67: 42 | K67: 16138 | L67: 677796 | M67: 475 | N67: 517 | O67: E015 | Q67: Credit | R67: Completed | S67: Regular Transaction | T67: =IF(COUNTIF(T69,Q79)>1,"Duplicate","OK") -> OK | U67: =IF(Table2[[#This Row],[Transaction_ID]]="","Missing","OK") -> OK | V67: =IF(COUNTIF(Table2[[#This Row],[Product_ID]],Table2[[#This Row],[Product_ID]])=0,"Invalid Product","OK") -> OK | W67: =IF(COUNTIF(Table2[[#This Row],[Supplier_ID]],Table2[[#This Row],[Supplier_ID]])=0,"Invalid Supplier","OK") -> OK | X67: =IF(COUNTIF(Table2[[#This Row],[Warehouse_ID]],Table2[[#This Row],[Warehouse_ID]])=0,"Invalid Warehouse","OK") -> OK | Y67: =IF(COUNTIF(Table2[[#This Row],[Employee_ID]],Table2[[#This Row],[Employee_ID]])=0,"Invalid Employee","OK") -> OK | Z67: =IF(Table2[[#This Row],[Stock_After]]=Table2[[#This Row],[Stock_After]]+Table2[[#This Row],[Stock_After]]-Table2[[#This Row],[Stock_After]]-Table2[[#This Row],[Stock_After]]+Table2[[#This Row],[Stock_After]],"OK","Error") -> OK | AA67: =IF(ROUND(Table2[[#This Row],[Total_Value]],2)=ROUND(Table2[[#This Row],[Quantity]]*Table2[[#This Row],[Unit_Price]],2),"OK","Error") -> OK | AB67: =IF(Table2[[#This Row],[Transaction_Type]]="Purchase", IF(Table2[[#This Row],[Stock_After]]=Table2[[#This Row],[Stock_Before]]+Table2[[#This Row],[Quantity]], "OK", "Error"), IF(Table2[[#This Row],[Transaction_Type]]="Return", IF(Table2[[#This Row],[Stock_After]]=Table2[[#This Row],[Stock_Before]]+Table2[[#This Row],[Quantity]], "OK", "Error"), IF(Table2[[#This Row],[Transaction_Type]]="Sale", IF(Table2[[#This Row],[Stock_After]]=MAX(0, Table2[[#This Row],[Stock_Before]]-Table2[[#This Row],[Quantity]]), "OK", "Error"), IF(Table2[[#This Row],[Transaction_Type]]="Adjustment", IF(Table2[[#This Row],[Stock_After]]>=0, "OK", "Error"), "Check")))) -> OK | AC67: =IF(AND(Table2[[#This Row],[Quantity]]>=0,Table2[[#This Row],[Unit_Price]]>=0),"OK","Error") -> OK | AD67: =IF(Table2[[#This Row],[Stock_After]]=0,"Stock-Out",IF(Table2[[#This Row],[Stock_After]]<=10,"Low Stock","Healthy")) -> Healthy
A68: T00067 | B68: 45875 | C68: P006 | D68: Office Chair | E68: Furniture | F68: Chairs | G68: S012 | H68: W03 | I68: Purchase | J68: 64 | K68: 21350 | L68: 1366400 | M68: 143 | N68: 207 | O68: E011 | Q68: UPI | R68: Approved | S68: Regular Transaction | T68: =IF(COUNTIF(T70,Q80)>1,"Duplicate","OK") -> OK | U68: =IF(Table2[[#This Row],[Transaction_ID]]="","Missing","OK") -> OK | V68: =IF(COUNTIF(Table2[[#This Row],[Product_ID]],Table2[[#This Row],[Product_ID]])=0,"Invalid Product","OK") -> OK | W68: =IF(COUNTIF(Table2[[#This Row],[Supplier_ID]],Table2[[#This Row],[Supplier_ID]])=0,"Invalid Supplier","OK") -> OK | X68: =IF(COUNTIF(Table2[[#This Row],[Warehouse_ID]],Table2[[#This Row],[Warehouse_ID]])=0,"Invalid Warehouse","OK") -> OK | Y68: =IF(COUNTIF(Table2[[#This Row],[Employee_ID]],Table2[[#This Row],[Employee_ID]])=0,"Invalid Employee","OK") -> OK | Z68: =IF(Table2[[#This Row],[Stock_After]]=Table2[[#This Row],[Stock_After]]+Table2[[#This Row],[Stock_After]]-Table2[[#This Row],[Stock_After]]-Table2[[#This Row],[Stock_After]]+Table2[[#This Row],[Stock_After]],"OK","Error") -> OK | AA68: =IF(ROUND(Table2[[#This Row],[Total_Value]],2)=ROUND(Table2[[#This Row],[Quantity]]*Table2[[#This Row],[Unit_Price]],2),"OK","Error") -> OK | AB68: =IF(Table2[[#This Row],[Transaction_Type]]="Purchase", IF(Table2[[#This Row],[Stock_After]]=Table2[[#This Row],[Stock_Before]]+Table2[[#This Row],[Quantity]], "OK", "Error"), IF(Table2[[#This Row],[Transaction_Type]]="Return", IF(Table2[[#This Row],[Stock_After]]=Table2[[#This Row],[Stock_Before]]+Table2[[#This Row],[Quantity]], "OK", "Error"), IF(Table2[[#This Row],[Transaction_Type]]="Sale", IF(Table2[[#This Row],[Stock_After]]=MAX(0, Table2[[#This Row],[Stock_Before]]-Table2[[#This Row],[Quantity]]), "OK", "Error"), IF(Table2[[#This Row],[Transaction_Type]]="Adjustment", IF(Table2[[#This Row],[Stock_After]]>=0, "OK", "Error"), "Check")))) -> OK | AC68: =IF(AND(Table2[[#This Row],[Quantity]]>=0,Table2[[#This Row],[Unit_Price]]>=0),"OK","Error") -> OK | AD68: =IF(Table2[[#This Row],[Stock_After]]=0,"Stock-Out",IF(Table2[[#This Row],[Stock_After]]<=10,"Low Stock","Healthy")) -> Healthy
A69: T00068 | B69: 45745 | C69: P010 | D69: File Folder | E69: Stationery | F69: Files | G69: S008 | H69: W04 | I69: Return | J69: 72 | K69: 715 | L69: 51480 | M69: 314 | N69: 386 | O69: E016 | Q69: Card | R69: Completed | S69: Regular Transaction | T69: =IF(COUNTIF(T71,Q81)>1,"Duplicate","OK") -> OK | U69: =IF(Table2[[#This Row],[Transaction_ID]]="","Missing","OK") -> OK | V69: =IF(COUNTIF(Table2[[#This Row],[Product_ID]],Table2[[#This Row],[Product_ID]])=0,"Invalid Product","OK") -> OK | W69: =IF(COUNTIF(Table2[[#This Row],[Supplier_ID]],Table2[[#This Row],[Supplier_ID]])=0,"Invalid Supplier","OK") -> OK | X69: =IF(COUNTIF(Table2[[#This Row],[Warehouse_ID]],Table2[[#This Row],[Warehouse_ID]])=0,"Invalid Warehouse","OK") -> OK | Y69: =IF(COUNTIF(Table2[[#This Row],[Employee_ID]],Table2[[#This Row],[Employee_ID]])=0,"Invalid Employee","OK") -> OK | Z69: =IF(Table2[[#This Row],[Stock_After]]=Table2[[#This Row],[Stock_After]]+Table2[[#This Row],[Stock_After]]-Table2[[#This Row],[Stock_After]]-Table2[[#This Row],[Stock_After]]+Table2[[#This Row],[Stock_After]],"OK","Error") -> OK | AA69: =IF(ROUND(Table2[[#This Row],[Total_Value]],2)=ROUND(Table2[[#This Row],[Quantity]]*Table2[[#This Row],[Unit_Price]],2),"OK","Error") -> OK | AB69: =IF(Table2[[#This Row],[Transaction_Type]]="Purchase", IF(Table2[[#This Row],[Stock_After]]=Table2[[#This Row],[Stock_Before]]+Table2[[#This Row],[Quantity]], "OK", "Error"), IF(Table2[[#This Row],[Transaction_Type]]="Return", IF(Table2[[#This Row],[Stock_After]]=Table2[[#This Row],[Stock_Before]]+Table2[[#This Row],[Quantity]], "OK", "Error"), IF(Table2[[#This Row],[Transaction_Type]]="Sale", IF(Table2[[#This Row],[Stock_After]]=MAX(0, Table2[[#This Row],[Stock_Before]]-Table2[[#This Row],[Quantity]]), "OK", "Error"), IF(Table2[[#This Row],[Transaction_Type]]="Adjustment", IF(Table2[[#This Row],[Stock_After]]>=0, "OK", "Error"), "Check")))) -> OK | AC69: =IF(AND(Table2[[#This Row],[Quantity]]>=0,Table2[[#This Row],[Unit_Price]]>=0),"OK","Error") -> OK | AD69: =IF(Table2[[#This Row],[Stock_After]]=0,"Stock-Out",IF(Table2[[#This Row],[Stock_After]]<=10,"Low Stock","Healthy")) -> Healthy
A70: T00069 | B70: 46072 | C70: P008 | D70: Notebook | E70: Stationery | F70: Books | G70: S008 | H70: W03 | I70: Adjustment | J70: 58 | K70: 1180 | L70: 68440 | M70: 97 | N70: 155 | O70: E019 | Q70: UPI | R70: Completed | S70: Regular Transaction | T70: =IF(COUNTIF(T72,Q82)>1,"Duplicate","OK") -> OK | U70: =IF(Table2[[#This Row],[Transaction_ID]]="","Missing","OK") -> OK | V70: =IF(COUNTIF(Table2[[#This Row],[Product_ID]],Table2[[#This Row],[Product_ID]])=0,"Invalid Product","OK") -> OK | W70: =IF(COUNTIF(Table2[[#This Row],[Supplier_ID]],Table2[[#This Row],[Supplier_ID]])=0,"Invalid Supplier","OK") -> OK | X70: =IF(COUNTIF(Table2[[#This Row],[Warehouse_ID]],Table2[[#This Row],[Warehouse_ID]])=0,"Invalid Warehouse","OK") -> OK | Y70: =IF(COUNTIF(Table2[[#This Row],[Employee_ID]],Table2[[#This Row],[Employee_ID]])=0,"Invalid Employee","OK") -> OK | Z70: =IF(Table2[[#This Row],[Stock_After]]=Table2[[#This Row],[Stock_After]]+Table2[[#This Row],[Stock_After]]-Table2[[#This Row],[Stock_After]]-Table2[[#This Row],[Stock_After]]+Table2[[#This Row],[Stock_After]],"OK","Error") -> OK | AA70: =IF(ROUND(Table2[[#This Row],[Total_Value]],2)=ROUND(Table2[[#This Row],[Quantity]]*Table2[[#This Row],[Unit_Price]],2),"OK","Error") -> OK | AB70: =IF(Table2[[#This Row],[Transaction_Type]]="Purchase", IF(Table2[[#This Row],[Stock_After]]=Table2[[#This Row],[Stock_Before]]+Table2[[#This Row],[Quantity]], "OK", "Error"), IF(Table2[[#This Row],[Transaction_Type]]="Return", IF(Table2[[#This Row],[Stock_After]]=Table2[[#This Row],[Stock_Before]]+Table2[[#This Row],[Quantity]], "OK", "Error"), IF(Table2[[#This Row],[Transaction_Type]]="Sale", IF(Table2[[#This Row],[Stock_After]]=MAX(0, Table2[[#This Row],[Stock_Before]]-Table2[[#This Row],[Quantity]]), "OK", "Error"), IF(Table2[[#This Row],[Transaction_Type]]="Adjustment", IF(Table2[[#This Row],[Stock_After]]>=0, "OK", "Error"), "Check")))) -> OK | AC70: =IF(AND(Table2[[#This Row],[Quantity]]>=0,Table2[[#This Row],[Unit_Price]]>=0),"OK","Error") -> OK | AD70: =IF(Table2[[#This Row],[Stock_After]]=0,"Stock-Out",IF(Table2[[#This Row],[Stock_After]]<=10,"Low Stock","Healthy")) -> Healthy
A71: T00070 | B71: 46018 | C71: P008 | D71: Notebook | E71: Stationery | F71: Books | G71: S015 | H71: W03 | I71: Return | J71: 55 | K71: 48935 | L71: 2691425 | M71: 331 | N71: 386 | O71: E010 | Q71: UPI | R71: Approved | S71: Regular Transaction | T71: =IF(COUNTIF(T73,Q83)>1,"Duplicate","OK") -> OK | U71: =IF(Table2[[#This Row],[Transaction_ID]]="","Missing","OK") -> OK | V71: =IF(COUNTIF(Table2[[#This Row],[Product_ID]],Table2[[#This Row],[Product_ID]])=0,"Invalid Product","OK") -> OK | W71: =IF(COUNTIF(Table2[[#This Row],[Supplier_ID]],Table2[[#This Row],[Supplier_ID]])=0,"Invalid Supplier","OK") -> OK | X71: =IF(COUNTIF(Table2[[#This Row],[Warehouse_ID]],Table2[[#This Row],[Warehouse_ID]])=0,"Invalid Warehouse","OK") -> OK | Y71: =IF(COUNTIF(Table2[[#This Row],[Employee_ID]],Table2[[#This Row],[Employee_ID]])=0,"Invalid Employee","OK") -> OK | Z71: =IF(Table2[[#This Row],[Stock_After]]=Table2[[#This Row],[Stock_After]]+Table2[[#This Row],[Stock_After]]-Table2[[#This Row],[Stock_After]]-Table2[[#This Row],[Stock_After]]+Table2[[#This Row],[Stock_After]],"OK","Error") -> OK | AA71: =IF(ROUND(Table2[[#This Row],[Total_Value]],2)=ROUND(Table2[[#This Row],[Quantity]]*Table2[[#This Row],[Unit_Price]],2),"OK","Error") -> OK | AB71: =IF(Table2[[#This Row],[Transaction_Type]]="Purchase", IF(Table2[[#This Row],[Stock_After]]=Table2[[#This Row],[Stock_Before]]+Table2[[#This Row],[Quantity]], "OK", "Error"), IF(Table2[[#This Row],[Transaction_Type]]="Return", IF(Table2[[#This Row],[Stock_After]]=Table2[[#This Row],[Stock_Before]]+Table2[[#This Row],[Quantity]], "OK", "Error"), IF(Table2[[#This Row],[Transaction_Type]]="Sale", IF(Table2[[#This Row],[Stock_After]]=MAX(0, Table2[[#This Row],[Stock_Before]]-Table2[[#This Row],[Quantity]]), "OK", "Error"), IF(Table2[[#This Row],[Transaction_Type]]="Adjustment", IF(Table2[[#This Row],[Stock_After]]>=0, "OK", "Error"), "Check")))) -> OK | AC71: =IF(AND(Table2[[#This Row],[Quantity]]>=0,Table2[[#This Row],[Unit_Price]]>=0),"OK","Error") -> OK | AD71: =IF(Table2[[#This Row],[Stock_After]]=0,"Stock-Out",IF(Table2[[#This Row],[Stock_After]]<=10,"Low Stock","Healthy")) -> Healthy
A72: T00071 | B72: 46206 | C72: P004 | D72: Monitor | E72: Electronics | F72: Displays | G72: S006 | H72: W02 | I72: Purchase | J72: 93 | K72: 12671 | L72: 1178403 | M72: 211 | N72: 304 | O72: E007 | Q72: Credit | R72: Completed | S72: Regular Transaction | T72: =IF(COUNTIF(T74,Q84)>1,"Duplicate","OK") -> OK | U72: =IF(Table2[[#This Row],[Transaction_ID]]="","Missing","OK") -> OK | V72: =IF(COUNTIF(Table2[[#This Row],[Product_ID]],Table2[[#This Row],[Product_ID]])=0,"Invalid Product","OK") -> OK | W72: =IF(COUNTIF(Table2[[#This Row],[Supplier_ID]],Table2[[#This Row],[Supplier_ID]])=0,"Invalid Supplier","OK") -> OK | X72: =IF(COUNTIF(Table2[[#This Row],[Warehouse_ID]],Table2[[#This Row],[Warehouse_ID]])=0,"Invalid Warehouse","OK") -> OK | Y72: =IF(COUNTIF(Table2[[#This Row],[Employee_ID]],Table2[[#This Row],[Employee_ID]])=0,"Invalid Employee","OK") -> OK | Z72: =IF(Table2[[#This Row],[Stock_After]]=Table2[[#This Row],[Stock_After]]+Table2[[#This Row],[Stock_After]]-Table2[[#This Row],[Stock_After]]-Table2[[#This Row],[Stock_After]]+Table2[[#This Row],[Stock_After]],"OK","Error") -> OK | AA72: =IF(ROUND(Table2[[#This Row],[Total_Value]],2)=ROUND(Table2[[#This Row],[Quantity]]*Table2[[#This Row],[Unit_Price]],2),"OK","Error") -> OK | AB72: =IF(Table2[[#This Row],[Transaction_Type]]="Purchase", IF(Table2[[#This Row],[Stock_After]]=Table2[[#This Row],[Stock_Before]]+Table2[[#This Row],[Quantity]], "OK", "Error"), IF(Table2[[#This Row],[Transaction_Type]]="Return", IF(Table2[[#This Row],[Stock_After]]=Table2[[#This Row],[Stock_Before]]+Table2[[#This Row],[Quantity]], "OK", "Error"), IF(Table2[[#This Row],[Transaction_Type]]="Sale", IF(Table2[[#This Row],[Stock_After]]=MAX(0, Table2[[#This Row],[Stock_Before]]-Table2[[#This Row],[Quantity]]), "OK", "Error"), IF(Table2[[#This Row],[Transaction_Type]]="Adjustment", IF(Table2[[#This Row],[Stock_After]]>=0, "OK", "Error"), "Check")))) -> OK | AC72: =IF(AND(Table2[[#This Row],[Quantity]]>=0,Table2[[#This Row],[Unit_Price]]>=0),"OK","Error") -> OK | AD72: =IF(Table2[[#This Row],[Stock_After]]=0,"Stock-Out",IF(Table2[[#This Row],[Stock_After]]<=10,"Low Stock","Healthy")) -> Healthy
A73: T00072 | B73: 46027 | C73: P005 | D73: Printer | E73: Electronics | F73: Printers | G73: S006 | H73: W03 | I73: Return | J73: 13 | K73: 12771 | L73: 166023 | M73: 201 | N73: 214 | O73: E001 | Q73: Card | R73: Completed | S73: Regular Transaction | T73: =IF(COUNTIF(T75,Q85)>1,"Duplicate","OK") -> OK | U73: =IF(Table2[[#This Row],[Transaction_ID]]="","Missing","OK") -> OK | V73: =IF(COUNTIF(Table2[[#This Row],[Product_ID]],Table2[[#This Row],[Product_ID]])=0,"Invalid Product","OK") -> OK | W73: =IF(COUNTIF(Table2[[#This Row],[Supplier_ID]],Table2[[#This Row],[Supplier_ID]])=0,"Invalid Supplier","OK") -> OK | X73: =IF(COUNTIF(Table2[[#This Row],[Warehouse_ID]],Table2[[#This Row],[Warehouse_ID]])=0,"Invalid Warehouse","OK") -> OK | Y73: =IF(COUNTIF(Table2[[#This Row],[Employee_ID]],Table2[[#This Row],[Employee_ID]])=0,"Invalid Employee","OK") -> OK | Z73: =IF(Table2[[#This Row],[Stock_After]]=Table2[[#This Row],[Stock_After]]+Table2[[#This Row],[Stock_After]]-Table2[[#This Row],[Stock_After]]-Table2[[#This Row],[Stock_After]]+Table2[[#This Row],[Stock_After]],"OK","Error") -> OK | AA73: =IF(ROUND(Table2[[#This Row],[Total_Value]],2)=ROUND(Table2[[#This Row],[Quantity]]*Table2[[#This Row],[Unit_Price]],2),"OK","Error") -> OK | AB73: =IF(Table2[[#This Row],[Transaction_Type]]="Purchase", IF(Table2[[#This Row],[Stock_After]]=Table2[[#This Row],[Stock_Before]]+Table2[[#This Row],[Quantity]], "OK", "Error"), IF(Table2[[#This Row],[Transaction_Type]]="Return", IF(Table2[[#This Row],[Stock_After]]=Table2[[#This Row],[Stock_Before]]+Table2[[#This Row],[Quantity]], "OK", "Error"), IF(Table2[[#This Row],[Transaction_Type]]="Sale", IF(Table2[[#This Row],[Stock_After]]=MAX(0, Table2[[#This Row],[Stock_Before]]-Table2[[#This Row],[Quantity]]), "OK", "Error"), IF(Table2[[#This Row],[Transaction_Type]]="Adjustment", IF(Table2[[#This Row],[Stock_After]]>=0, "OK", "Error"), "Check")))) -> OK | AC73: =IF(AND(Table2[[#This Row],[Quantity]]>=0,Table2[[#This Row],[Unit_Price]]>=0),"OK","Error") -> OK | AD73: =IF(Table2[[#This Row],[Stock_After]]=0,"Stock-Out",IF(Table2[[#This Row],[Stock_After]]<=10,"Low Stock","Healthy")) -> Healthy
A74: T00073 | B74: 45787 | C74: P005 | D74: Printer | E74: Electronics | F74: Printers | G74: S016 | H74: W01 | I74: Purchase | J74: 7 | K74: 36314 | L74: 254198 | M74: 199 | N74: 206 | O74: E001 | Q74: UPI | R74: Pending | S74: Regular Transaction | T74: =IF(COUNTIF(T76,Q86)>1,"Duplicate","OK") -> OK | U74: =IF(Table2[[#This Row],[Transaction_ID]]="","Missing","OK") -> OK | V74: =IF(COUNTIF(Table2[[#This Row],[Product_ID]],Table2[[#This Row],[Product_ID]])=0,"Invalid Product","OK") -> OK | W74: =IF(COUNTIF(Table2[[#This Row],[Supplier_ID]],Table2[[#This Row],[Supplier_ID]])=0,"Invalid Supplier","OK") -> OK | X74: =IF(COUNTIF(Table2[[#This Row],[Warehouse_ID]],Table2[[#This Row],[Warehouse_ID]])=0,"Invalid Warehouse","OK") -> OK | Y74: =IF(COUNTIF(Table2[[#This Row],[Employee_ID]],Table2[[#This Row],[Employee_ID]])=0,"Invalid Employee","OK") -> OK | Z74: =IF(Table2[[#This Row],[Stock_After]]=Table2[[#This Row],[Stock_After]]+Table2[[#This Row],[Stock_After]]-Table2[[#This Row],[Stock_After]]-Table2[[#This Row],[Stock_After]]+Table2[[#This Row],[Stock_After]],"OK","Error") -> OK | AA74: =IF(ROUND(Table2[[#This Row],[Total_Value]],2)=ROUND(Table2[[#This Row],[Quantity]]*Table2[[#This Row],[Unit_Price]],2),"OK","Error") -> OK | AB74: =IF(Table2[[#This Row],[Transaction_Type]]="Purchase", IF(Table2[[#This Row],[Stock_After]]=Table2[[#This Row],[Stock_Before]]+Table2[[#This Row],[Quantity]], "OK", "Error"), IF(Table2[[#This Row],[Transaction_Type]]="Return", IF(Table2[[#This Row],[Stock_After]]=Table2[[#This Row],[Stock_Before]]+Table2[[#This Row],[Quantity]], "OK", "Error"), IF(Table2[[#This Row],[Transaction_Type]]="Sale", IF(Table2[[#This Row],[Stock_After]]=MAX(0, Table2[[#This Row],[Stock_Before]]-Table2[[#This Row],[Quantity]]), "OK", "Error"), IF(Table2[[#This Row],[Transaction_Type]]="Adjustment", IF(Table2[[#This Row],[Stock_After]]>=0, "OK", "Error"), "Check")))) -> OK | AC74: =IF(AND(Table2[[#This Row],[Quantity]]>=0,Table2[[#This Row],[Unit_Price]]>=0),"OK","Error") -> OK | AD74: =IF(Table2[[#This Row],[Stock_After]]=0,"Stock-Out",IF(Table2[[#This Row],[Stock_After]]<=10,"Low Stock","Healthy")) -> Healthy
A75: T00074 | B75: 46147 | C75: P008 | D75: Notebook | E75: Stationery | F75: Books | G75: S004 | H75: W01 | I75: Adjustment | J75: 57 | K75: 22378 | L75: 1275546 | M75: 144 | N75: 87 | O75: E013 | Q75: Credit | R75: Approved | S75: Regular Transaction | T75: =IF(COUNTIF(T77,Q87)>1,"Duplicate","OK") -> OK | U75: =IF(Table2[[#This Row],[Transaction_ID]]="","Missing","OK") -> OK | V75: =IF(COUNTIF(Table2[[#This Row],[Product_ID]],Table2[[#This Row],[Product_ID]])=0,"Invalid Product","OK") -> OK | W75: =IF(COUNTIF(Table2[[#This Row],[Supplier_ID]],Table2[[#This Row],[Supplier_ID]])=0,"Invalid Supplier","OK") -> OK | X75: =IF(COUNTIF(Table2[[#This Row],[Warehouse_ID]],Table2[[#This Row],[Warehouse_ID]])=0,"Invalid Warehouse","OK") -> OK | Y75: =IF(COUNTIF(Table2[[#This Row],[Employee_ID]],Table2[[#This Row],[Employee_ID]])=0,"Invalid Employee","OK") -> OK | Z75: =IF(Table2[[#This Row],[Stock_After]]=Table2[[#This Row],[Stock_After]]+Table2[[#This Row],[Stock_After]]-Table2[[#This Row],[Stock_After]]-Table2[[#This Row],[Stock_After]]+Table2[[#This Row],[Stock_After]],"OK","Error") -> OK | AA75: =IF(ROUND(Table2[[#This Row],[Total_Value]],2)=ROUND(Table2[[#This Row],[Quantity]]*Table2[[#This Row],[Unit_Price]],2),"OK","Error") -> OK | AB75: =IF(Table2[[#This Row],[Transaction_Type]]="Purchase", IF(Table2[[#This Row],[Stock_After]]=Table2[[#This Row],[Stock_Before]]+Table2[[#This Row],[Quantity]], "OK", "Error"), IF(Table2[[#This Row],[Transaction_Type]]="Return", IF(Table2[[#This Row],[Stock_After]]=Table2[[#This Row],[Stock_Before]]+Table2[[#This Row],[Quantity]], "OK", "Error"), IF(Table2[[#This Row],[Transaction_Type]]="Sale", IF(Table2[[#This Row],[Stock_After]]=MAX(0, Table2[[#This Row],[Stock_Before]]-Table2[[#This Row],[Quantity]]), "OK", "Error"), IF(Table2[[#This Row],[Transaction_Type]]="Adjustment", IF(Table2[[#This Row],[Stock_After]]>=0, "OK", "Error"), "Check")))) -> OK | AC75: =IF(AND(Table2[[#This Row],[Quantity]]>=0,Table2[[#This Row],[Unit_Price]]>=0),"OK","Error") -> OK | AD75: =IF(Table2[[#This Row],[Stock_After]]=0,"Stock-Out",IF(Table2[[#This Row],[Stock_After]]<=10,"Low Stock","Healthy")) -> Healthy
A76: T00075 | B76: 45969 | C76: P002 | D76: Keyboard | E76: Electronics | F76: Accessories | G76: S003 | H76: W02 | I76: Purchase | J76: 20 | K76: 9827 | L76: 196540 | M76: 465 | N76: 485 | O76: E004 | Q76: Credit | R76: Pending | S76: Regular Transaction | T76: =IF(COUNTIF(T78,Q88)>1,"Duplicate","OK") -> OK | U76: =IF(Table2[[#This Row],[Transaction_ID]]="","Missing","OK") -> OK | V76: =IF(COUNTIF(Table2[[#This Row],[Product_ID]],Table2[[#This Row],[Product_ID]])=0,"Invalid Product","OK") -> OK | W76: =IF(COUNTIF(Table2[[#This Row],[Supplier_ID]],Table2[[#This Row],[Supplier_ID]])=0,"Invalid Supplier","OK") -> OK | X76: =IF(COUNTIF(Table2[[#This Row],[Warehouse_ID]],Table2[[#This Row],[Warehouse_ID]])=0,"Invalid Warehouse","OK") -> OK | Y76: =IF(COUNTIF(Table2[[#This Row],[Employee_ID]],Table2[[#This Row],[Employee_ID]])=0,"Invalid Employee","OK") -> OK | Z76: =IF(Table2[[#This Row],[Stock_After]]=Table2[[#This Row],[Stock_After]]+Table2[[#This Row],[Stock_After]]-Table2[[#This Row],[Stock_After]]-Table2[[#This Row],[Stock_After]]+Table2[[#This Row],[Stock_After]],"OK","Error") -> OK | AA76: =IF(ROUND(Table2[[#This Row],[Total_Value]],2)=ROUND(Table2[[#This Row],[Quantity]]*Table2[[#This Row],[Unit_Price]],2),"OK","Error") -> OK | AB76: =IF(Table2[[#This Row],[Transaction_Type]]="Purchase", IF(Table2[[#This Row],[Stock_After]]=Table2[[#This Row],[Stock_Before]]+Table2[[#This Row],[Quantity]], "OK", "Error"), IF(Table2[[#This Row],[Transaction_Type]]="Return", IF(Table2[[#This Row],[Stock_After]]=Table2[[#This Row],[Stock_Before]]+Table2[[#This Row],[Quantity]], "OK", "Error"), IF(Table2[[#This Row],[Transaction_Type]]="Sale", IF(Table2[[#This Row],[Stock_After]]=MAX(0, Table2[[#This Row],[Stock_Before]]-Table2[[#This Row],[Quantity]]), "OK", "Error"), IF(Table2[[#This Row],[Transaction_Type]]="Adjustment", IF(Table2[[#This Row],[Stock_After]]>=0, "OK", "Error"), "Check")))) -> OK | AC76: =IF(AND(Table2[[#This Row],[Quantity]]>=0,Table2[[#This Row],[Unit_Price]]>=0),"OK","Error") -> OK | AD76: =IF(Table2[[#This Row],[Stock_After]]=0,"Stock-Out",IF(Table2[[#This Row],[Stock_After]]<=10,"Low Stock","Healthy")) -> Healthy
A77: T00076 | B77: 45962 | C77: P010 | D77: File Folder | E77: Stationery | F77: Files | G77: S019 | H77: W04 | I77: Sale | J77: 100 | K77: 34297 | L77: 3429700 | M77: 244 | N77: 144 | O77: E010 | P77: C0231 | Q77: Cash | R77: Approved | S77: Regular Transaction | T77: =IF(COUNTIF(T79,Q89)>1,"Duplicate","OK") -> OK | U77: =IF(Table2[[#This Row],[Transaction_ID]]="","Missing","OK") -> OK | V77: =IF(COUNTIF(Table2[[#This Row],[Product_ID]],Table2[[#This Row],[Product_ID]])=0,"Invalid Product","OK") -> OK | W77: =IF(COUNTIF(Table2[[#This Row],[Supplier_ID]],Table2[[#This Row],[Supplier_ID]])=0,"Invalid Supplier","OK") -> OK | X77: =IF(COUNTIF(Table2[[#This Row],[Warehouse_ID]],Table2[[#This Row],[Warehouse_ID]])=0,"Invalid Warehouse","OK") -> OK | Y77: =IF(COUNTIF(Table2[[#This Row],[Employee_ID]],Table2[[#This Row],[Employee_ID]])=0,"Invalid Employee","OK") -> OK | Z77: =IF(Table2[[#This Row],[Stock_After]]=Table2[[#This Row],[Stock_After]]+Table2[[#This Row],[Stock_After]]-Table2[[#This Row],[Stock_After]]-Table2[[#This Row],[Stock_After]]+Table2[[#This Row],[Stock_After]],"OK","Error") -> OK | AA77: =IF(ROUND(Table2[[#This Row],[Total_Value]],2)=ROUND(Table2[[#This Row],[Quantity]]*Table2[[#This Row],[Unit_Price]],2),"OK","Error") -> OK | AB77: =IF(Table2[[#This Row],[Transaction_Type]]="Purchase", IF(Table2[[#This Row],[Stock_After]]=Table2[[#This Row],[Stock_Before]]+Table2[[#This Row],[Quantity]], "OK", "Error"), IF(Table2[[#This Row],[Transaction_Type]]="Return", IF(Table2[[#This Row],[Stock_After]]=Table2[[#This Row],[Stock_Before]]+Table2[[#This Row],[Quantity]], "OK", "Error"), IF(Table2[[#This Row],[Transaction_Type]]="Sale", IF(Table2[[#This Row],[Stock_After]]=MAX(0, Table2[[#This Row],[Stock_Before]]-Table2[[#This Row],[Quantity]]), "OK", "Error"), IF(Table2[[#This Row],[Transaction_Type]]="Adjustment", IF(Table2[[#This Row],[Stock_After]]>=0, "OK", "Error"), "Check")))) -> OK | AC77: =IF(AND(Table2[[#This Row],[Quantity]]>=0,Table2[[#This Row],[Unit_Price]]>=0),"OK","Error") -> OK | AD77: =IF(Table2[[#This Row],[Stock_After]]=0,"Stock-Out",IF(Table2[[#This Row],[Stock_After]]<=10,"Low Stock","Healthy")) -> Healthy
A78: T00077 | B78: 45928 | C78: P010 | D78: File Folder | E78: Stationery | F78: Files | G78: S003 | H78: W02 | I78: Purchase | J78: 98 | K78: 13667 | L78: 1339366 | M78: 370 | N78: 468 | O78: E008 | Q78: Card | R78: Completed | S78: Regular Transaction | T78: =IF(COUNTIF(T80,Q90)>1,"Duplicate","OK") -> OK | U78: =IF(Table2[[#This Row],[Transaction_ID]]="","Missing","OK") -> OK | V78: =IF(COUNTIF(Table2[[#This Row],[Product_ID]],Table2[[#This Row],[Product_ID]])=0,"Invalid Product","OK") -> OK | W78: =IF(COUNTIF(Table2[[#This Row],[Supplier_ID]],Table2[[#This Row],[Supplier_ID]])=0,"Invalid Supplier","OK") -> OK | X78: =IF(COUNTIF(Table2[[#This Row],[Warehouse_ID]],Table2[[#This Row],[Warehouse_ID]])=0,"Invalid Warehouse","OK") -> OK | Y78: =IF(COUNTIF(Table2[[#This Row],[Employee_ID]],Table2[[#This Row],[Employee_ID]])=0,"Invalid Employee","OK") -> OK | Z78: =IF(Table2[[#This Row],[Stock_After]]=Table2[[#This Row],[Stock_After]]+Table2[[#This Row],[Stock_After]]-Table2[[#This Row],[Stock_After]]-Table2[[#This Row],[Stock_After]]+Table2[[#This Row],[Stock_After]],"OK","Error") -> OK | AA78: =IF(ROUND(Table2[[#This Row],[Total_Value]],2)=ROUND(Table2[[#This Row],[Quantity]]*Table2[[#This Row],[Unit_Price]],2),"OK","Error") -> OK | AB78: =IF(Table2[[#This Row],[Transaction_Type]]="Purchase", IF(Table2[[#This Row],[Stock_After]]=Table2[[#This Row],[Stock_Before]]+Table2[[#This Row],[Quantity]], "OK", "Error"), IF(Table2[[#This Row],[Transaction_Type]]="Return", IF(Table2[[#This Row],[Stock_After]]=Table2[[#This Row],[Stock_Before]]+Table2[[#This Row],[Quantity]], "OK", "Error"), IF(Table2[[#This Row],[Transaction_Type]]="Sale", IF(Table2[[#This Row],[Stock_After]]=MAX(0, Table2[[#This Row],[Stock_Before]]-Table2[[#This Row],[Quantity]]), "OK", "Error"), IF(Table2[[#This Row],[Transaction_Type]]="Adjustment", IF(Table2[[#This Row],[Stock_After]]>=0, "OK", "Error"), "Check")))) -> OK | AC78: =IF(AND(Table2[[#This Row],[Quantity]]>=0,Table2[[#This Row],[Unit_Price]]>=0),"OK","Error") -> OK | AD78: =IF(Table2[[#This Row],[Stock_After]]=0,"Stock-Out",IF(Table2[[#This Row],[Stock_After]]<=10,"Low Stock","Healthy")) -> Healthy
A79: T00078 | B79: 46363 | C79: P009 | D79: Pen | E79: Stationery | F79: Writing | G79: S020 | H79: W04 | I79: Purchase | J79: 21 | K79: 225 | L79: 4725 | M79: 259 | N79: 280 | O79: E010 | Q79: Cash | R79: Approved | S79: Regular Transaction | T79: =IF(COUNTIF(T81,Q91)>1,"Duplicate","OK") -> OK | U79: =IF(Table2[[#This Row],[Transaction_ID]]="","Missing","OK") -> OK | V79: =IF(COUNTIF(Table2[[#This Row],[Product_ID]],Table2[[#This Row],[Product_ID]])=0,"Invalid Product","OK") -> OK | W79: =IF(COUNTIF(Table2[[#This Row],[Supplier_ID]],Table2[[#This Row],[Supplier_ID]])=0,"Invalid Supplier","OK") -> OK | X79: =IF(COUNTIF(Table2[[#This Row],[Warehouse_ID]],Table2[[#This Row],[Warehouse_ID]])=0,"Invalid Warehouse","OK") -> OK | Y79: =IF(COUNTIF(Table2[[#This Row],[Employee_ID]],Table2[[#This Row],[Employee_ID]])=0,"Invalid Employee","OK") -> OK | Z79: =IF(Table2[[#This Row],[Stock_After]]=Table2[[#This Row],[Stock_After]]+Table2[[#This Row],[Stock_After]]-Table2[[#This Row],[Stock_After]]-Table2[[#This Row],[Stock_After]]+Table2[[#This Row],[Stock_After]],"OK","Error") -> OK | AA79: =IF(ROUND(Table2[[#This Row],[Total_Value]],2)=ROUND(Table2[[#This Row],[Quantity]]*Table2[[#This Row],[Unit_Price]],2),"OK","Error") -> OK | AB79: =IF(Table2[[#This Row],[Transaction_Type]]="Purchase", IF(Table2[[#This Row],[Stock_After]]=Table2[[#This Row],[Stock_Before]]+Table2[[#This Row],[Quantity]], "OK", "Error"), IF(Table2[[#This Row],[Transaction_Type]]="Return", IF(Table2[[#This Row],[Stock_After]]=Table2[[#This Row],[Stock_Before]]+Table2[[#This Row],[Quantity]], "OK", "Error"), IF(Table2[[#This Row],[Transaction_Type]]="Sale", IF(Table2[[#This Row],[Stock_After]]=MAX(0, Table2[[#This Row],[Stock_Before]]-Table2[[#This Row],[Quantity]]), "OK", "Error"), IF(Table2[[#This Row],[Transaction_Type]]="Adjustment", IF(Table2[[#This Row],[Stock_After]]>=0, "OK", "Error"), "Check")))) -> OK | AC79: =IF(AND(Table2[[#This Row],[Quantity]]>=0,Table2[[#This Row],[Unit_Price]]>=0),"OK","Error") -> OK | AD79: =IF(Table2[[#This Row],[Stock_After]]=0,"Stock-Out",IF(Table2[[#This Row],[Stock_After]]<=10,"Low Stock","Healthy")) -> Healthy
A80: T00079 | B80: 45730 | C80: P004 | D80: Monitor | E80: Electronics | F80: Displays | G80: S008 | H80: W03 | I80: Return | J80: 91 | K80: 18578 | L80: 1690598 | M80: 409 | N80: 500 | O80: E019 | Q80: Card | R80: Approved | S80: Regular Transaction | T80: =IF(COUNTIF(T82,Q92)>1,"Duplicate","OK") -> OK | U80: =IF(Table2[[#This Row],[Transaction_ID]]="","Missing","OK") -> OK | V80: =IF(COUNTIF(Table2[[#This Row],[Product_ID]],Table2[[#This Row],[Product_ID]])=0,"Invalid Product","OK") -> OK | W80: =IF(COUNTIF(Table2[[#This Row],[Supplier_ID]],Table2[[#This Row],[Supplier_ID]])=0,"Invalid Supplier","OK") -> OK | X80: =IF(COUNTIF(Table2[[#This Row],[Warehouse_ID]],Table2[[#This Row],[Warehouse_ID]])=0,"Invalid Warehouse","OK") -> OK | Y80: =IF(COUNTIF(Table2[[#This Row],[Employee_ID]],Table2[[#This Row],[Employee_ID]])=0,"Invalid Employee","OK") -> OK | Z80: =IF(Table2[[#This Row],[Stock_After]]=Table2[[#This Row],[Stock_After]]+Table2[[#This Row],[Stock_After]]-Table2[[#This Row],[Stock_After]]-Table2[[#This Row],[Stock_After]]+Table2[[#This Row],[Stock_After]],"OK","Error") -> OK | AA80: =IF(ROUND(Table2[[#This Row],[Total_Value]],2)=ROUND(Table2[[#This Row],[Quantity]]*Table2[[#This Row],[Unit_Price]],2),"OK","Error") -> OK | AB80: =IF(Table2[[#This Row],[Transaction_Type]]="Purchase", IF(Table2[[#This Row],[Stock_After]]=Table2[[#This Row],[Stock_Before]]+Table2[[#This Row],[Quantity]], "OK", "Error"), IF(Table2[[#This Row],[Transaction_Type]]="Return", IF(Table2[[#This Row],[Stock_After]]=Table2[[#This Row],[Stock_Before]]+Table2[[#This Row],[Quantity]], "OK", "Error"), IF(Table2[[#This Row],[Transaction_Type]]="Sale", IF(Table2[[#This Row],[Stock_After]]=MAX(0, Table2[[#This Row],[Stock_Before]]-Table2[[#This Row],[Quantity]]), "OK", "Error"), IF(Table2[[#This Row],[Transaction_Type]]="Adjustment", IF(Table2[[#This Row],[Stock_After]]>=0, "OK", "Error"), "Check")))) -> OK | AC80: =IF(AND(Table2[[#This Row],[Quantity]]>=0,Table2[[#This Row],[Unit_Price]]>=0),"OK","Error") -> OK | AD80: =IF(Table2[[#This Row],[Stock_After]]=0,"Stock-Out",IF(Table2[[#This Row],[Stock_After]]<=10,"Low Stock","Healthy")) -> Healthy
A81: T00080 | B81: 45930 | C81: P007 | D81: Office Desk | E81: Furniture | F81: Desks | G81: S005 | H81: W01 | I81: Purchase | J81: 70 | K81: 14783 | L81: 1034810 | M81: 381 | N81: 451 | O81: E002 | Q81: Card | R81: Completed | S81: Regular Transaction | T81: =IF(COUNTIF(T83,Q93)>1,"Duplicate","OK") -> OK | U81: =IF(Table2[[#This Row],[Transaction_ID]]="","Missing","OK") -> OK | V81: =IF(COUNTIF(Table2[[#This Row],[Product_ID]],Table2[[#This Row],[Product_ID]])=0,"Invalid Product","OK") -> OK | W81: =IF(COUNTIF(Table2[[#This Row],[Supplier_ID]],Table2[[#This Row],[Supplier_ID]])=0,"Invalid Supplier","OK") -> OK | X81: =IF(COUNTIF(Table2[[#This Row],[Warehouse_ID]],Table2[[#This Row],[Warehouse_ID]])=0,"Invalid Warehouse","OK") -> OK | Y81: =IF(COUNTIF(Table2[[#This Row],[Employee_ID]],Table2[[#This Row],[Employee_ID]])=0,"Invalid Employee","OK") -> OK | Z81: =IF(Table2[[#This Row],[Stock_After]]=Table2[[#This Row],[Stock_After]]+Table2[[#This Row],[Stock_After]]-Table2[[#This Row],[Stock_After]]-Table2[[#This Row],[Stock_After]]+Table2[[#This Row],[Stock_After]],"OK","Error") -> OK | AA81: =IF(ROUND(Table2[[#This Row],[Total_Value]],2)=ROUND(Table2[[#This Row],[Quantity]]*Table2[[#This Row],[Unit_Price]],2),"OK","Error") -> OK | AB81: =IF(Table2[[#This Row],[Transaction_Type]]="Purchase", IF(Table2[[#This Row],[Stock_After]]=Table2[[#This Row],[Stock_Before]]+Table2[[#This Row],[Quantity]], "OK", "Error"), IF(Table2[[#This Row],[Transaction_Type]]="Return", IF(Table2[[#This Row],[Stock_After]]=Table2[[#This Row],[Stock_Before]]+Table2[[#This Row],[Quantity]], "OK", "Error"), IF(Table2[[#This Row],[Transaction_Type]]="Sale", IF(Table2[[#This Row],[Stock_After]]=MAX(0, Table2[[#This Row],[Stock_Before]]-Table2[[#This Row],[Quantity]]), "OK", "Error"), IF(Table2[[#This Row],[Transaction_Type]]="Adjustment", IF(Table2[[#This Row],[Stock_After]]>=0, "OK", "Error"), "Check")))) -> OK | AC81: =IF(AND(Table2[[#This Row],[Quantity]]>=0,Table2[[#This Row],[Unit_Price]]>=0),"OK","Error") -> OK | AD81: =IF(Table2[[#This Row],[Stock_After]]=0,"Stock-Out",IF(Table2[[#This Row],[Stock_After]]<=10,"Low Stock","Healthy")) -> Healthy
A82: T00081 | B82: 45969 | C82: P005 | D82: Printer | E82: Electronics | F82: Printers | G82: S013 | H82: W03 | I82: Return | J82: 57 | K82: 8199 | L82: 467343 | M82: 289 | N82: 346 | O82: E017 | Q82: Credit | R82: Pending | S82: Regular Transaction | T82: =IF(COUNTIF(T84,Q94)>1,"Duplicate","OK") -> OK | U82: =IF(Table2[[#This Row],[Transaction_ID]]="","Missing","OK") -> OK | V82: =IF(COUNTIF(Table2[[#This Row],[Product_ID]],Table2[[#This Row],[Product_ID]])=0,"Invalid Product","OK") -> OK | W82: =IF(COUNTIF(Table2[[#This Row],[Supplier_ID]],Table2[[#This Row],[Supplier_ID]])=0,"Invalid Supplier","OK") -> OK | X82: =IF(COUNTIF(Table2[[#This Row],[Warehouse_ID]],Table2[[#This Row],[Warehouse_ID]])=0,"Invalid Warehouse","OK") -> OK | Y82: =IF(COUNTIF(Table2[[#This Row],[Employee_ID]],Table2[[#This Row],[Employee_ID]])=0,"Invalid Employee","OK") -> OK | Z82: =IF(Table2[[#This Row],[Stock_After]]=Table2[[#This Row],[Stock_After]]+Table2[[#This Row],[Stock_After]]-Table2[[#This Row],[Stock_After]]-Table2[[#This Row],[Stock_After]]+Table2[[#This Row],[Stock_After]],"OK","Error") -> OK | AA82: =IF(ROUND(Table2[[#This Row],[Total_Value]],2)=ROUND(Table2[[#This Row],[Quantity]]*Table2[[#This Row],[Unit_Price]],2),"OK","Error") -> OK | AB82: =IF(Table2[[#This Row],[Transaction_Type]]="Purchase", IF(Table2[[#This Row],[Stock_After]]=Table2[[#This Row],[Stock_Before]]+Table2[[#This Row],[Quantity]], "OK", "Error"), IF(Table2[[#This Row],[Transaction_Type]]="Return", IF(Table2[[#This Row],[Stock_After]]=Table2[[#This Row],[Stock_Before]]+Table2[[#This Row],[Quantity]], "OK", "Error"), IF(Table2[[#This Row],[Transaction_Type]]="Sale", IF(Table2[[#This Row],[Stock_After]]=MAX(0, Table2[[#This Row],[Stock_Before]]-Table2[[#This Row],[Quantity]]), "OK", "Error"), IF(Table2[[#This Row],[Transaction_Type]]="Adjustment", IF(Table2[[#This Row],[Stock_After]]>=0, "OK", "Error"), "Check")))) -> OK | AC82: =IF(AND(Table2[[#This Row],[Quantity]]>=0,Table2[[#This Row],[Unit_Price]]>=0),"OK","Error") -> OK | AD82: =IF(Table2[[#This Row],[Stock_After]]=0,"Stock-Out",IF(Table2[[#This Row],[Stock_After]]<=10,"Low Stock","Healthy")) -> Healthy
A83: T00082 | B83: 45988 | C83: P008 | D83: Notebook | E83: Stationery | F83: Books | G83: S020 | H83: W03 | I83: Purchase | J83: 77 | K83: 2662 | L83: 204974 | M83: 271 | N83: 348 | O83: E001 | Q83: Cash | R83: Pending | S83: Regular Transaction | T83: =IF(COUNTIF(T85,Q95)>1,"Duplicate","OK") -> OK | U83: =IF(Table2[[#This Row],[Transaction_ID]]="","Missing","OK") -> OK | V83: =IF(COUNTIF(Table2[[#This Row],[Product_ID]],Table2[[#This Row],[Product_ID]])=0,"Invalid Product","OK") -> OK | W83: =IF(COUNTIF(Table2[[#This Row],[Supplier_ID]],Table2[[#This Row],[Supplier_ID]])=0,"Invalid Supplier","OK") -> OK | X83: =IF(COUNTIF(Table2[[#This Row],[Warehouse_ID]],Table2[[#This Row],[Warehouse_ID]])=0,"Invalid Warehouse","OK") -> OK | Y83: =IF(COUNTIF(Table2[[#This Row],[Employee_ID]],Table2[[#This Row],[Employee_ID]])=0,"Invalid Employee","OK") -> OK | Z83: =IF(Table2[[#This Row],[Stock_After]]=Table2[[#This Row],[Stock_After]]+Table2[[#This Row],[Stock_After]]-Table2[[#This Row],[Stock_After]]-Table2[[#This Row],[Stock_After]]+Table2[[#This Row],[Stock_After]],"OK","Error") -> OK | AA83: =IF(ROUND(Table2[[#This Row],[Total_Value]],2)=ROUND(Table2[[#This Row],[Quantity]]*Table2[[#This Row],[Unit_Price]],2),"OK","Error") -> OK | AB83: =IF(Table2[[#This Row],[Transaction_Type]]="Purchase", IF(Table2[[#This Row],[Stock_After]]=Table2[[#This Row],[Stock_Before]]+Table2[[#This Row],[Quantity]], "OK", "Error"), IF(Table2[[#This Row],[Transaction_Type]]="Return", IF(Table2[[#This Row],[Stock_After]]=Table2[[#This Row],[Stock_Before]]+Table2[[#This Row],[Quantity]], "OK", "Error"), IF(Table2[[#This Row],[Transaction_Type]]="Sale", IF(Table2[[#This Row],[Stock_After]]=MAX(0, Table2[[#This Row],[Stock_Before]]-Table2[[#This Row],[Quantity]]), "OK", "Error"), IF(Table2[[#This Row],[Transaction_Type]]="Adjustment", IF(Table2[[#This Row],[Stock_After]]>=0, "OK", "Error"), "Check")))) -> OK | AC83: =IF(AND(Table2[[#This Row],[Quantity]]>=0,Table2[[#This Row],[Unit_Price]]>=0),"OK","Error") -> OK | AD83: =IF(Table2[[#This Row],[Stock_After]]=0,"Stock-Out",IF(Table2[[#This Row],[Stock_After]]<=10,"Low Stock","Healthy")) -> Healthy
A84: T00083 | B84: 46248 | C84: P004 | D84: Monitor | E84: Electronics | F84: Displays | G84: S002 | H84: W02 | I84: Purchase | J84: 98 | K84: 44108 | L84: 4322584 | M84: 470 | N84: 568 | O84: E016 | Q84: Credit | R84: Approved | S84: Regular Transaction | T84: =IF(COUNTIF(T86,Q96)>1,"Duplicate","OK") -> OK | U84: =IF(Table2[[#This Row],[Transaction_ID]]="","Missing","OK") -> OK | V84: =IF(COUNTIF(Table2[[#This Row],[Product_ID]],Table2[[#This Row],[Product_ID]])=0,"Invalid Product","OK") -> OK | W84: =IF(COUNTIF(Table2[[#This Row],[Supplier_ID]],Table2[[#This Row],[Supplier_ID]])=0,"Invalid Supplier","OK") -> OK | X84: =IF(COUNTIF(Table2[[#This Row],[Warehouse_ID]],Table2[[#This Row],[Warehouse_ID]])=0,"Invalid Warehouse","OK") -> OK | Y84: =IF(COUNTIF(Table2[[#This Row],[Employee_ID]],Table2[[#This Row],[Employee_ID]])=0,"Invalid Employee","OK") -> OK | Z84: =IF(Table2[[#This Row],[Stock_After]]=Table2[[#This Row],[Stock_After]]+Table2[[#This Row],[Stock_After]]-Table2[[#This Row],[Stock_After]]-Table2[[#This Row],[Stock_After]]+Table2[[#This Row],[Stock_After]],"OK","Error") -> OK | AA84: =IF(ROUND(Table2[[#This Row],[Total_Value]],2)=ROUND(Table2[[#This Row],[Quantity]]*Table2[[#This Row],[Unit_Price]],2),"OK","Error") -> OK | AB84: =IF(Table2[[#This Row],[Transaction_Type]]="Purchase", IF(Table2[[#This Row],[Stock_After]]=Table2[[#This Row],[Stock_Before]]+Table2[[#This Row],[Quantity]], "OK", "Error"), IF(Table2[[#This Row],[Transaction_Type]]="Return", IF(Table2[[#This Row],[Stock_After]]=Table2[[#This Row],[Stock_Before]]+Table2[[#This Row],[Quantity]], "OK", "Error"), IF(Table2[[#This Row],[Transaction_Type]]="Sale", IF(Table2[[#This Row],[Stock_After]]=MAX(0, Table2[[#This Row],[Stock_Before]]-Table2[[#This Row],[Quantity]]), "OK", "Error"), IF(Table2[[#This Row],[Transaction_Type]]="Adjustment", IF(Table2[[#This Row],[Stock_After]]>=0, "OK", "Error"), "Check")))) -> OK | AC84: =IF(AND(Table2[[#This Row],[Quantity]]>=0,Table2[[#This Row],[Unit_Price]]>=0),"OK","Error") -> OK | AD84: =IF(Table2[[#This Row],[Stock_After]]=0,"Stock-Out",IF(Table2[[#This Row],[Stock_After]]<=10,"Low Stock","Healthy")) -> Healthy
A85: T00084 | B85: 45751 | C85: P005 | D85: Printer | E85: Electronics | F85: Printers | G85: S016 | H85: W03 | I85: Sale | J85: 75 | K85: 28616 | L85: 2146200 | M85: 375 | N85: 300 | O85: E014 | P85: C0417 | Q85: UPI | R85: Approved | S85: Regular Transaction | T85: =IF(COUNTIF(T87,Q97)>1,"Duplicate","OK") -> OK | U85: =IF(Table2[[#This Row],[Transaction_ID]]="","Missing","OK") -> OK | V85: =IF(COUNTIF(Table2[[#This Row],[Product_ID]],Table2[[#This Row],[Product_ID]])=0,"Invalid Product","OK") -> OK | W85: =IF(COUNTIF(Table2[[#This Row],[Supplier_ID]],Table2[[#This Row],[Supplier_ID]])=0,"Invalid Supplier","OK") -> OK | X85: =IF(COUNTIF(Table2[[#This Row],[Warehouse_ID]],Table2[[#This Row],[Warehouse_ID]])=0,"Invalid Warehouse","OK") -> OK | Y85: =IF(COUNTIF(Table2[[#This Row],[Employee_ID]],Table2[[#This Row],[Employee_ID]])=0,"Invalid Employee","OK") -> OK | Z85: =IF(Table2[[#This Row],[Stock_After]]=Table2[[#This Row],[Stock_After]]+Table2[[#This Row],[Stock_After]]-Table2[[#This Row],[Stock_After]]-Table2[[#This Row],[Stock_After]]+Table2[[#This Row],[Stock_After]],"OK","Error") -> OK | AA85: =IF(ROUND(Table2[[#This Row],[Total_Value]],2)=ROUND(Table2[[#This Row],[Quantity]]*Table2[[#This Row],[Unit_Price]],2),"OK","Error") -> OK | AB85: =IF(Table2[[#This Row],[Transaction_Type]]="Purchase", IF(Table2[[#This Row],[Stock_After]]=Table2[[#This Row],[Stock_Before]]+Table2[[#This Row],[Quantity]], "OK", "Error"), IF(Table2[[#This Row],[Transaction_Type]]="Return", IF(Table2[[#This Row],[Stock_After]]=Table2[[#This Row],[Stock_Before]]+Table2[[#This Row],[Quantity]], "OK", "Error"), IF(Table2[[#This Row],[Transaction_Type]]="Sale", IF(Table2[[#This Row],[Stock_After]]=MAX(0, Table2[[#This Row],[Stock_Before]]-Table2[[#This Row],[Quantity]]), "OK", "Error"), IF(Table2[[#This Row],[Transaction_Type]]="Adjustment", IF(Table2[[#This Row],[Stock_After]]>=0, "OK", "Error"), "Check")))) -> OK | AC85: =IF(AND(Table2[[#This Row],[Quantity]]>=0,Table2[[#This Row],[Unit_Price]]>=0),"OK","Error") -> OK | AD85: =IF(Table2[[#This Row],[Stock_After]]=0,"Stock-Out",IF(Table2[[#This Row],[Stock_After]]<=10,"Low Stock","Healthy")) -> Healthy
A86: T00085 | B86: 46165 | C86: P006 | D86: Office Chair | E86: Furniture | F86: Chairs | G86: S010 | H86: W04 | I86: Purchase | J86: 21 | K86: 21664 | L86: 454944 | M86: 260 | N86: 281 | O86: E018 | Q86: Cash | R86: Pending | S86: Regular Transaction | T86: =IF(COUNTIF(T88,Q98)>1,"Duplicate","OK") -> OK | U86: =IF(Table2[[#This Row],[Transaction_ID]]="","Missing","OK") -> OK | V86: =IF(COUNTIF(Table2[[#This Row],[Product_ID]],Table2[[#This Row],[Product_ID]])=0,"Invalid Product","OK") -> OK | W86: =IF(COUNTIF(Table2[[#This Row],[Supplier_ID]],Table2[[#This Row],[Supplier_ID]])=0,"Invalid Supplier","OK") -> OK | X86: =IF(COUNTIF(Table2[[#This Row],[Warehouse_ID]],Table2[[#This Row],[Warehouse_ID]])=0,"Invalid Warehouse","OK") -> OK | Y86: =IF(COUNTIF(Table2[[#This Row],[Employee_ID]],Table2[[#This Row],[Employee_ID]])=0,"Invalid Employee","OK") -> OK | Z86: =IF(Table2[[#This Row],[Stock_After]]=Table2[[#This Row],[Stock_After]]+Table2[[#This Row],[Stock_After]]-Table2[[#This Row],[Stock_After]]-Table2[[#This Row],[Stock_After]]+Table2[[#This Row],[Stock_After]],"OK","Error") -> OK | AA86: =IF(ROUND(Table2[[#This Row],[Total_Value]],2)=ROUND(Table2[[#This Row],[Quantity]]*Table2[[#This Row],[Unit_Price]],2),"OK","Error") -> OK | AB86: =IF(Table2[[#This Row],[Transaction_Type]]="Purchase", IF(Table2[[#This Row],[Stock_After]]=Table2[[#This Row],[Stock_Before]]+Table2[[#This Row],[Quantity]], "OK", "Error"), IF(Table2[[#This Row],[Transaction_Type]]="Return", IF(Table2[[#This Row],[Stock_After]]=Table2[[#This Row],[Stock_Before]]+Table2[[#This Row],[Quantity]], "OK", "Error"), IF(Table2[[#This Row],[Transaction_Type]]="Sale", IF(Table2[[#This Row],[Stock_After]]=MAX(0, Table2[[#This Row],[Stock_Before]]-Table2[[#This Row],[Quantity]]), "OK", "Error"), IF(Table2[[#This Row],[Transaction_Type]]="Adjustment", IF(Table2[[#This Row],[Stock_After]]>=0, "OK", "Error"), "Check")))) -> OK | AC86: =IF(AND(Table2[[#This Row],[Quantity]]>=0,Table2[[#This Row],[Unit_Price]]>=0),"OK","Error") -> OK | AD86: =IF(Table2[[#This Row],[Stock_After]]=0,"Stock-Out",IF(Table2[[#This Row],[Stock_After]]<=10,"Low Stock","Healthy")) -> Healthy
A87: T00086 | B87: 46071 | C87: P008 | D87: Notebook | E87: Stationery | F87: Books | G87: S017 | H87: W01 | I87: Purchase | J87: 41 | K87: 16591 | L87: 680231 | M87: 215 | N87: 256 | O87: E018 | Q87: Credit | R87: Completed | S87: Regular Transaction | T87: =IF(COUNTIF(T89,Q99)>1,"Duplicate","OK") -> OK | U87: =IF(Table2[[#This Row],[Transaction_ID]]="","Missing","OK") -> OK | V87: =IF(COUNTIF(Table2[[#This Row],[Product_ID]],Table2[[#This Row],[Product_ID]])=0,"Invalid Product","OK") -> OK | W87: =IF(COUNTIF(Table2[[#This Row],[Supplier_ID]],Table2[[#This Row],[Supplier_ID]])=0,"Invalid Supplier","OK") -> OK | X87: =IF(COUNTIF(Table2[[#This Row],[Warehouse_ID]],Table2[[#This Row],[Warehouse_ID]])=0,"Invalid Warehouse","OK") -> OK | Y87: =IF(COUNTIF(Table2[[#This Row],[Employee_ID]],Table2[[#This Row],[Employee_ID]])=0,"Invalid Employee","OK") -> OK | Z87: =IF(Table2[[#This Row],[Stock_After]]=Table2[[#This Row],[Stock_After]]+Table2[[#This Row],[Stock_After]]-Table2[[#This Row],[Stock_After]]-Table2[[#This Row],[Stock_After]]+Table2[[#This Row],[Stock_After]],"OK","Error") -> OK | AA87: =IF(ROUND(Table2[[#This Row],[Total_Value]],2)=ROUND(Table2[[#This Row],[Quantity]]*Table2[[#This Row],[Unit_Price]],2),"OK","Error") -> OK | AB87: =IF(Table2[[#This Row],[Transaction_Type]]="Purchase", IF(Table2[[#This Row],[Stock_After]]=Table2[[#This Row],[Stock_Before]]+Table2[[#This Row],[Quantity]], "OK", "Error"), IF(Table2[[#This Row],[Transaction_Type]]="Return", IF(Table2[[#This Row],[Stock_After]]=Table2[[#This Row],[Stock_Before]]+Table2[[#This Row],[Quantity]], "OK", "Error"), IF(Table2[[#This Row],[Transaction_Type]]="Sale", IF(Table2[[#This Row],[Stock_After]]=MAX(0, Table2[[#This Row],[Stock_Before]]-Table2[[#This Row],[Quantity]]), "OK", "Error"), IF(Table2[[#This Row],[Transaction_Type]]="Adjustment", IF(Table2[[#This Row],[Stock_After]]>=0, "OK", "Error"), "Check")))) -> OK | AC87: =IF(AND(Table2[[#This Row],[Quantity]]>=0,Table2[[#This Row],[Unit_Price]]>=0),"OK","Error") -> OK | AD87: =IF(Table2[[#This Row],[Stock_After]]=0,"Stock-Out",IF(Table2[[#This Row],[Stock_After]]<=10,"Low Stock","Healthy")) -> Healthy
A88: T00087 | B88: 46168 | C88: P007 | D88: Office Desk | E88: Furniture | F88: Desks | G88: S015 | H88: W01 | I88: Purchase | J88: 25 | K88: 34026 | L88: 850650 | M88: 235 | N88: 260 | O88: E007 | Q88: UPI | R88: Pending | S88: Regular Transaction | T88: =IF(COUNTIF(T90,Q100)>1,"Duplicate","OK") -> OK | U88: =IF(Table2[[#This Row],[Transaction_ID]]="","Missing","OK") -> OK | V88: =IF(COUNTIF(Table2[[#This Row],[Product_ID]],Table2[[#This Row],[Product_ID]])=0,"Invalid Product","OK") -> OK | W88: =IF(COUNTIF(Table2[[#This Row],[Supplier_ID]],Table2[[#This Row],[Supplier_ID]])=0,"Invalid Supplier","OK") -> OK | X88: =IF(COUNTIF(Table2[[#This Row],[Warehouse_ID]],Table2[[#This Row],[Warehouse_ID]])=0,"Invalid Warehouse","OK") -> OK | Y88: =IF(COUNTIF(Table2[[#This Row],[Employee_ID]],Table2[[#This Row],[Employee_ID]])=0,"Invalid Employee","OK") -> OK | Z88: =IF(Table2[[#This Row],[Stock_After]]=Table2[[#This Row],[Stock_After]]+Table2[[#This Row],[Stock_After]]-Table2[[#This Row],[Stock_After]]-Table2[[#This Row],[Stock_After]]+Table2[[#This Row],[Stock_After]],"OK","Error") -> OK | AA88: =IF(ROUND(Table2[[#This Row],[Total_Value]],2)=ROUND(Table2[[#This Row],[Quantity]]*Table2[[#This Row],[Unit_Price]],2),"OK","Error") -> OK | AB88: =IF(Table2[[#This Row],[Transaction_Type]]="Purchase", IF(Table2[[#This Row],[Stock_After]]=Table2[[#This Row],[Stock_Before]]+Table2[[#This Row],[Quantity]], "OK", "Error"), IF(Table2[[#This Row],[Transaction_Type]]="Return", IF(Table2[[#This Row],[Stock_After]]=Table2[[#This Row],[Stock_Before]]+Table2[[#This Row],[Quantity]], "OK", "Error"), IF(Table2[[#This Row],[Transaction_Type]]="Sale", IF(Table2[[#This Row],[Stock_After]]=MAX(0, Table2[[#This Row],[Stock_Before]]-Table2[[#This Row],[Quantity]]), "OK", "Error"), IF(Table2[[#This Row],[Transaction_Type]]="Adjustment", IF(Table2[[#This Row],[Stock_After]]>=0, "OK", "Error"), "Check")))) -> OK | AC88: =IF(AND(Table2[[#This Row],[Quantity]]>=0,Table2[[#This Row],[Unit_Price]]>=0),"OK","Error") -> OK | AD88: =IF(Table2[[#This Row],[Stock_After]]=0,"Stock-Out",IF(Table2[[#This Row],[Stock_After]]<=10,"Low Stock","Healthy")) -> Healthy
A89: T00088 | B89: 45782 | C89: P009 | D89: Pen | E89: Stationery | F89: Writing | G89: S001 | H89: W05 | I89: Sale | J89: 37 | K89: 28762 | L89: 1064194 | M89: 500 | N89: 463 | O89: E008 | P89: C0358 | Q89: Card | R89: Approved | S89: Regular Transaction | T89: =IF(COUNTIF(T91,Q101)>1,"Duplicate","OK") -> OK | U89: =IF(Table2[[#This Row],[Transaction_ID]]="","Missing","OK") -> OK | V89: =IF(COUNTIF(Table2[[#This Row],[Product_ID]],Table2[[#This Row],[Product_ID]])=0,"Invalid Product","OK") -> OK | W89: =IF(COUNTIF(Table2[[#This Row],[Supplier_ID]],Table2[[#This Row],[Supplier_ID]])=0,"Invalid Supplier","OK") -> OK | X89: =IF(COUNTIF(Table2[[#This Row],[Warehouse_ID]],Table2[[#This Row],[Warehouse_ID]])=0,"Invalid Warehouse","OK") -> OK | Y89: =IF(COUNTIF(Table2[[#This Row],[Employee_ID]],Table2[[#This Row],[Employee_ID]])=0,"Invalid Employee","OK") -> OK | Z89: =IF(Table2[[#This Row],[Stock_After]]=Table2[[#This Row],[Stock_After]]+Table2[[#This Row],[Stock_After]]-Table2[[#This Row],[Stock_After]]-Table2[[#This Row],[Stock_After]]+Table2[[#This Row],[Stock_After]],"OK","Error") -> OK | AA89: =IF(ROUND(Table2[[#This Row],[Total_Value]],2)=ROUND(Table2[[#This Row],[Quantity]]*Table2[[#This Row],[Unit_Price]],2),"OK","Error") -> OK | AB89: =IF(Table2[[#This Row],[Transaction_Type]]="Purchase", IF(Table2[[#This Row],[Stock_After]]=Table2[[#This Row],[Stock_Before]]+Table2[[#This Row],[Quantity]], "OK", "Error"), IF(Table2[[#This Row],[Transaction_Type]]="Return", IF(Table2[[#This Row],[Stock_After]]=Table2[[#This Row],[Stock_Before]]+Table2[[#This Row],[Quantity]], "OK", "Error"), IF(Table2[[#This Row],[Transaction_Type]]="Sale", IF(Table2[[#This Row],[Stock_After]]=MAX(0, Table2[[#This Row],[Stock_Before]]-Table2[[#This Row],[Quantity]]), "OK", "Error"), IF(Table2[[#This Row],[Transaction_Type]]="Adjustment", IF(Table2[[#This Row],[Stock_After]]>=0, "OK", "Error"), "Check")))) -> OK | AC89: =IF(AND(Table2[[#This Row],[Quantity]]>=0,Table2[[#This Row],[Unit_Price]]>=0),"OK","Error") -> OK | AD89: =IF(Table2[[#This Row],[Stock_After]]=0,"Stock-Out",IF(Table2[[#This Row],[Stock_After]]<=10,"Low Stock","Healthy")) -> Healthy
